{
  "type": "Feature",
  "properties": {
    "gn:admin1_code":"LI",
    "gn:admin2_code":"803.0",
    "gn:admin3_code":"80302.0",
    "gn:asciiname":"Irlelo",
    "gn:country_code":"TL",
    "gn:dem":63,
    "gn:feature_class":"P",
    "gn:feature_code":"PPL",
    "gn:name":"Irlelo",
    "gn:population":0,
    "gn:timezone":"Asia/Dili",
    "iso:country":"TL",
    "wof:name":"Irlelo",
    "wof:placetype":"locality"
},
  "geometry": {"coordinates":[125.16694,-8.73222],"type":"Point"}
}