{
  "type": "Feature",
  "properties": {
    "gn:admin1_code":"ER",
    "gn:admin2_code":"705.0",
    "gn:admin3_code":"70507.0",
    "gn:asciiname":"Hatete",
    "gn:country_code":"TL",
    "gn:dem":1394,
    "gn:feature_class":"P",
    "gn:feature_code":"PPL",
    "gn:name":"Hatete",
    "gn:population":0,
    "gn:timezone":"Asia/Dili",
    "iso:country":"TL",
    "wof:name":"Hatete",
    "wof:placetype":"locality"
},
  "geometry": {"coordinates":[125.36888999999999,-8.77694],"type":"Point"}
}