{
  "type": "Feature",
  "properties": {
    "gn:admin1_code":"AN",
    "gn:admin2_code":"103.0",
    "gn:admin3_code":"10306.0",
    "gn:asciiname":"Fatubessi",
    "gn:country_code":"TL",
    "gn:dem":1411,
    "gn:feature_class":"P",
    "gn:feature_code":"PPL",
    "gn:name":"Fatubessi",
    "gn:population":0,
    "gn:timezone":"Asia/Dili",
    "iso:country":"TL",
    "name:deu_x_preferred":[
        "Fatubessi"
    ],
    "name:msa_x_preferred":[
        "Fatubessi"
    ],
    "name:tet_x_preferred":[
        "Fatubessi"
    ],
    "wof:name":"Fatubessi",
    "wof:placetype":"locality"
},
  "geometry": {"coordinates":[125.66417,-8.80306],"type":"Point"}
}