{
  "type": "Feature",
  "properties": {
    "gn:admin1_code":"OE",
    "gn:admin2_code":"1203.0",
    "gn:admin3_code":"120301.0",
    "gn:asciiname":"Afumalule",
    "gn:country_code":"TL",
    "gn:dem":359,
    "gn:feature_class":"P",
    "gn:feature_code":"PPL",
    "gn:name":"Afumalule",
    "gn:population":0,
    "gn:timezone":"Asia/Dili",
    "iso:country":"TL",
    "wof:name":"Afumalule",
    "wof:placetype":"locality"
},
  "geometry": {"coordinates":[124.37,-9.34111],"type":"Point"}
}