{
  "type": "Feature",
  "properties": {
    "gn:admin1_code":"MT",
    "gn:admin2_code":"1102.0",
    "gn:admin3_code":"110203.0",
    "gn:asciiname":"Cairui",
    "gn:country_code":"TL",
    "gn:dem":116,
    "gn:feature_class":"P",
    "gn:feature_code":"PPL",
    "gn:name":"Cairui",
    "gn:population":0,
    "gn:timezone":"Asia/Dili",
    "iso:country":"TL",
    "wof:name":"Cairui",
    "wof:placetype":"locality"
},
  "geometry": {"coordinates":[126.15000000000001,-8.61667],"type":"Point"}
}