{
  "type": "Feature",
  "properties": {
    "gn:admin1_code":"ER",
    "gn:admin2_code":"701.0",
    "gn:admin3_code":"70106.0",
    "gn:asciiname":"Dorema",
    "gn:country_code":"TL",
    "gn:dem":1107,
    "gn:feature_class":"P",
    "gn:feature_code":"PPL",
    "gn:name":"Dorema",
    "gn:population":0,
    "gn:timezone":"Asia/Dili",
    "iso:country":"TL",
    "wof:name":"Dorema",
    "wof:placetype":"locality"
},
  "geometry": {"coordinates":[125.50161,-8.68903],"type":"Point"}
}