{
  "type": "Feature",
  "properties": {
    "gn:admin1_code":"AN",
    "gn:admin2_code":"104.0",
    "gn:admin3_code":"10401.0",
    "gn:asciiname":"Luru",
    "gn:country_code":"TL",
    "gn:dem":443,
    "gn:feature_class":"P",
    "gn:feature_code":"PPL",
    "gn:name":"Luru",
    "gn:population":0,
    "gn:timezone":"Asia/Dili",
    "iso:country":"TL",
    "wof:name":"Luru",
    "wof:placetype":"locality"
},
  "geometry": {"coordinates":[125.58443,-9.1267],"type":"Point"}
}