{
  "type": "Feature",
  "properties": {
    "gn:admin1_code":"LA",
    "gn:admin2_code":"902.0",
    "gn:admin3_code":"90204.0",
    "gn:asciiname":"Barubatu",
    "gn:country_code":"TL",
    "gn:dem":14,
    "gn:feature_class":"P",
    "gn:feature_code":"PPL",
    "gn:name":"Barubatu",
    "gn:population":0,
    "gn:timezone":"Asia/Dili",
    "iso:country":"TL",
    "wof:name":"Barubatu",
    "wof:placetype":"locality"
},
  "geometry": {"coordinates":[126.74167,-8.41222],"type":"Point"}
}