{
  "type": "Feature",
  "properties": {
    "gn:admin1_code":"ER",
    "gn:admin2_code":"703.0",
    "gn:admin3_code":"70302.0",
    "gn:asciiname":"Riamori",
    "gn:country_code":"TL",
    "gn:dem":1127,
    "gn:feature_class":"P",
    "gn:feature_code":"PPL",
    "gn:name":"Riamori",
    "gn:population":0,
    "gn:timezone":"Asia/Dili",
    "iso:country":"TL",
    "wof:name":"Riamori",
    "wof:placetype":"locality"
},
  "geometry": {"coordinates":[125.43472,-8.85778],"type":"Point"}
}