{
  "type": "Feature",
  "properties": {
    "gn:admin1_code":"BO",
    "gn:admin2_code":"402.0",
    "gn:admin3_code":"40206.0",
    "gn:asciiname":"Gerotete",
    "gn:country_code":"TL",
    "gn:dem":291,
    "gn:feature_class":"P",
    "gn:feature_code":"PPL",
    "gn:name":"Gerotete",
    "gn:population":0,
    "gn:timezone":"Asia/Dili",
    "iso:country":"TL",
    "wof:name":"Gerotete",
    "wof:placetype":"locality"
},
  "geometry": {"coordinates":[125.26443999999999,-8.88417],"type":"Point"}
}