{
  "type": "Feature",
  "properties": {
    "gn:admin1_code":"CO",
    "gn:admin2_code":"503.0",
    "gn:admin3_code":"50302.0",
    "gn:asciiname":"Laktos",
    "gn:country_code":"TL",
    "gn:dem":1111,
    "gn:feature_class":"P",
    "gn:feature_code":"PPL",
    "gn:name":"Laktos",
    "gn:population":0,
    "gn:timezone":"Asia/Dili",
    "iso:country":"TL",
    "wof:name":"Laktos",
    "wof:placetype":"locality"
},
  "geometry": {"coordinates":[125.095,-9.24639],"type":"Point"}
}