{
  "type": "Feature",
  "properties": {
    "gn:admin1_code":"AN",
    "gn:admin2_code":"103.0",
    "gn:admin3_code":"10304.0",
    "gn:asciiname":"Aihou",
    "gn:country_code":"TL",
    "gn:dem":1743,
    "gn:feature_class":"P",
    "gn:feature_code":"PPL",
    "gn:name":"Aihou",
    "gn:population":0,
    "gn:timezone":"Asia/Dili",
    "iso:country":"TL",
    "wof:name":"Aihou",
    "wof:placetype":"locality"
},
  "geometry": {"coordinates":[125.59028000000001,-8.87583],"type":"Point"}
}