{
  "type": "Feature",
  "properties": {
    "gn:admin1_code":"ER",
    "gn:admin2_code":"703.0",
    "gn:admin3_code":"70303.0",
    "gn:asciiname":"Leubasa",
    "gn:country_code":"TL",
    "gn:dem":1614,
    "gn:feature_class":"P",
    "gn:feature_code":"PPL",
    "gn:name":"Leubasa",
    "gn:population":0,
    "gn:timezone":"Asia/Dili",
    "iso:country":"TL",
    "wof:name":"Leubasa",
    "wof:placetype":"locality"
},
  "geometry": {"coordinates":[125.42528,-8.8925],"type":"Point"}
}