{
  "type": "Feature",
  "properties": {
    "gn:admin1_code":"BO",
    "gn:admin2_code":"406.0",
    "gn:admin3_code":"40617.0",
    "gn:asciiname":"Bugas",
    "gn:country_code":"TL",
    "gn:dem":758,
    "gn:feature_class":"P",
    "gn:feature_code":"PPL",
    "gn:name":"Bugas",
    "gn:population":0,
    "gn:timezone":"Asia/Dili",
    "iso:country":"TL",
    "wof:name":"Bugas",
    "wof:placetype":"locality"
},
  "geometry": {"coordinates":[125.37222,-9.01556],"type":"Point"}
}