{
  "type": "Feature",
  "properties": {
    "gn:admin1_code":"DI",
    "gn:admin2_code":"606.0",
    "gn:admin3_code":"60605.0",
    "gn:asciiname":"Fatuloda",
    "gn:country_code":"TL",
    "gn:dem":654,
    "gn:feature_class":"P",
    "gn:feature_code":"PPL",
    "gn:name":"Fatuloda",
    "gn:population":0,
    "gn:timezone":"Asia/Dili",
    "iso:country":"TL",
    "wof:name":"Fatuloda",
    "wof:placetype":"locality"
},
  "geometry": {"coordinates":[125.59139,-8.59972],"type":"Point"}
}