{
  "type": "Feature",
  "properties": {
    "gn:admin1_code":"BO",
    "gn:admin2_code":"402.0",
    "gn:admin3_code":"40208.0",
    "gn:asciiname":"Manapa",
    "gn:country_code":"TL",
    "gn:dem":360,
    "gn:feature_class":"P",
    "gn:feature_code":"PPL",
    "gn:name":"Manapa",
    "gn:population":0,
    "gn:timezone":"Asia/Dili",
    "iso:country":"TL",
    "wof:name":"Manapa",
    "wof:placetype":"locality"
},
  "geometry": {"coordinates":[125.23333,-8.96667],"type":"Point"}
}