{
  "type": "Feature",
  "properties": {
    "gn:admin1_code":"MF",
    "gn:admin2_code":"1003.0",
    "gn:admin3_code":"100304.0",
    "gn:asciiname":"Fatucahi",
    "gn:country_code":"TL",
    "gn:dem":41,
    "gn:feature_class":"P",
    "gn:feature_code":"PPL",
    "gn:name":"Fatucahi",
    "gn:population":0,
    "gn:timezone":"Asia/Dili",
    "iso:country":"TL",
    "wof:name":"Fatucahi",
    "wof:placetype":"locality"
},
  "geometry": {"coordinates":[125.98677000000001,-9.03514],"type":"Point"}
}