{
  "type": "Feature",
  "properties": {
    "gn:admin1_code":"DI",
    "gn:admin2_code":"604.0",
    "gn:admin3_code":"60404.0",
    "gn:asciiname":"Berau",
    "gn:country_code":"TL",
    "gn:dem":145,
    "gn:feature_class":"P",
    "gn:feature_code":"PPL",
    "gn:name":"Berau",
    "gn:population":0,
    "gn:timezone":"Asia/Dili",
    "iso:country":"TL",
    "name:als_x_preferred":[
        "Berau"
    ],
    "name:deu_x_preferred":[
        "Berau"
    ],
    "name:ind_x_preferred":[
        "Berau"
    ],
    "name:und_x_variant":[
        "Maquedade",
        "Makadade",
        "Mascadade",
        "Macadade"
    ],
    "wof:name":"Berau",
    "wof:placetype":"locality"
},
  "geometry": {"coordinates":[125.55833,-8.29667],"type":"Point"}
}