{
  "type": "Feature",
  "properties": {
    "gn:admin1_code":"LA",
    "gn:admin2_code":"903.0",
    "gn:admin3_code":"90304.0",
    "gn:asciiname":"Lliomar",
    "gn:country_code":"TL",
    "gn:dem":346,
    "gn:feature_class":"P",
    "gn:feature_code":"PPL",
    "gn:name":"Lliomar",
    "gn:population":0,
    "gn:timezone":"Asia/Dili",
    "iso:country":"TL",
    "wof:name":"Lliomar",
    "wof:placetype":"locality"
},
  "geometry": {"coordinates":[126.83333,-8.71667],"type":"Point"}
}