{
  "type": "Feature",
  "properties": {
    "gn:admin1_code":"LI",
    "gn:admin2_code":"801.0",
    "gn:admin3_code":"80107.0",
    "gn:asciiname":"Urluli",
    "gn:country_code":"TL",
    "gn:dem":1132,
    "gn:feature_class":"P",
    "gn:feature_code":"PPL",
    "gn:name":"Urluli",
    "gn:population":0,
    "gn:timezone":"Asia/Dili",
    "iso:country":"TL",
    "wof:name":"Urluli",
    "wof:placetype":"locality"
},
  "geometry": {"coordinates":[125.37694,-8.68361],"type":"Point"}
}