{
  "type": "Feature",
  "properties": {
    "gn:admin1_code":"ER",
    "gn:admin2_code":"705.0",
    "gn:admin3_code":"70513.0",
    "gn:asciiname":"Fatubessi",
    "gn:country_code":"TL",
    "gn:dem":1029,
    "gn:feature_class":"P",
    "gn:feature_code":"PPL",
    "gn:name":"Fatubessi",
    "gn:population":0,
    "gn:timezone":"Asia/Dili",
    "iso:country":"TL",
    "name:deu_x_preferred":[
        "Fatubessi"
    ],
    "name:msa_x_preferred":[
        "Fatubessi"
    ],
    "name:tet_x_preferred":[
        "Fatubessi"
    ],
    "name:und_x_variant":[
        "Fatu Besi",
        "Fatubessi"
    ],
    "wof:name":"Fatubessi",
    "wof:placetype":"locality"
},
  "geometry": {"coordinates":[125.32611,-8.74833],"type":"Point"}
}