{
  "type": "Feature",
  "properties": {
    "gn:admin1_code":"VI",
    "gn:admin2_code":"1302.0",
    "gn:admin3_code":"130204.0",
    "gn:asciiname":"Borala",
    "gn:country_code":"TL",
    "gn:dem":608,
    "gn:feature_class":"P",
    "gn:feature_code":"PPL",
    "gn:name":"Borala",
    "gn:population":0,
    "gn:timezone":"Asia/Dili",
    "iso:country":"TL",
    "wof:name":"Borala",
    "wof:placetype":"locality"
},
  "geometry": {"coordinates":[126.38194,-8.75167],"type":"Point"}
}