{
  "type": "Feature",
  "properties": {
    "gn:admin1_code":"MT",
    "gn:admin2_code":"1104.0",
    "gn:admin3_code":"110405.0",
    "gn:asciiname":"Manufahe",
    "gn:country_code":"TL",
    "gn:dem":624,
    "gn:feature_class":"P",
    "gn:feature_code":"PPL",
    "gn:name":"Manufahe",
    "gn:population":0,
    "gn:timezone":"Asia/Dili",
    "iso:country":"TL",
    "wof:name":"Manufahe",
    "wof:placetype":"locality"
},
  "geometry": {"coordinates":[125.92167000000001,-8.83111],"type":"Point"}
}