{
  "type": "Feature",
  "properties": {
    "gn:admin1_code":"ER",
    "gn:admin2_code":"704.0",
    "gn:admin3_code":"70412.0",
    "gn:asciiname":"Raelau",
    "gn:country_code":"TL",
    "gn:dem":1291,
    "gn:feature_class":"P",
    "gn:feature_code":"PPL",
    "gn:name":"Raelau",
    "gn:population":0,
    "gn:timezone":"Asia/Dili",
    "iso:country":"TL",
    "wof:name":"Raelau",
    "wof:placetype":"locality"
},
  "geometry": {"coordinates":[125.41806,-8.89972],"type":"Point"}
}