{
  "type": "Feature",
  "properties": {
    "gn:admin1_code":"BA",
    "gn:admin2_code":"302.0",
    "gn:admin3_code":"30205.0",
    "gn:asciiname":"Auraba",
    "gn:country_code":"TL",
    "gn:dem":455,
    "gn:feature_class":"P",
    "gn:feature_code":"PPL",
    "gn:name":"Auraba",
    "gn:population":0,
    "gn:timezone":"Asia/Dili",
    "iso:country":"TL",
    "wof:name":"Auraba",
    "wof:placetype":"locality"
},
  "geometry": {"coordinates":[126.70583000000001,-8.51778],"type":"Point"}
}