{
  "type": "Feature",
  "properties": {
    "gn:admin1_code":"VI",
    "gn:admin2_code":"1302.0",
    "gn:admin3_code":"130201.0",
    "gn:asciiname":"Munidailo",
    "gn:country_code":"TL",
    "gn:dem":377,
    "gn:feature_class":"P",
    "gn:feature_code":"PPL",
    "gn:name":"Munidailo",
    "gn:population":0,
    "gn:timezone":"Asia/Dili",
    "iso:country":"TL",
    "wof:name":"Munidailo",
    "wof:placetype":"locality"
},
  "geometry": {"coordinates":[126.48278000000001,-8.64833],"type":"Point"}
}