{
  "type": "Feature",
  "properties": {
    "gn:admin1_code":"DI",
    "gn:admin2_code":"606.0",
    "gn:admin3_code":"60604.0",
    "gn:asciiname":"Akanunu",
    "gn:country_code":"TL",
    "gn:dem":47,
    "gn:feature_class":"P",
    "gn:feature_code":"PPL",
    "gn:name":"Akanunu",
    "gn:population":0,
    "gn:timezone":"Asia/Dili",
    "iso:country":"TL",
    "wof:name":"Akanunu",
    "wof:placetype":"locality"
},
  "geometry": {"coordinates":[125.64897999999999,-8.55689],"type":"Point"}
}