{
  "type": "Feature",
  "properties": {
    "gn:admin1_code":"BO",
    "gn:admin2_code":"405.0",
    "gn:admin3_code":"40502.0",
    "gn:asciiname":"Ames",
    "gn:country_code":"TL",
    "gn:dem":617,
    "gn:feature_class":"P",
    "gn:feature_code":"PPL",
    "gn:name":"Ames",
    "gn:population":0,
    "gn:timezone":"Asia/Dili",
    "iso:country":"TL",
    "wof:name":"Ames",
    "wof:placetype":"locality"
},
  "geometry": {"coordinates":[125.27972,-9.15917],"type":"Point"}
}