{
  "type": "Feature",
  "properties": {
    "gn:admin1_code":"BO",
    "gn:admin2_code":"405.0",
    "gn:admin3_code":"40502.0",
    "gn:asciiname":"Ames",
    "gn:country_code":"TL",
    "gn:dem":617,
    "gn:feature_class":"P",
    "gn:feature_code":"PPL",
    "gn:name":"Ames",
    "gn:population":0,
    "gn:timezone":"Asia/Dili",
    "iso:country":"TL",
    "name:bre_x_preferred":[
        "Ames"
    ],
    "name:cat_x_preferred":[
        "Ames"
    ],
    "name:ceb_x_preferred":[
        "Ames"
    ],
    "name:deu_x_preferred":[
        "Ames"
    ],
    "name:eus_x_preferred":[
        "Ames"
    ],
    "name:fra_x_preferred":[
        "Ames"
    ],
    "name:glg_x_preferred":[
        "Ames"
    ],
    "name:heb_x_preferred":[
        "\u05d0\u05d9\u05d9\u05de\u05e1"
    ],
    "name:hun_x_preferred":[
        "Ames"
    ],
    "name:ita_x_preferred":[
        "Ames"
    ],
    "name:jpn_x_preferred":[
        "\u30a8\u30a4\u30e0\u30ba"
    ],
    "name:kor_x_preferred":[
        "\uc5d0\uc784\uc2a4"
    ],
    "name:msa_x_preferred":[
        "Ames"
    ],
    "name:nld_x_preferred":[
        "Ames"
    ],
    "name:oci_x_preferred":[
        "Ames"
    ],
    "name:pol_x_preferred":[
        "Ames"
    ],
    "name:por_x_preferred":[
        "Ames"
    ],
    "name:rus_x_preferred":[
        "\u042d\u0439\u043c\u0441"
    ],
    "name:sco_x_preferred":[
        "Ames"
    ],
    "name:spa_x_preferred":[
        "Ames"
    ],
    "name:srp_x_preferred":[
        "\u0415\u0458\u043c\u0441"
    ],
    "name:swe_x_preferred":[
        "Ames"
    ],
    "name:tha_x_preferred":[
        "\u0e40\u0e2d\u0e21\u0e2a\u0e4c"
    ],
    "name:ukr_x_preferred":[
        "\u0415\u0439\u043c\u0441"
    ],
    "name:uzb_x_preferred":[
        "Ames"
    ],
    "name:vie_x_preferred":[
        "Ames"
    ],
    "name:vol_x_preferred":[
        "Ames"
    ],
    "name:war_x_preferred":[
        "Ames"
    ],
    "wof:name":"Ames",
    "wof:placetype":"locality"
},
  "geometry": {"coordinates":[125.27972,-9.15917],"type":"Point"}
}