{
  "type": "Feature",
  "properties": {
    "gn:admin1_code":"LA",
    "gn:admin2_code":"902.0",
    "gn:admin3_code":"90207.0",
    "gn:asciiname":"Laikara",
    "gn:country_code":"TL",
    "gn:dem":368,
    "gn:feature_class":"P",
    "gn:feature_code":"PPL",
    "gn:name":"Laikara",
    "gn:population":0,
    "gn:timezone":"Asia/Dili",
    "iso:country":"TL",
    "wof:name":"Laikara",
    "wof:placetype":"locality"
},
  "geometry": {"coordinates":[126.87166999999999,-8.44278],"type":"Point"}
}