{
  "type": "Feature",
  "properties": {
    "gn:admin1_code":"OE",
    "gn:admin2_code":"1201.0",
    "gn:admin3_code":"120103.0",
    "gn:asciiname":"Kiumina",
    "gn:country_code":"TL",
    "gn:dem":62,
    "gn:feature_class":"P",
    "gn:feature_code":"PPL",
    "gn:name":"Kiumina",
    "gn:population":0,
    "gn:timezone":"Asia/Dili",
    "iso:country":"TL",
    "wof:name":"Kiumina",
    "wof:placetype":"locality"
},
  "geometry": {"coordinates":[124.35861,-9.26611],"type":"Point"}
}