{
  "type": "Feature",
  "properties": {
    "gn:admin1_code":"LI",
    "gn:admin2_code":"803.0",
    "gn:admin3_code":"80302.0",
    "gn:asciiname":"Goulete",
    "gn:country_code":"TL",
    "gn:dem":39,
    "gn:feature_class":"P",
    "gn:feature_code":"PPL",
    "gn:name":"Goulete",
    "gn:population":0,
    "gn:timezone":"Asia/Dili",
    "iso:country":"TL",
    "wof:name":"Goulete",
    "wof:placetype":"locality"
},
  "geometry": {"coordinates":[125.17972,-8.74306],"type":"Point"}
}