{
  "type": "Feature",
  "properties": {
    "gn:admin1_code":"CO",
    "gn:admin2_code":"505.0",
    "gn:admin3_code":"50502.0",
    "gn:asciiname":"Fatukoan",
    "gn:country_code":"TL",
    "gn:dem":36,
    "gn:feature_class":"P",
    "gn:feature_code":"PPL",
    "gn:name":"Fatukoan",
    "gn:population":0,
    "gn:timezone":"Asia/Dili",
    "iso:country":"TL",
    "wof:name":"Fatukoan",
    "wof:placetype":"locality"
},
  "geometry": {"coordinates":[125.20305999999999,-9.3425],"type":"Point"}
}