{
  "type": "Feature",
  "properties": {
    "gn:admin1_code":"DI",
    "gn:admin2_code":"601.0",
    "gn:admin3_code":"60106.0",
    "gn:asciiname":"Motael",
    "gn:country_code":"TL",
    "gn:dem":6,
    "gn:feature_class":"P",
    "gn:feature_code":"PPL",
    "gn:name":"Motael",
    "gn:population":0,
    "gn:timezone":"Asia/Dili",
    "iso:country":"TL",
    "wof:name":"Motael",
    "wof:placetype":"locality"
},
  "geometry": {"coordinates":[125.56667,-8.55],"type":"Point"}
}