{
  "type": "Feature",
  "properties": {
    "gn:admin1_code":"ER",
    "gn:admin2_code":"702.0",
    "gn:admin3_code":"70206.0",
    "gn:asciiname":"Borohei",
    "gn:country_code":"TL",
    "gn:dem":1296,
    "gn:feature_class":"P",
    "gn:feature_code":"PPL",
    "gn:name":"Borohei",
    "gn:population":0,
    "gn:timezone":"Asia/Dili",
    "iso:country":"TL",
    "wof:name":"Borohei",
    "wof:placetype":"locality"
},
  "geometry": {"coordinates":[125.43333,-8.76667],"type":"Point"}
}