{
  "type": "Feature",
  "properties": {
    "gn:admin1_code":"CO",
    "gn:admin2_code":"502.0",
    "gn:admin3_code":"50201.0",
    "gn:asciiname":"Dato Rua",
    "gn:country_code":"TL",
    "gn:dem":909,
    "gn:feature_class":"P",
    "gn:feature_code":"PPL",
    "gn:name":"Dato Rua",
    "gn:population":0,
    "gn:timezone":"Asia/Dili",
    "iso:country":"TL",
    "wof:name":"Dato Rua",
    "wof:placetype":"locality"
},
  "geometry": {"coordinates":[125.05583,-9.23123],"type":"Point"}
}