{
  "type": "Feature",
  "properties": {
    "gn:admin1_code":"MT",
    "gn:admin2_code":"1101.0",
    "gn:admin3_code":"110103.0",
    "gn:asciiname":"Aitehen",
    "gn:country_code":"TL",
    "gn:dem":3,
    "gn:feature_class":"P",
    "gn:feature_code":"PPL",
    "gn:name":"Aitehen",
    "gn:population":0,
    "gn:timezone":"Asia/Dili",
    "iso:country":"TL",
    "wof:name":"Aitehen",
    "wof:placetype":"locality"
},
  "geometry": {"coordinates":[126.03055999999999,-8.51278],"type":"Point"}
}