{
  "type": "Feature",
  "properties": {
    "gn:admin1_code":"ER",
    "gn:admin2_code":"703.0",
    "gn:admin3_code":"70301.0",
    "gn:asciiname":"Eratoi",
    "gn:country_code":"TL",
    "gn:dem":1774,
    "gn:feature_class":"P",
    "gn:feature_code":"PPL",
    "gn:name":"Eratoi",
    "gn:population":0,
    "gn:timezone":"Asia/Dili",
    "iso:country":"TL",
    "wof:name":"Eratoi",
    "wof:placetype":"locality"
},
  "geometry": {"coordinates":[125.48972000000001,-8.83889],"type":"Point"}
}