{
  "type": "Feature",
  "properties": {
    "gn:admin1_code":"CO",
    "gn:admin2_code":"507.0",
    "gn:admin3_code":"50704.0",
    "gn:asciiname":"Zulotos",
    "gn:country_code":"TL",
    "gn:dem":499,
    "gn:feature_class":"P",
    "gn:feature_code":"PPL",
    "gn:name":"Zulotos",
    "gn:population":0,
    "gn:timezone":"Asia/Dili",
    "iso:country":"TL",
    "wof:name":"Zulotos",
    "wof:placetype":"locality"
},
  "geometry": {"coordinates":[125.41153,-9.11434],"type":"Point"}
}