{
  "type": "Feature",
  "properties": {
    "gn:admin1_code":"AN",
    "gn:admin2_code":"104.0",
    "gn:admin3_code":"10402.0",
    "gn:asciiname":"Fatukabelak",
    "gn:country_code":"TL",
    "gn:dem":71,
    "gn:feature_class":"P",
    "gn:feature_code":"PPL",
    "gn:name":"Fatukabelak",
    "gn:population":0,
    "gn:timezone":"Asia/Dili",
    "iso:country":"TL",
    "wof:name":"Fatukabelak",
    "wof:placetype":"locality"
},
  "geometry": {"coordinates":[125.65719,-9.14568],"type":"Point"}
}