{
  "type": "Feature",
  "properties": {
    "gn:admin1_code":"MF",
    "gn:admin2_code":"1001.0",
    "gn:admin3_code":"100102.0",
    "gn:asciiname":"Deunai",
    "gn:country_code":"TL",
    "gn:dem":997,
    "gn:feature_class":"P",
    "gn:feature_code":"PPL",
    "gn:name":"Deunai",
    "gn:population":0,
    "gn:timezone":"Asia/Dili",
    "iso:country":"TL",
    "wof:name":"Deunai",
    "wof:placetype":"locality"
},
  "geometry": {"coordinates":[125.66194,-8.90667],"type":"Point"}
}