{
  "type": "Feature",
  "properties": {
    "gn:admin1_code":"BO",
    "gn:admin2_code":"401.0",
    "gn:admin3_code":"40103.0",
    "gn:asciiname":"Lugululi",
    "gn:country_code":"TL",
    "gn:dem":310,
    "gn:feature_class":"P",
    "gn:feature_code":"PPL",
    "gn:name":"Lugululi",
    "gn:population":0,
    "gn:timezone":"Asia/Dili",
    "iso:country":"TL",
    "wof:name":"Lugululi",
    "wof:placetype":"locality"
},
  "geometry": {"coordinates":[125.23111000000002,-8.97139],"type":"Point"}
}