{
  "type": "Feature",
  "properties": {
    "gn:admin1_code":"BA",
    "gn:asciiname":"Binagua",
    "gn:country_code":"TL",
    "gn:dem":10,
    "gn:feature_class":"P",
    "gn:feature_code":"PPL",
    "gn:name":"Binagua",
    "gn:population":0,
    "gn:timezone":"Asia/Dili",
    "iso:country":"TL",
    "wof:name":"Binagua",
    "wof:placetype":"locality"
},
  "geometry": {"coordinates":[126.68015,-8.43147],"type":"Point"}
}