{
  "type": "Feature",
  "properties": {
    "gn:admin1_code":"LA",
    "gn:admin2_code":"905.0",
    "gn:admin3_code":"90501.0",
    "gn:asciiname":"Malahara",
    "gn:country_code":"TL",
    "gn:dem":344,
    "gn:feature_class":"P",
    "gn:feature_code":"PPL",
    "gn:name":"Malahara",
    "gn:population":0,
    "gn:timezone":"Asia/Dili",
    "iso:country":"TL",
    "wof:name":"Malahara",
    "wof:placetype":"locality"
},
  "geometry": {"coordinates":[127.13972,-8.47306],"type":"Point"}
}