{
  "type": "Feature",
  "properties": {
    "gn:admin1_code":"ER",
    "gn:admin2_code":"705.0",
    "gn:admin3_code":"70509.0",
    "gn:asciiname":"Hatulialete",
    "gn:country_code":"TL",
    "gn:dem":372,
    "gn:feature_class":"P",
    "gn:feature_code":"PPL",
    "gn:name":"Hatulialete",
    "gn:population":0,
    "gn:timezone":"Asia/Dili",
    "iso:country":"TL",
    "wof:name":"Hatulialete",
    "wof:placetype":"locality"
},
  "geometry": {"coordinates":[125.29861,-8.71778],"type":"Point"}
}