{
  "type": "Feature",
  "properties": {
    "gn:admin1_code":"OE",
    "gn:admin2_code":"1202.0",
    "gn:admin3_code":"120202.0",
    "gn:asciiname":"Naktuka",
    "gn:country_code":"TL",
    "gn:dem":19,
    "gn:feature_class":"P",
    "gn:feature_code":"PPL",
    "gn:name":"Naktuka",
    "gn:population":0,
    "gn:timezone":"Asia/Dili",
    "iso:country":"TL",
    "wof:name":"Naktuka",
    "wof:placetype":"locality"
},
  "geometry": {"coordinates":[124.06974,-9.34365],"type":"Point"}
}