{
  "type": "Feature",
  "properties": {
    "gn:admin1_code":"LA",
    "gn:admin2_code":"903.0",
    "gn:admin3_code":"90302.0",
    "gn:asciiname":"Hamahun",
    "gn:country_code":"TL",
    "gn:dem":531,
    "gn:feature_class":"P",
    "gn:feature_code":"PPL",
    "gn:name":"Hamahun",
    "gn:population":0,
    "gn:timezone":"Asia/Dili",
    "iso:country":"TL",
    "wof:name":"Hamahun",
    "wof:placetype":"locality"
},
  "geometry": {"coordinates":[126.825,-8.64361],"type":"Point"}
}