{
  "type": "Feature",
  "properties": {
    "gn:admin1_code":"CO",
    "gn:admin2_code":"502.0",
    "gn:admin3_code":"50202.0",
    "gn:asciiname":"Manekiik",
    "gn:country_code":"TL",
    "gn:dem":937,
    "gn:feature_class":"P",
    "gn:feature_code":"PPL",
    "gn:name":"Manekiik",
    "gn:population":0,
    "gn:timezone":"Asia/Dili",
    "iso:country":"TL",
    "wof:name":"Manekiik",
    "wof:placetype":"locality"
},
  "geometry": {"coordinates":[124.99666999999999,-9.25278],"type":"Point"}
}