{
  "type": "Feature",
  "properties": {
    "gn:admin1_code":"LI",
    "gn:admin2_code":"801.0",
    "gn:admin3_code":"80107.0",
    "gn:asciiname":"Fatuhou",
    "gn:country_code":"TL",
    "gn:dem":1085,
    "gn:feature_class":"P",
    "gn:feature_code":"PPL",
    "gn:name":"Fatuhou",
    "gn:population":0,
    "gn:timezone":"Asia/Dili",
    "iso:country":"TL",
    "wof:name":"Fatuhou",
    "wof:placetype":"locality"
},
  "geometry": {"coordinates":[125.36861,-8.68222],"type":"Point"}
}