{
  "type": "Feature",
  "properties": {
    "gn:admin1_code":"VI",
    "gn:admin2_code":"1304.0",
    "gn:admin3_code":"130405.0",
    "gn:asciiname":"Maluro",
    "gn:country_code":"TL",
    "gn:dem":6,
    "gn:feature_class":"P",
    "gn:feature_code":"PPL",
    "gn:name":"Maluro",
    "gn:population":0,
    "gn:timezone":"Asia/Dili",
    "iso:country":"TL",
    "wof:name":"Maluro",
    "wof:placetype":"locality"
},
  "geometry": {"coordinates":[126.45056,-8.94583],"type":"Point"}
}