{
  "type": "Feature",
  "properties": {
    "gn:admin1_code":"BO",
    "gn:admin2_code":"404.0",
    "gn:admin3_code":"40402.0",
    "gn:asciiname":"Vila Maria",
    "gn:country_code":"TL",
    "gn:dem":483,
    "gn:feature_class":"P",
    "gn:feature_code":"PPL",
    "gn:name":"Vila Maria",
    "gn:population":0,
    "gn:timezone":"Asia/Dili",
    "iso:country":"TL",
    "name:war_x_preferred":[
        "Vila Maria"
    ],
    "wof:name":"Vila Maria",
    "wof:placetype":"locality"
},
  "geometry": {"coordinates":[125.16667,-8.81667],"type":"Point"}
}