{
  "type": "Feature",
  "properties": {
    "gn:admin1_code":"AN",
    "gn:admin2_code":"104.0",
    "gn:admin3_code":"10402.0",
    "gn:asciiname":"Beko",
    "gn:country_code":"TL",
    "gn:dem":158,
    "gn:feature_class":"P",
    "gn:feature_code":"PPL",
    "gn:name":"Beko",
    "gn:population":0,
    "gn:timezone":"Asia/Dili",
    "iso:country":"TL",
    "wof:name":"Beko",
    "wof:placetype":"locality"
},
  "geometry": {"coordinates":[125.68333,-9.10194],"type":"Point"}
}