{
  "type": "Feature",
  "properties": {
    "gn:admin1_code":"AN",
    "gn:admin2_code":"104.0",
    "gn:admin3_code":"10402.0",
    "gn:asciiname":"Beko",
    "gn:country_code":"TL",
    "gn:dem":158,
    "gn:feature_class":"P",
    "gn:feature_code":"PPL",
    "gn:name":"Beko",
    "gn:population":0,
    "gn:timezone":"Asia/Dili",
    "iso:country":"TL",
    "name:ara_x_preferred":[
        "\u0628\u064a\u0643\u0648"
    ],
    "name:aze_x_preferred":[
        "Beko"
    ],
    "name:deu_x_preferred":[
        "Beko Deutschland"
    ],
    "name:ell_x_preferred":[
        "Beko"
    ],
    "name:fas_x_preferred":[
        "\u0628\u06a9\u0648"
    ],
    "name:fra_x_preferred":[
        "Beko"
    ],
    "name:heb_x_preferred":[
        "Beko"
    ],
    "name:hun_x_preferred":[
        "Beko"
    ],
    "name:ita_x_preferred":[
        "Beko"
    ],
    "name:kat_x_preferred":[
        "\u10d1\u10d4\u10d9\u10dd"
    ],
    "name:nld_x_preferred":[
        "Beko"
    ],
    "name:pol_x_preferred":[
        "Beko"
    ],
    "name:rus_x_preferred":[
        "Beko"
    ],
    "name:tur_x_preferred":[
        "Beko"
    ],
    "wof:name":"Beko",
    "wof:placetype":"locality"
},
  "geometry": {"coordinates":[125.68333,-9.10194],"type":"Point"}
}