{
  "type": "Feature",
  "properties": {
    "gn:admin1_code":"BO",
    "gn:admin2_code":"406.0",
    "gn:admin3_code":"40613.0",
    "gn:asciiname":"Mologuenglana",
    "gn:country_code":"TL",
    "gn:dem":1226,
    "gn:feature_class":"P",
    "gn:feature_code":"PPL",
    "gn:name":"Mologuenglana",
    "gn:population":0,
    "gn:timezone":"Asia/Dili",
    "iso:country":"TL",
    "wof:name":"Mologuenglana",
    "wof:placetype":"locality"
},
  "geometry": {"coordinates":[125.27491999999999,-9.04869],"type":"Point"}
}