{
  "type": "Feature",
  "properties": {
    "gn:admin1_code":"BO",
    "gn:admin2_code":"405.0",
    "gn:admin3_code":"40504.0",
    "gn:asciiname":"Ifililig",
    "gn:country_code":"TL",
    "gn:dem":1044,
    "gn:feature_class":"P",
    "gn:feature_code":"PPL",
    "gn:name":"Ifililig",
    "gn:population":0,
    "gn:timezone":"Asia/Dili",
    "iso:country":"TL",
    "name:und_x_variant":[
        "Itililig"
    ],
    "wof:name":"Ifililig",
    "wof:placetype":"locality"
},
  "geometry": {"coordinates":[125.26220000000001,-9.13996],"type":"Point"}
}