{
  "type": "Feature",
  "properties": {
    "gn:admin1_code":"BA",
    "gn:admin2_code":"301.0",
    "gn:admin3_code":"30101.0",
    "gn:asciiname":"Roulu",
    "gn:country_code":"TL",
    "gn:dem":309,
    "gn:feature_class":"P",
    "gn:feature_code":"PPL",
    "gn:name":"Roulu",
    "gn:population":0,
    "gn:timezone":"Asia/Dili",
    "iso:country":"TL",
    "name:und_x_variant":[
        "Ro-Ulo"
    ],
    "wof:name":"Roulu",
    "wof:placetype":"locality"
},
  "geometry": {"coordinates":[126.44893999999999,-8.45837],"type":"Point"}
}