{
  "type": "Feature",
  "properties": {
    "gn:admin1_code":"ER",
    "gn:admin2_code":"702.0",
    "gn:admin3_code":"70210.0",
    "gn:asciiname":"Leotelon",
    "gn:country_code":"TL",
    "gn:dem":1301,
    "gn:feature_class":"P",
    "gn:feature_code":"PPL",
    "gn:name":"Leotelon",
    "gn:population":0,
    "gn:timezone":"Asia/Dili",
    "iso:country":"TL",
    "wof:name":"Leotelon",
    "wof:placetype":"locality"
},
  "geometry": {"coordinates":[125.425,-8.79528],"type":"Point"}
}