{
  "type": "Feature",
  "properties": {
    "gn:admin1_code":"BA",
    "gn:admin2_code":"304.0",
    "gn:admin3_code":"30403.0",
    "gn:asciiname":"Afguia",
    "gn:country_code":"TL",
    "gn:dem":312,
    "gn:feature_class":"P",
    "gn:feature_code":"PPL",
    "gn:name":"Afguia",
    "gn:population":0,
    "gn:timezone":"Asia/Dili",
    "iso:country":"TL",
    "wof:name":"Afguia",
    "wof:placetype":"locality"
},
  "geometry": {"coordinates":[126.67722000000001,-8.62556],"type":"Point"}
}