{
  "type": "Feature",
  "properties": {
    "gn:admin1_code":"BA",
    "gn:admin2_code":"304.0",
    "gn:admin3_code":"30404.0",
    "gn:asciiname":"Osso Huna",
    "gn:country_code":"TL",
    "gn:dem":616,
    "gn:feature_class":"P",
    "gn:feature_code":"PPL",
    "gn:name":"Osso Huna",
    "gn:population":0,
    "gn:timezone":"Asia/Dili",
    "iso:country":"TL",
    "wof:name":"Osso Huna",
    "wof:placetype":"locality"
},
  "geometry": {"coordinates":[126.63333,-8.65],"type":"Point"}
}