{
  "type": "Feature",
  "properties": {
    "gn:admin1_code":"VI",
    "gn:admin2_code":"1301.0",
    "gn:admin3_code":"130101.0",
    "gn:asciiname":"Taradiga",
    "gn:country_code":"TL",
    "gn:dem":22,
    "gn:feature_class":"P",
    "gn:feature_code":"PPL",
    "gn:name":"Taradiga",
    "gn:population":0,
    "gn:timezone":"Asia/Dili",
    "iso:country":"TL",
    "wof:name":"Taradiga",
    "wof:placetype":"locality"
},
  "geometry": {"coordinates":[126.71444,-8.7425],"type":"Point"}
}