{
  "type": "Feature",
  "properties": {
    "gn:admin1_code":"OE",
    "gn:admin2_code":"1201.0",
    "gn:admin3_code":"120107.0",
    "gn:asciiname":"Bihana",
    "gn:country_code":"TL",
    "gn:dem":72,
    "gn:feature_class":"P",
    "gn:feature_code":"PPL",
    "gn:name":"Bihana",
    "gn:population":0,
    "gn:timezone":"Asia/Dili",
    "iso:country":"TL",
    "wof:name":"Bihana",
    "wof:placetype":"locality"
},
  "geometry": {"coordinates":[124.36783,-9.27908],"type":"Point"}
}