{
  "type": "Feature",
  "properties": {
    "gn:admin1_code":"VI",
    "gn:admin2_code":"1301.0",
    "gn:admin3_code":"130104.0",
    "gn:asciiname":"Bahatata",
    "gn:country_code":"TL",
    "gn:dem":371,
    "gn:feature_class":"P",
    "gn:feature_code":"PPL",
    "gn:name":"Bahatata",
    "gn:population":0,
    "gn:timezone":"Asia/Dili",
    "iso:country":"TL",
    "wof:name":"Bahatata",
    "wof:placetype":"locality"
},
  "geometry": {"coordinates":[126.65139000000001,-8.64917],"type":"Point"}
}