{
  "type": "Feature",
  "properties": {
    "gn:admin1_code":"VI",
    "gn:admin2_code":"1302.0",
    "gn:admin3_code":"130205.0",
    "gn:asciiname":"Uaitutumata",
    "gn:country_code":"TL",
    "gn:dem":439,
    "gn:feature_class":"P",
    "gn:feature_code":"PPL",
    "gn:name":"Uaitutumata",
    "gn:population":0,
    "gn:timezone":"Asia/Dili",
    "iso:country":"TL",
    "wof:name":"Uaitutumata",
    "wof:placetype":"locality"
},
  "geometry": {"coordinates":[126.40917,-8.76861],"type":"Point"}
}