{
  "type": "Feature",
  "properties": {
    "gn:admin1_code":"BA",
    "gn:admin2_code":"301.0",
    "gn:admin3_code":"30105.0",
    "gn:asciiname":"Uatubala",
    "gn:country_code":"TL",
    "gn:dem":110,
    "gn:feature_class":"P",
    "gn:feature_code":"PPL",
    "gn:name":"Uatubala",
    "gn:population":0,
    "gn:timezone":"Asia/Dili",
    "iso:country":"TL",
    "wof:name":"Uatubala",
    "wof:placetype":"locality"
},
  "geometry": {"coordinates":[126.45305999999999,-8.55694],"type":"Point"}
}