{
  "type": "Feature",
  "properties": {
    "gn:admin1_code":"CO",
    "gn:admin2_code":"505.0",
    "gn:admin3_code":"50502.0",
    "gn:asciiname":"Lakonakbesik",
    "gn:country_code":"TL",
    "gn:dem":30,
    "gn:feature_class":"P",
    "gn:feature_code":"PPL",
    "gn:name":"Lakonakbesik",
    "gn:population":0,
    "gn:timezone":"Asia/Dili",
    "iso:country":"TL",
    "wof:name":"Lakonakbesik",
    "wof:placetype":"locality"
},
  "geometry": {"coordinates":[125.22095,-9.33342],"type":"Point"}
}