{
  "type": "Feature",
  "properties": {
    "gn:admin1_code":"DI",
    "gn:admin2_code":"606.0",
    "gn:admin3_code":"60602.0",
    "gn:asciiname":"Buburlau",
    "gn:country_code":"TL",
    "gn:dem":81,
    "gn:feature_class":"P",
    "gn:feature_code":"PPL",
    "gn:name":"Buburlau",
    "gn:population":0,
    "gn:timezone":"Asia/Dili",
    "iso:country":"TL",
    "wof:name":"Buburlau",
    "wof:placetype":"locality"
},
  "geometry": {"coordinates":[125.61806,-8.57083],"type":"Point"}
}