{
  "type": "Feature",
  "properties": {
    "gn:admin1_code":"AN",
    "gn:admin2_code":"104.0",
    "gn:admin3_code":"10401.0",
    "gn:asciiname":"Bismata",
    "gn:country_code":"TL",
    "gn:dem":372,
    "gn:feature_class":"P",
    "gn:feature_code":"PPL",
    "gn:name":"Bismata",
    "gn:population":0,
    "gn:timezone":"Asia/Dili",
    "iso:country":"TL",
    "wof:name":"Bismata",
    "wof:placetype":"locality"
},
  "geometry": {"coordinates":[125.60527999999999,-9.13278],"type":"Point"}
}