{
  "type": "Feature",
  "properties": {
    "gn:admin1_code":"OE",
    "gn:admin2_code":"1201.0",
    "gn:admin3_code":"120103.0",
    "gn:asciiname":"Fautmet",
    "gn:country_code":"TL",
    "gn:dem":58,
    "gn:feature_class":"P",
    "gn:feature_code":"PPL",
    "gn:name":"Fautmet",
    "gn:population":0,
    "gn:timezone":"Asia/Dili",
    "iso:country":"TL",
    "wof:name":"Fautmet",
    "wof:placetype":"locality"
},
  "geometry": {"coordinates":[124.35722,-9.26778],"type":"Point"}
}