{
  "type": "Feature",
  "properties": {
    "gn:admin1_code":"MT",
    "gn:admin2_code":"1103.0",
    "gn:admin3_code":"110301.0",
    "gn:asciiname":"Tuha",
    "gn:country_code":"TL",
    "gn:dem":349,
    "gn:feature_class":"P",
    "gn:feature_code":"PPL",
    "gn:name":"Tuha",
    "gn:population":0,
    "gn:timezone":"Asia/Dili",
    "iso:country":"TL",
    "wof:name":"Tuha",
    "wof:placetype":"locality"
},
  "geometry": {"coordinates":[125.85193999999998,-8.60722],"type":"Point"}
}