{
  "type": "Feature",
  "properties": {
    "gn:admin1_code":"LI",
    "gn:admin2_code":"802.0",
    "gn:admin3_code":"80204.0",
    "gn:asciiname":"Natare",
    "gn:country_code":"TL",
    "gn:dem":1110,
    "gn:feature_class":"P",
    "gn:feature_code":"PPL",
    "gn:name":"Natare",
    "gn:population":0,
    "gn:timezone":"Asia/Dili",
    "iso:country":"TL",
    "wof:name":"Natare",
    "wof:placetype":"locality"
},
  "geometry": {"coordinates":[125.36083000000001,-8.64972],"type":"Point"}
}