{
  "type": "Feature",
  "properties": {
    "gn:admin1_code":"BA",
    "gn:admin2_code":"304.0",
    "gn:admin3_code":"30409.0",
    "gn:asciiname":"Fanalolo",
    "gn:country_code":"TL",
    "gn:dem":437,
    "gn:feature_class":"P",
    "gn:feature_code":"PPL",
    "gn:name":"Fanalolo",
    "gn:population":0,
    "gn:timezone":"Asia/Dili",
    "iso:country":"TL",
    "wof:name":"Fanalolo",
    "wof:placetype":"locality"
},
  "geometry": {"coordinates":[126.68222,-8.56972],"type":"Point"}
}