{
  "type": "Feature",
  "properties": {
    "gn:admin1_code":"MF",
    "gn:admin2_code":"1003.0",
    "gn:admin3_code":"100305.0",
    "gn:asciiname":"Ailalec",
    "gn:country_code":"TL",
    "gn:dem":57,
    "gn:feature_class":"P",
    "gn:feature_code":"PPL",
    "gn:name":"Ailalec",
    "gn:population":0,
    "gn:timezone":"Asia/Dili",
    "iso:country":"TL",
    "wof:name":"Ailalec",
    "wof:placetype":"locality"
},
  "geometry": {"coordinates":[125.96138999999999,-9.04472],"type":"Point"}
}