{
  "type": "Feature",
  "properties": {
    "gn:admin1_code":"LI",
    "gn:admin2_code":"801.0",
    "gn:admin3_code":"80105.0",
    "gn:asciiname":"Metaluli",
    "gn:country_code":"TL",
    "gn:dem":656,
    "gn:feature_class":"P",
    "gn:feature_code":"PPL",
    "gn:name":"Metaluli",
    "gn:population":0,
    "gn:timezone":"Asia/Dili",
    "iso:country":"TL",
    "wof:name":"Metaluli",
    "wof:placetype":"locality"
},
  "geometry": {"coordinates":[125.36667,-8.62306],"type":"Point"}
}