{
  "type": "Feature",
  "properties": {
    "gn:admin1_code":"BA",
    "gn:admin2_code":"304.0",
    "gn:admin3_code":"30406.0",
    "gn:asciiname":"Larisula",
    "gn:country_code":"TL",
    "gn:dem":83,
    "gn:feature_class":"P",
    "gn:feature_code":"PPL",
    "gn:name":"Larisula",
    "gn:population":0,
    "gn:timezone":"Asia/Dili",
    "iso:country":"TL",
    "wof:name":"Larisula",
    "wof:placetype":"locality"
},
  "geometry": {"coordinates":[126.72750000000001,-8.65333],"type":"Point"}
}