{
  "type": "Feature",
  "properties": {
    "gn:admin1_code":"LA",
    "gn:admin2_code":"901.0",
    "gn:admin3_code":"90108.0",
    "gn:asciiname":"Mua Pitine",
    "gn:country_code":"TL",
    "gn:dem":357,
    "gn:feature_class":"P",
    "gn:feature_code":"PPL",
    "gn:name":"Mua Pitine",
    "gn:population":0,
    "gn:timezone":"Asia/Dili",
    "iso:country":"TL",
    "name:und_x_variant":[
        "Mau-Pitine",
        "Mua Pitine"
    ],
    "wof:name":"Mua Pitine",
    "wof:placetype":"locality"
},
  "geometry": {"coordinates":[127.06667,-8.53333],"type":"Point"}
}