{
  "type": "Feature",
  "properties": {
    "gn:admin1_code":"LA",
    "gn:admin2_code":"901.0",
    "gn:admin3_code":"90110.0",
    "gn:asciiname":"Lauro",
    "gn:country_code":"TL",
    "gn:dem":464,
    "gn:feature_class":"P",
    "gn:feature_code":"PPL",
    "gn:name":"Lauro",
    "gn:population":0,
    "gn:timezone":"Asia/Dili",
    "iso:country":"TL",
    "wof:name":"Lauro",
    "wof:placetype":"locality"
},
  "geometry": {"coordinates":[126.95222,-8.52306],"type":"Point"}
}