{
  "type": "Feature",
  "properties": {
    "gn:admin1_code":"LA",
    "gn:admin2_code":"901.0",
    "gn:admin3_code":"90110.0",
    "gn:asciiname":"Lauro",
    "gn:country_code":"TL",
    "gn:dem":464,
    "gn:feature_class":"P",
    "gn:feature_code":"PPL",
    "gn:name":"Lauro",
    "gn:population":0,
    "gn:timezone":"Asia/Dili",
    "iso:country":"TL",
    "name:azb_x_preferred":[
        "\u0644\u0627\u0648\u0631\u0648"
    ],
    "name:bul_x_preferred":[
        "\u041b\u0430\u0443\u0440\u043e"
    ],
    "name:ceb_x_preferred":[
        "Lauro"
    ],
    "name:deu_x_preferred":[
        "Lauro"
    ],
    "name:epo_x_preferred":[
        "Lauro"
    ],
    "name:eus_x_preferred":[
        "Lauro"
    ],
    "name:fas_x_preferred":[
        "\u0644\u0627\u0648\u0631\u0648"
    ],
    "name:fin_x_preferred":[
        "Lauro"
    ],
    "name:fra_x_preferred":[
        "Lauro"
    ],
    "name:hun_x_preferred":[
        "Lauro"
    ],
    "name:hye_x_preferred":[
        "\u053c\u0561\u0578\u0582\u0580\u0578"
    ],
    "name:ina_x_preferred":[
        "Lauro"
    ],
    "name:ind_x_preferred":[
        "Lauro"
    ],
    "name:ita_x_preferred":[
        "Lauro"
    ],
    "name:jpn_x_preferred":[
        "\u30e9\u30a6\u30ed"
    ],
    "name:kaz_x_preferred":[
        "\u041b\u0430\u0443\u0440\u043e"
    ],
    "name:kor_x_preferred":[
        "\ub77c\uc6b0\ub85c"
    ],
    "name:lat_x_preferred":[
        "Laurus"
    ],
    "name:lmo_x_preferred":[
        "Lauro"
    ],
    "name:mkd_x_preferred":[
        "\u041b\u0430\u0443\u0440\u043e"
    ],
    "name:msa_x_preferred":[
        "Lauro"
    ],
    "name:nap_x_preferred":[
        "Lauro"
    ],
    "name:nld_x_preferred":[
        "Lauro"
    ],
    "name:pms_x_preferred":[
        "Lauro"
    ],
    "name:pol_x_preferred":[
        "Lauro"
    ],
    "name:por_x_preferred":[
        "Lauro"
    ],
    "name:ron_x_preferred":[
        "Lauro"
    ],
    "name:rus_x_preferred":[
        "\u041b\u0430\u0443\u0440\u043e"
    ],
    "name:scn_x_preferred":[
        "Lauru"
    ],
    "name:spa_x_preferred":[
        "Lauro"
    ],
    "name:srp_x_preferred":[
        "\u041b\u0430\u0443\u0440\u043e"
    ],
    "name:tgl_x_preferred":[
        "Lauro"
    ],
    "name:ukr_x_preferred":[
        "\u041b\u0430\u0443\u0440\u043e"
    ],
    "name:uzb_x_preferred":[
        "Lauro"
    ],
    "name:vec_x_preferred":[
        "Lauro"
    ],
    "name:vie_x_preferred":[
        "Lauro"
    ],
    "name:vol_x_preferred":[
        "Lauro"
    ],
    "name:war_x_preferred":[
        "Lauro"
    ],
    "wof:name":"Lauro",
    "wof:placetype":"locality"
},
  "geometry": {"coordinates":[126.95222,-8.52306],"type":"Point"}
}