{
  "type": "Feature",
  "properties": {
    "gn:admin1_code":"MT",
    "gn:admin2_code":"1101.0",
    "gn:admin3_code":"110104.0",
    "gn:asciiname":"Malarahu",
    "gn:country_code":"TL",
    "gn:dem":27,
    "gn:feature_class":"P",
    "gn:feature_code":"PPL",
    "gn:name":"Malarahu",
    "gn:population":0,
    "gn:timezone":"Asia/Dili",
    "iso:country":"TL",
    "wof:name":"Malarahu",
    "wof:placetype":"locality"
},
  "geometry": {"coordinates":[125.99778000000001,-8.52167],"type":"Point"}
}