{
  "type": "Feature",
  "properties": {
    "gn:admin1_code":"CO",
    "gn:admin2_code":"503.0",
    "gn:admin3_code":"50301.0",
    "gn:asciiname":"Fohoren",
    "gn:country_code":"TL",
    "gn:dem":554,
    "gn:feature_class":"P",
    "gn:feature_code":"PPL",
    "gn:name":"Fohoren",
    "gn:population":0,
    "gn:timezone":"Asia/Dili",
    "iso:country":"TL",
    "name:ceb_x_preferred":[
        "Fohoren"
    ],
    "name:deu_x_preferred":[
        "Fohoren"
    ],
    "name:msa_x_preferred":[
        "Fohoren"
    ],
    "name:tet_x_preferred":[
        "Fohor\u00e9n"
    ],
    "name:urd_x_preferred":[
        "\u0641\u0648\u06c1\u0648\u0631\u06cc\u0646"
    ],
    "wof:name":"Fohoren",
    "wof:placetype":"locality"
},
  "geometry": {"coordinates":[125.08333,-9.28333],"type":"Point"}
}