{
  "type": "Feature",
  "properties": {
    "gn:admin1_code":"CO",
    "gn:admin2_code":"502.0",
    "gn:admin3_code":"50203.0",
    "gn:asciiname":"Buburlaran",
    "gn:country_code":"TL",
    "gn:dem":632,
    "gn:feature_class":"P",
    "gn:feature_code":"PPL",
    "gn:name":"Buburlaran",
    "gn:population":0,
    "gn:timezone":"Asia/Dili",
    "iso:country":"TL",
    "wof:name":"Buburlaran",
    "wof:placetype":"locality"
},
  "geometry": {"coordinates":[125.02806,-9.28361],"type":"Point"}
}