{
  "type": "Feature",
  "properties": {
    "gn:admin1_code":"LA",
    "gn:admin2_code":"902.0",
    "gn:admin3_code":"90207.0",
    "gn:asciiname":"Lereira",
    "gn:country_code":"TL",
    "gn:dem":530,
    "gn:feature_class":"P",
    "gn:feature_code":"PPL",
    "gn:name":"Lereira",
    "gn:population":0,
    "gn:timezone":"Asia/Dili",
    "iso:country":"TL",
    "wof:name":"Lereira",
    "wof:placetype":"locality"
},
  "geometry": {"coordinates":[126.88333,-8.46806],"type":"Point"}
}