{
  "type": "Feature",
  "properties": {
    "gn:admin1_code":"OE",
    "gn:admin2_code":"1201.0",
    "gn:admin3_code":"120108.0",
    "gn:asciiname":"Bobonoe",
    "gn:country_code":"TL",
    "gn:dem":121,
    "gn:feature_class":"P",
    "gn:feature_code":"PPL",
    "gn:name":"Bobonoe",
    "gn:population":0,
    "gn:timezone":"Asia/Dili",
    "iso:country":"TL",
    "wof:name":"Bobonoe",
    "wof:placetype":"locality"
},
  "geometry": {"coordinates":[124.36888999999999,-9.30222],"type":"Point"}
}