{
  "type": "Feature",
  "properties": {
    "gn:admin1_code":"LA",
    "gn:admin2_code":"902.0",
    "gn:admin3_code":"90207.0",
    "gn:asciiname":"Codo",
    "gn:country_code":"TL",
    "gn:dem":535,
    "gn:feature_class":"P",
    "gn:feature_code":"PPL",
    "gn:name":"Codo",
    "gn:population":0,
    "gn:timezone":"Asia/Dili",
    "iso:country":"TL",
    "name:arg_x_preferred":[
        "Codo"
    ],
    "name:ceb_x_preferred":[
        "Codo"
    ],
    "name:deu_x_preferred":[
        "Codo"
    ],
    "name:eus_x_preferred":[
        "Ukondo"
    ],
    "name:fra_x_preferred":[
        "Codo"
    ],
    "name:por_x_preferred":[
        "Codo"
    ],
    "name:ron_x_preferred":[
        "Codo"
    ],
    "name:spa_x_preferred":[
        "Codo"
    ],
    "name:swe_x_preferred":[
        "Codo"
    ],
    "wof:name":"Codo",
    "wof:placetype":"locality"
},
  "geometry": {"coordinates":[126.88194,-8.46694],"type":"Point"}
}