{
  "type": "Feature",
  "properties": {
    "gn:admin1_code":"LA",
    "gn:admin2_code":"901.0",
    "gn:admin3_code":"90102.0",
    "gn:asciiname":"Puaperchula",
    "gn:country_code":"TL",
    "gn:dem":454,
    "gn:feature_class":"P",
    "gn:feature_code":"PPL",
    "gn:name":"Puaperchula",
    "gn:population":0,
    "gn:timezone":"Asia/Dili",
    "iso:country":"TL",
    "wof:name":"Puaperchula",
    "wof:placetype":"locality"
},
  "geometry": {"coordinates":[127.00333000000001,-8.56222],"type":"Point"}
}