{
  "type": "Feature",
  "properties": {
    "gn:admin1_code":"CO",
    "gn:admin2_code":"502.0",
    "gn:admin3_code":"50201.0",
    "gn:asciiname":"Fatumea",
    "gn:country_code":"TL",
    "gn:dem":739,
    "gn:feature_class":"P",
    "gn:feature_code":"PPL",
    "gn:name":"Fatumea",
    "gn:population":0,
    "gn:timezone":"Asia/Dili",
    "iso:country":"TL",
    "wof:name":"Fatumea",
    "wof:placetype":"locality"
},
  "geometry": {"coordinates":[125.03333000000001,-9.23333],"type":"Point"}
}