{
  "type": "Feature",
  "properties": {
    "gn:admin1_code":"VI",
    "gn:admin2_code":"1301.0",
    "gn:admin3_code":"130104.0",
    "gn:asciiname":"Marae",
    "gn:country_code":"TL",
    "gn:dem":604,
    "gn:feature_class":"P",
    "gn:feature_code":"PPL",
    "gn:name":"Marae",
    "gn:population":0,
    "gn:timezone":"Asia/Dili",
    "iso:country":"TL",
    "name:afr_x_preferred":[
        "Marae"
    ],
    "name:arg_x_preferred":[
        "Marae"
    ],
    "name:cat_x_preferred":[
        "Marae"
    ],
    "name:ces_x_preferred":[
        "Marae"
    ],
    "name:cym_x_preferred":[
        "Marae"
    ],
    "name:deu_x_preferred":[
        "Marae"
    ],
    "name:fra_x_preferred":[
        "Marae"
    ],
    "name:ita_x_preferred":[
        "Marae"
    ],
    "name:kat_x_preferred":[
        "\u10db\u10d0\u10e0\u10d0\u10d4"
    ],
    "name:mri_x_preferred":[
        "Marae"
    ],
    "name:nld_x_preferred":[
        "Marae"
    ],
    "name:nor_x_preferred":[
        "Marae"
    ],
    "name:pol_x_preferred":[
        "Marae"
    ],
    "name:por_x_preferred":[
        "Marae"
    ],
    "name:rus_x_preferred":[
        "\u041c\u0430\u0440\u0430\u044d"
    ],
    "name:spa_x_preferred":[
        "Marae"
    ],
    "wof:name":"Marae",
    "wof:placetype":"locality"
},
  "geometry": {"coordinates":[126.63806,-8.65556],"type":"Point"}
}