{
  "type": "Feature",
  "properties": {
    "gn:admin1_code":"VI",
    "gn:admin2_code":"1301.0",
    "gn:admin3_code":"130104.0",
    "gn:asciiname":"Marae",
    "gn:country_code":"TL",
    "gn:dem":604,
    "gn:feature_class":"P",
    "gn:feature_code":"PPL",
    "gn:name":"Marae",
    "gn:population":0,
    "gn:timezone":"Asia/Dili",
    "iso:country":"TL",
    "wof:name":"Marae",
    "wof:placetype":"locality"
},
  "geometry": {"coordinates":[126.63806,-8.65556],"type":"Point"}
}