{
  "type": "Feature",
  "properties": {
    "gn:admin1_code":"BA",
    "gn:admin2_code":"301.0",
    "gn:admin3_code":"30109.0",
    "gn:asciiname":"Osso Ua",
    "gn:country_code":"TL",
    "gn:dem":104,
    "gn:feature_class":"P",
    "gn:feature_code":"PPL",
    "gn:name":"Osso Ua",
    "gn:population":0,
    "gn:timezone":"Asia/Dili",
    "iso:country":"TL",
    "wof:name":"Osso Ua",
    "wof:placetype":"locality"
},
  "geometry": {"coordinates":[126.35773,-8.4493],"type":"Point"}
}