{
  "type": "Feature",
  "properties": {
    "gn:admin1_code":"CO",
    "gn:admin2_code":"506.0",
    "gn:admin3_code":"50604.0",
    "gn:asciiname":"Koloana",
    "gn:country_code":"TL",
    "gn:dem":27,
    "gn:feature_class":"P",
    "gn:feature_code":"PPL",
    "gn:name":"Koloana",
    "gn:population":0,
    "gn:timezone":"Asia/Dili",
    "iso:country":"TL",
    "wof:name":"Koloana",
    "wof:placetype":"locality"
},
  "geometry": {"coordinates":[125.18933,-9.37917],"type":"Point"}
}