{
  "type": "Feature",
  "properties": {
    "gn:admin1_code":"DI",
    "gn:admin2_code":"601.0",
    "gn:admin3_code":"60101.0",
    "gn:asciiname":"Lahane",
    "gn:country_code":"TL",
    "gn:dem":280,
    "gn:feature_class":"P",
    "gn:feature_code":"PPL",
    "gn:name":"Lahane",
    "gn:population":0,
    "gn:timezone":"Asia/Dili",
    "iso:country":"TL",
    "name:und_x_variant":[
        "Lahae",
        "Lahane"
    ],
    "wof:name":"Lahane",
    "wof:placetype":"locality"
},
  "geometry": {"coordinates":[125.58333,-8.58333],"type":"Point"}
}