{
  "type": "Feature",
  "properties": {
    "gn:admin1_code":"MT",
    "gn:admin2_code":"1105.0",
    "gn:admin3_code":"110504.0",
    "gn:asciiname":"Kribasbarique",
    "gn:country_code":"TL",
    "gn:dem":366,
    "gn:feature_class":"P",
    "gn:feature_code":"PPL",
    "gn:name":"Kribasbarique",
    "gn:population":0,
    "gn:timezone":"Asia/Dili",
    "iso:country":"TL",
    "wof:name":"Kribasbarique",
    "wof:placetype":"locality"
},
  "geometry": {"coordinates":[126.06194000000001,-8.84639],"type":"Point"}
}