{
  "type": "Feature",
  "properties": {
    "gn:admin1_code":"BO",
    "gn:admin2_code":"401.0",
    "gn:admin3_code":"40106.0",
    "gn:asciiname":"Lepguen",
    "gn:country_code":"TL",
    "gn:dem":260,
    "gn:feature_class":"P",
    "gn:feature_code":"PPL",
    "gn:name":"Lepguen",
    "gn:population":0,
    "gn:timezone":"Asia/Dili",
    "iso:country":"TL",
    "wof:name":"Lepguen",
    "wof:placetype":"locality"
},
  "geometry": {"coordinates":[125.19083000000001,-9.01556],"type":"Point"}
}