{
  "type": "Feature",
  "properties": {
    "gn:admin1_code":"ER",
    "gn:admin2_code":"701.0",
    "gn:admin3_code":"70107.0",
    "gn:asciiname":"Rihiu",
    "gn:country_code":"TL",
    "gn:dem":937,
    "gn:feature_class":"P",
    "gn:feature_code":"PPL",
    "gn:name":"Rihiu",
    "gn:population":0,
    "gn:timezone":"Asia/Dili",
    "iso:country":"TL",
    "wof:name":"Rihiu",
    "wof:placetype":"locality"
},
  "geometry": {"coordinates":[125.51503,-8.65981],"type":"Point"}
}