{
  "type": "Feature",
  "properties": {
    "gn:admin1_code":"ER",
    "gn:admin2_code":"705.0",
    "gn:admin3_code":"70512.0",
    "gn:asciiname":"Fatubolo",
    "gn:country_code":"TL",
    "gn:dem":1447,
    "gn:feature_class":"P",
    "gn:feature_code":"PPL",
    "gn:name":"Fatubolo",
    "gn:population":0,
    "gn:timezone":"Asia/Dili",
    "iso:country":"TL",
    "wof:name":"Fatubolo",
    "wof:placetype":"locality"
},
  "geometry": {"coordinates":[125.36833,-8.74944],"type":"Point"}
}