{
  "type": "Feature",
  "properties": {
    "gn:admin1_code":"BO",
    "gn:admin2_code":"402.0",
    "gn:admin3_code":"40201.0",
    "gn:asciiname":"Haareme",
    "gn:country_code":"TL",
    "gn:dem":680,
    "gn:feature_class":"P",
    "gn:feature_code":"PPL",
    "gn:name":"Haareme",
    "gn:population":0,
    "gn:timezone":"Asia/Dili",
    "iso:country":"TL",
    "wof:name":"Haareme",
    "wof:placetype":"locality"
},
  "geometry": {"coordinates":[125.29416999999999,-8.96944],"type":"Point"}
}