{
  "type": "Feature",
  "properties": {
    "gn:admin1_code":"BA",
    "gn:admin2_code":"306.0",
    "gn:admin3_code":"30607.0",
    "gn:asciiname":"Fatulia",
    "gn:country_code":"TL",
    "gn:dem":778,
    "gn:feature_class":"P",
    "gn:feature_code":"PPL",
    "gn:name":"Fatulia",
    "gn:population":0,
    "gn:timezone":"Asia/Dili",
    "iso:country":"TL",
    "wof:name":"Fatulia",
    "wof:placetype":"locality"
},
  "geometry": {"coordinates":[126.36611000000001,-8.64111],"type":"Point"}
}