{
  "type": "Feature",
  "properties": {
    "gn:admin1_code":"CO",
    "gn:admin2_code":"507.0",
    "gn:admin3_code":"50706.0",
    "gn:asciiname":"Zulo",
    "gn:country_code":"TL",
    "gn:dem":495,
    "gn:feature_class":"P",
    "gn:feature_code":"PPL",
    "gn:name":"Zulo",
    "gn:population":0,
    "gn:timezone":"Asia/Dili",
    "iso:country":"TL",
    "wof:name":"Zulo",
    "wof:placetype":"locality"
},
  "geometry": {"coordinates":[125.40833000000001,-9.11],"type":"Point"}
}