{
  "type": "Feature",
  "properties": {
    "gn:admin1_code":"BO",
    "gn:admin2_code":"401.0",
    "gn:admin3_code":"40101.0",
    "gn:asciiname":"Lesuboten",
    "gn:country_code":"TL",
    "gn:dem":458,
    "gn:feature_class":"P",
    "gn:feature_code":"PPL",
    "gn:name":"Lesuboten",
    "gn:population":0,
    "gn:timezone":"Asia/Dili",
    "iso:country":"TL",
    "wof:name":"Lesuboten",
    "wof:placetype":"locality"
},
  "geometry": {"coordinates":[125.23694,-9.00222],"type":"Point"}
}