{
  "type": "Feature",
  "properties": {
    "gn:admin1_code":"CO",
    "gn:admin2_code":"506.0",
    "gn:admin3_code":"50602.0",
    "gn:asciiname":"Kotafoun",
    "gn:country_code":"TL",
    "gn:dem":473,
    "gn:feature_class":"P",
    "gn:feature_code":"PPL",
    "gn:name":"Kotafoun",
    "gn:population":0,
    "gn:timezone":"Asia/Dili",
    "iso:country":"TL",
    "wof:name":"Kotafoun",
    "wof:placetype":"locality"
},
  "geometry": {"coordinates":[125.11956000000001,-9.34408],"type":"Point"}
}