{
  "type": "Feature",
  "properties": {
    "gn:admin1_code":"AN",
    "gn:admin2_code":"103.0",
    "gn:admin3_code":"10306.0",
    "gn:asciiname":"Tarabula",
    "gn:country_code":"TL",
    "gn:dem":1547,
    "gn:feature_class":"P",
    "gn:feature_code":"PPL",
    "gn:name":"Tarabula",
    "gn:population":0,
    "gn:timezone":"Asia/Dili",
    "iso:country":"TL",
    "wof:name":"Tarabula",
    "wof:placetype":"locality"
},
  "geometry": {"coordinates":[125.66443999999998,-8.82139],"type":"Point"}
}