{
  "type": "Feature",
  "properties": {
    "gn:admin1_code":"CO",
    "gn:admin2_code":"507.0",
    "gn:admin3_code":"50701.0",
    "gn:asciiname":"Mape",
    "gn:country_code":"TL",
    "gn:dem":98,
    "gn:feature_class":"P",
    "gn:feature_code":"PPL",
    "gn:name":"Mape",
    "gn:population":0,
    "gn:timezone":"Asia/Dili",
    "iso:country":"TL",
    "name:deu_x_preferred":[
        "Mape"
    ],
    "name:msa_x_preferred":[
        "Mape"
    ],
    "name:tet_x_preferred":[
        "Mape"
    ],
    "wof:name":"Mape",
    "wof:placetype":"locality"
},
  "geometry": {"coordinates":[125.45361,-9.155],"type":"Point"}
}