{
  "type": "Feature",
  "properties": {
    "gn:admin1_code":"OE",
    "gn:admin2_code":"1203.0",
    "gn:admin3_code":"120303.0",
    "gn:asciiname":"Bono",
    "gn:country_code":"TL",
    "gn:dem":438,
    "gn:feature_class":"P",
    "gn:feature_code":"PPL",
    "gn:name":"Bono",
    "gn:population":0,
    "gn:timezone":"Asia/Dili",
    "iso:country":"TL",
    "wof:name":"Bono",
    "wof:placetype":"locality"
},
  "geometry": {"coordinates":[124.34721999999999,-9.37139],"type":"Point"}
}