{
  "type": "Feature",
  "properties": {
    "gn:admin1_code":"LA",
    "gn:admin2_code":"901.0",
    "gn:admin3_code":"90102.0",
    "gn:asciiname":"Kartini",
    "gn:country_code":"TL",
    "gn:dem":386,
    "gn:feature_class":"P",
    "gn:feature_code":"PPL",
    "gn:name":"Kartini",
    "gn:population":0,
    "gn:timezone":"Asia/Dili",
    "iso:country":"TL",
    "name:deu_x_preferred":[
        "Kartini"
    ],
    "name:fra_x_preferred":[
        "Kartini"
    ],
    "name:glg_x_preferred":[
        "Kartini"
    ],
    "name:ind_x_preferred":[
        "Kartini"
    ],
    "name:jav_x_preferred":[
        "Kartini"
    ],
    "name:kor_x_preferred":[
        "\uce74\ub974\ud2f0\ub2c8"
    ],
    "name:msa_x_preferred":[
        "R.A. Kartini"
    ],
    "name:nld_x_preferred":[
        "Kartini"
    ],
    "name:pol_x_preferred":[
        "Kartini"
    ],
    "name:rus_x_preferred":[
        "\u041a\u0430\u0440\u0442\u0438\u043d\u0438"
    ],
    "name:sun_x_preferred":[
        "Kartini"
    ],
    "name:swe_x_preferred":[
        "Kartini"
    ],
    "name:tha_x_preferred":[
        "\u0e01\u0e32\u0e23\u0e4c\u0e15\u0e35\u0e19\u0e35"
    ],
    "wof:name":"Kartini",
    "wof:placetype":"locality"
},
  "geometry": {"coordinates":[126.99944000000001,-8.52889],"type":"Point"}
}