{
  "type": "Feature",
  "properties": {
    "gn:admin1_code":"BO",
    "gn:admin2_code":"403.0",
    "gn:admin3_code":"40301.0",
    "gn:asciiname":"Fatunisin",
    "gn:country_code":"TL",
    "gn:dem":494,
    "gn:feature_class":"P",
    "gn:feature_code":"PPL",
    "gn:name":"Fatunisin",
    "gn:population":0,
    "gn:timezone":"Asia/Dili",
    "iso:country":"TL",
    "wof:name":"Fatunisin",
    "wof:placetype":"locality"
},
  "geometry": {"coordinates":[125.06471999999999,-8.955],"type":"Point"}
}