{
  "type": "Feature",
  "properties": {
    "gn:admin1_code":"BO",
    "gn:admin2_code":"405.0",
    "gn:admin3_code":"40501.0",
    "gn:asciiname":"Raimea",
    "gn:country_code":"TL",
    "gn:dem":781,
    "gn:feature_class":"P",
    "gn:feature_code":"PPL",
    "gn:name":"Raimea",
    "gn:population":0,
    "gn:timezone":"Asia/Dili",
    "iso:country":"TL",
    "wof:name":"Raimea",
    "wof:placetype":"locality"
},
  "geometry": {"coordinates":[125.27500000000001,-9.16611],"type":"Point"}
}