{
  "type": "Feature",
  "properties": {
    "gn:admin1_code":"BO",
    "gn:admin2_code":"402.0",
    "gn:admin3_code":"40203.0",
    "gn:asciiname":"Meligo",
    "gn:country_code":"TL",
    "gn:dem":809,
    "gn:feature_class":"P",
    "gn:feature_code":"PPL",
    "gn:name":"Meligo",
    "gn:population":0,
    "gn:timezone":"Asia/Dili",
    "iso:country":"TL",
    "wof:name":"Meligo",
    "wof:placetype":"locality"
},
  "geometry": {"coordinates":[125.25556,-8.92417],"type":"Point"}
}