{
  "type": "Feature",
  "properties": {
    "gn:admin1_code":"BA",
    "gn:admin2_code":"301.0",
    "gn:admin3_code":"30107.0",
    "gn:asciiname":"Maucale",
    "gn:country_code":"TL",
    "gn:dem":504,
    "gn:feature_class":"P",
    "gn:feature_code":"PPL",
    "gn:name":"Maucale",
    "gn:population":0,
    "gn:timezone":"Asia/Dili",
    "iso:country":"TL",
    "wof:name":"Maucale",
    "wof:placetype":"locality"
},
  "geometry": {"coordinates":[126.41441,-8.55662],"type":"Point"}
}