{
  "type": "Feature",
  "properties": {
    "gn:admin1_code":"AL",
    "gn:admin2_code":"202.0",
    "gn:admin3_code":"20201.0",
    "gn:asciiname":"Daro",
    "gn:country_code":"TL",
    "gn:dem":1341,
    "gn:feature_class":"P",
    "gn:feature_code":"PPL",
    "gn:name":"Daro",
    "gn:population":0,
    "gn:timezone":"Asia/Dili",
    "iso:country":"TL",
    "wof:name":"Daro",
    "wof:placetype":"locality"
},
  "geometry": {"coordinates":[125.64079,-8.71271],"type":"Point"}
}