{
  "type": "Feature",
  "properties": {
    "gn:admin1_code":"CO",
    "gn:admin2_code":"505.0",
    "gn:admin3_code":"50502.0",
    "gn:asciiname":"Serankotek",
    "gn:country_code":"TL",
    "gn:dem":27,
    "gn:feature_class":"P",
    "gn:feature_code":"PPL",
    "gn:name":"Serankotek",
    "gn:population":0,
    "gn:timezone":"Asia/Dili",
    "iso:country":"TL",
    "wof:name":"Serankotek",
    "wof:placetype":"locality"
},
  "geometry": {"coordinates":[125.23721999999999,-9.32525],"type":"Point"}
}