{
  "type": "Feature",
  "properties": {
    "gn:admin1_code":"MF",
    "gn:admin2_code":"1001.0",
    "gn:admin3_code":"100105.0",
    "gn:asciiname":"Lesulau",
    "gn:country_code":"TL",
    "gn:dem":124,
    "gn:feature_class":"P",
    "gn:feature_code":"PPL",
    "gn:name":"Lesulau",
    "gn:population":0,
    "gn:timezone":"Asia/Dili",
    "iso:country":"TL",
    "wof:name":"Lesulau",
    "wof:placetype":"locality"
},
  "geometry": {"coordinates":[125.68389000000001,-9.08083],"type":"Point"}
}