{
  "type": "Feature",
  "properties": {
    "gn:admin1_code":"BO",
    "gn:admin2_code":"406.0",
    "gn:admin3_code":"40608.0",
    "gn:asciiname":"Tasqolo",
    "gn:country_code":"TL",
    "gn:dem":652,
    "gn:feature_class":"P",
    "gn:feature_code":"PPL",
    "gn:name":"Tasqolo",
    "gn:population":0,
    "gn:timezone":"Asia/Dili",
    "iso:country":"TL",
    "wof:name":"Tasqolo",
    "wof:placetype":"locality"
},
  "geometry": {"coordinates":[125.35699,-9.06761],"type":"Point"}
}