{
  "type": "Feature",
  "properties": {
    "gn:admin1_code":"VI",
    "gn:admin2_code":"1302.0",
    "gn:admin3_code":"130204.0",
    "gn:asciiname":"Belas",
    "gn:country_code":"TL",
    "gn:dem":725,
    "gn:feature_class":"P",
    "gn:feature_code":"PPL",
    "gn:name":"Belas",
    "gn:population":0,
    "gn:timezone":"Asia/Dili",
    "iso:country":"TL",
    "name:ceb_x_preferred":[
        "Belas"
    ],
    "name:deu_x_preferred":[
        "Belas"
    ],
    "name:fra_x_preferred":[
        "Belas"
    ],
    "name:por_x_preferred":[
        "Belas"
    ],
    "name:rus_x_preferred":[
        "\u0411\u0435\u043b\u0430\u0448"
    ],
    "name:swe_x_preferred":[
        "Belas"
    ],
    "name:ukr_x_preferred":[
        "\u0411\u0435\u043b\u0430\u0448"
    ],
    "wof:name":"Belas",
    "wof:placetype":"locality"
},
  "geometry": {"coordinates":[126.37667,-8.74083],"type":"Point"}
}