{
  "type": "Feature",
  "properties": {
    "gn:admin1_code":"BA",
    "gn:admin2_code":"303.0",
    "gn:admin3_code":"30311.0",
    "gn:asciiname":"Uaidaba",
    "gn:country_code":"TL",
    "gn:dem":737,
    "gn:feature_class":"P",
    "gn:feature_code":"PPL",
    "gn:name":"Uaidaba",
    "gn:population":0,
    "gn:timezone":"Asia/Dili",
    "iso:country":"TL",
    "wof:name":"Uaidaba",
    "wof:placetype":"locality"
},
  "geometry": {"coordinates":[126.54056,-8.65417],"type":"Point"}
}