{
  "type": "Feature",
  "properties": {
    "gn:admin1_code":"LA",
    "gn:admin2_code":"901.0",
    "gn:admin3_code":"90106.0",
    "gn:asciiname":"Harolata",
    "gn:country_code":"TL",
    "gn:dem":137,
    "gn:feature_class":"P",
    "gn:feature_code":"PPL",
    "gn:name":"Harolata",
    "gn:population":0,
    "gn:timezone":"Asia/Dili",
    "iso:country":"TL",
    "wof:name":"Harolata",
    "wof:placetype":"locality"
},
  "geometry": {"coordinates":[127.01528,-8.64389],"type":"Point"}
}