{
  "type": "Feature",
  "properties": {
    "gn:admin1_code":"LI",
    "gn:admin2_code":"802.0",
    "gn:admin3_code":"80207.0",
    "gn:asciiname":"Boibau",
    "gn:country_code":"TL",
    "gn:dem":666,
    "gn:feature_class":"P",
    "gn:feature_code":"PPL",
    "gn:name":"Boibau",
    "gn:population":0,
    "gn:timezone":"Asia/Dili",
    "iso:country":"TL",
    "name:und_x_variant":[
        "Boibao",
        "Boibau"
    ],
    "wof:name":"Boibau",
    "wof:placetype":"locality"
},
  "geometry": {"coordinates":[125.31722000000001,-8.68333],"type":"Point"}
}