{
  "type": "Feature",
  "properties": {
    "gn:admin1_code":"ER",
    "gn:admin2_code":"704.0",
    "gn:admin3_code":"70403.0",
    "gn:asciiname":"Raibuti",
    "gn:country_code":"TL",
    "gn:dem":1119,
    "gn:feature_class":"P",
    "gn:feature_code":"PPL",
    "gn:name":"Raibuti",
    "gn:population":0,
    "gn:timezone":"Asia/Dili",
    "iso:country":"TL",
    "wof:name":"Raibuti",
    "wof:placetype":"locality"
},
  "geometry": {"coordinates":[125.39639,-8.91694],"type":"Point"}
}