{
  "type": "Feature",
  "properties": {
    "gn:admin1_code":"BA",
    "gn:admin2_code":"301.0",
    "gn:admin3_code":"30109.0",
    "gn:asciiname":"Uaisa",
    "gn:country_code":"TL",
    "gn:dem":130,
    "gn:feature_class":"P",
    "gn:feature_code":"PPL",
    "gn:name":"Uaisa",
    "gn:population":0,
    "gn:timezone":"Asia/Dili",
    "iso:country":"TL",
    "wof:name":"Uaisa",
    "wof:placetype":"locality"
},
  "geometry": {"coordinates":[126.35878,-8.44926],"type":"Point"}
}