{
  "type": "Feature",
  "properties": {
    "gn:admin1_code":"LI",
    "gn:admin2_code":"803.0",
    "gn:admin3_code":"80303.0",
    "gn:asciiname":"Samanaro",
    "gn:country_code":"TL",
    "gn:dem":16,
    "gn:feature_class":"P",
    "gn:feature_code":"PPL",
    "gn:name":"Samanaro",
    "gn:population":0,
    "gn:timezone":"Asia/Dili",
    "iso:country":"TL",
    "wof:name":"Samanaro",
    "wof:placetype":"locality"
},
  "geometry": {"coordinates":[125.23972000000001,-8.60667],"type":"Point"}
}