{
  "type": "Feature",
  "properties": {
    "gn:admin1_code":"DI",
    "gn:admin2_code":"601.0",
    "gn:admin3_code":"60105.0",
    "gn:asciiname":"Colmera",
    "gn:country_code":"TL",
    "gn:dem":3,
    "gn:feature_class":"P",
    "gn:feature_code":"PPL",
    "gn:name":"Colmera",
    "gn:population":0,
    "gn:timezone":"Asia/Dili",
    "iso:country":"TL",
    "wof:name":"Colmera",
    "wof:placetype":"locality"
},
  "geometry": {"coordinates":[125.57089999999999,-8.55744],"type":"Point"}
}