{
  "type": "Feature",
  "properties": {
    "gn:admin1_code":"MT",
    "gn:admin2_code":"1106.0",
    "gn:admin3_code":"110604.0",
    "gn:asciiname":"Batara",
    "gn:country_code":"TL",
    "gn:dem":1213,
    "gn:feature_class":"P",
    "gn:feature_code":"PPL",
    "gn:name":"Batara",
    "gn:population":0,
    "gn:timezone":"Asia/Dili",
    "iso:country":"TL",
    "name:ceb_x_preferred":[
        "Batara"
    ],
    "name:deu_x_preferred":[
        "Batara"
    ],
    "name:fra_x_preferred":[
        "Batara"
    ],
    "name:pol_x_preferred":[
        "Batara"
    ],
    "name:swe_x_preferred":[
        "Batara"
    ],
    "wof:name":"Batara",
    "wof:placetype":"locality"
},
  "geometry": {"coordinates":[125.91667,-8.735],"type":"Point"}
}