{
  "type": "Feature",
  "properties": {
    "gn:admin1_code":"BO",
    "gn:admin2_code":"406.0",
    "gn:admin3_code":"40605.0",
    "gn:asciiname":"Manonia",
    "gn:country_code":"TL",
    "gn:dem":984,
    "gn:feature_class":"P",
    "gn:feature_code":"PPL",
    "gn:name":"Manonia",
    "gn:population":0,
    "gn:timezone":"Asia/Dili",
    "iso:country":"TL",
    "wof:name":"Manonia",
    "wof:placetype":"locality"
},
  "geometry": {"coordinates":[125.38583,-8.9875],"type":"Point"}
}