{
  "type": "Feature",
  "properties": {
    "gn:admin1_code":"BA",
    "gn:admin2_code":"306.0",
    "gn:admin3_code":"30602.0",
    "gn:asciiname":"Kaimalehoo",
    "gn:country_code":"TL",
    "gn:dem":468,
    "gn:feature_class":"P",
    "gn:feature_code":"PPL",
    "gn:name":"Kaimalehoo",
    "gn:population":0,
    "gn:timezone":"Asia/Dili",
    "iso:country":"TL",
    "wof:name":"Kaimalehoo",
    "wof:placetype":"locality"
},
  "geometry": {"coordinates":[126.42055999999999,-8.61306],"type":"Point"}
}