{
  "type": "Feature",
  "properties": {
    "gn:admin1_code":"MT",
    "gn:admin2_code":"1106.0",
    "gn:admin3_code":"110604.0",
    "gn:asciiname":"Balulin",
    "gn:country_code":"TL",
    "gn:dem":1124,
    "gn:feature_class":"P",
    "gn:feature_code":"PPL",
    "gn:name":"Balulin",
    "gn:population":0,
    "gn:timezone":"Asia/Dili",
    "iso:country":"TL",
    "wof:name":"Balulin",
    "wof:placetype":"locality"
},
  "geometry": {"coordinates":[125.90555999999999,-8.74611],"type":"Point"}
}