{
  "type": "Feature",
  "properties": {
    "gn:admin1_code":"BO",
    "gn:admin2_code":"404.0",
    "gn:admin3_code":"40402.0",
    "gn:asciiname":"Fatubessi",
    "gn:country_code":"TL",
    "gn:dem":55,
    "gn:feature_class":"P",
    "gn:feature_code":"PPL",
    "gn:name":"Fatubessi",
    "gn:population":0,
    "gn:timezone":"Asia/Dili",
    "iso:country":"TL",
    "name:deu_x_preferred":[
        "Fatubessi"
    ],
    "name:msa_x_preferred":[
        "Fatubessi"
    ],
    "name:tet_x_preferred":[
        "Fatubessi"
    ],
    "wof:name":"Fatubessi",
    "wof:placetype":"locality"
},
  "geometry": {"coordinates":[125.21193999999998,-8.79778],"type":"Point"}
}