{
  "type": "Feature",
  "properties": {
    "gn:admin1_code":"ER",
    "gn:admin2_code":"702.0",
    "gn:admin3_code":"70201.0",
    "gn:asciiname":"Tidibesse",
    "gn:country_code":"TL",
    "gn:dem":1336,
    "gn:feature_class":"P",
    "gn:feature_code":"PPL",
    "gn:name":"Tidibesse",
    "gn:population":0,
    "gn:timezone":"Asia/Dili",
    "iso:country":"TL",
    "wof:name":"Tidibesse",
    "wof:placetype":"locality"
},
  "geometry": {"coordinates":[125.38943999999999,-8.76139],"type":"Point"}
}