{
  "type": "Feature",
  "properties": {
    "gn:admin1_code":"AN",
    "gn:admin2_code":"101.0",
    "gn:admin3_code":"10102.0",
    "gn:asciiname":"Noulo",
    "gn:country_code":"TL",
    "gn:dem":597,
    "gn:feature_class":"P",
    "gn:feature_code":"PPL",
    "gn:name":"Noulo",
    "gn:population":0,
    "gn:timezone":"Asia/Dili",
    "iso:country":"TL",
    "wof:name":"Noulo",
    "wof:placetype":"locality"
},
  "geometry": {"coordinates":[125.53749999999999,-9.02944],"type":"Point"}
}