{
  "type": "Feature",
  "properties": {
    "gn:admin1_code":"DI",
    "gn:admin2_code":"606.0",
    "gn:admin3_code":"60602.0",
    "gn:asciiname":"Kulau",
    "gn:country_code":"TL",
    "gn:dem":253,
    "gn:feature_class":"P",
    "gn:feature_code":"PPL",
    "gn:name":"Kulau",
    "gn:population":0,
    "gn:timezone":"Asia/Dili",
    "iso:country":"TL",
    "name:ceb_x_preferred":[
        "Kulau"
    ],
    "name:dty_x_preferred":[
        "\u0915\u0941\u0932\u093e\u0909 \u0917\u093e\u0935\u093f\u0938"
    ],
    "name:mai_x_preferred":[
        "\u0915\u0941\u0932\u093e\u0909"
    ],
    "name:msa_x_preferred":[
        "Kulau"
    ],
    "name:nep_x_preferred":[
        "\u0915\u0941\u0932\u093e\u0909"
    ],
    "name:new_x_preferred":[
        "\u0915\u0941\u0932\u093e\u0909"
    ],
    "name:pol_x_preferred":[
        "Kulau"
    ],
    "wof:name":"Kulau",
    "wof:placetype":"locality"
},
  "geometry": {"coordinates":[125.60599999999999,-8.57313],"type":"Point"}
}