{
  "type": "Feature",
  "properties": {
    "gn:admin1_code":"AL",
    "gn:admin2_code":"201.0",
    "gn:admin3_code":"20101.0",
    "gn:asciiname":"Aissirimou",
    "gn:country_code":"TL",
    "gn:dem":930,
    "gn:feature_class":"P",
    "gn:feature_code":"PPL",
    "gn:name":"Aissirimou",
    "gn:population":0,
    "gn:timezone":"Asia/Dili",
    "iso:country":"TL",
    "name:ceb_x_preferred":[
        "Aissirimou"
    ],
    "name:deu_x_preferred":[
        "Aissirimou"
    ],
    "name:fas_x_preferred":[
        "\u0627\u06cc\u0633\u06cc\u0631\u06cc\u0645\u0648"
    ],
    "name:msa_x_preferred":[
        "Aisirimou"
    ],
    "name:por_x_preferred":[
        "Aissirimou"
    ],
    "name:tet_x_preferred":[
        "Aisirimou"
    ],
    "wof:name":"Aissirimou",
    "wof:placetype":"locality"
},
  "geometry": {"coordinates":[125.57146000000002,-8.72607],"type":"Point"}
}