{
  "type": "Feature",
  "properties": {
    "gn:admin1_code":"AL",
    "gn:admin2_code":"201.0",
    "gn:admin3_code":"20101.0",
    "gn:asciiname":"Aissirimou",
    "gn:country_code":"TL",
    "gn:dem":930,
    "gn:feature_class":"P",
    "gn:feature_code":"PPL",
    "gn:name":"Aissirimou",
    "gn:population":0,
    "gn:timezone":"Asia/Dili",
    "iso:country":"TL",
    "wof:name":"Aissirimou",
    "wof:placetype":"locality"
},
  "geometry": {"coordinates":[125.57146000000002,-8.72607],"type":"Point"}
}