{
  "type": "Feature",
  "properties": {
    "gn:admin1_code":"ER",
    "gn:admin2_code":"701.0",
    "gn:admin3_code":"70103.0",
    "gn:asciiname":"Fatada",
    "gn:country_code":"TL",
    "gn:dem":809,
    "gn:feature_class":"P",
    "gn:feature_code":"PPL",
    "gn:name":"Fatada",
    "gn:population":0,
    "gn:timezone":"Asia/Dili",
    "iso:country":"TL",
    "wof:name":"Fatada",
    "wof:placetype":"locality"
},
  "geometry": {"coordinates":[125.43528000000001,-8.70222],"type":"Point"}
}