{
  "type": "Feature",
  "properties": {
    "gn:admin1_code":"MT",
    "gn:admin2_code":"1104.0",
    "gn:admin3_code":"110401.0",
    "gn:asciiname":"Soibada",
    "gn:country_code":"TL",
    "gn:dem":701,
    "gn:feature_class":"P",
    "gn:feature_code":"PPL",
    "gn:name":"Soibada",
    "gn:population":0,
    "gn:timezone":"Asia/Dili",
    "iso:country":"TL",
    "name:deu_x_preferred":[
        "Soibada"
    ],
    "name:ita_x_preferred":[
        "Soibada"
    ],
    "name:tet_x_preferred":[
        "Soibada"
    ],
    "name:und_x_variant":[
        "Soilaoa",
        "Saibada"
    ],
    "wof:name":"Soibada",
    "wof:placetype":"locality"
},
  "geometry": {"coordinates":[125.93694000000001,-8.86056],"type":"Point"}
}