{
  "type": "Feature",
  "properties": {
    "gn:admin1_code":"LA",
    "gn:admin2_code":"902.0",
    "gn:admin3_code":"90207.0",
    "gn:asciiname":"Maina 2",
    "gn:country_code":"TL",
    "gn:dem":517,
    "gn:feature_class":"P",
    "gn:feature_code":"PPL",
    "gn:name":"Maina 2",
    "gn:population":0,
    "gn:timezone":"Asia/Dili",
    "iso:country":"TL",
    "wof:name":"Maina 2",
    "wof:placetype":"locality"
},
  "geometry": {"coordinates":[126.88278,-8.46583],"type":"Point"}
}