{
  "type": "Feature",
  "properties": {
    "gn:admin1_code":"ER",
    "gn:admin2_code":"702.0",
    "gn:admin3_code":"70203.0",
    "gn:asciiname":"Saheu",
    "gn:country_code":"TL",
    "gn:dem":1184,
    "gn:feature_class":"P",
    "gn:feature_code":"PPL",
    "gn:name":"Saheu",
    "gn:population":0,
    "gn:timezone":"Asia/Dili",
    "iso:country":"TL",
    "wof:name":"Saheu",
    "wof:placetype":"locality"
},
  "geometry": {"coordinates":[125.40806000000001,-8.74444],"type":"Point"}
}