{
  "type": "Feature",
  "properties": {
    "gn:admin1_code":"BA",
    "gn:admin2_code":"301.0",
    "gn:admin3_code":"30101.0",
    "gn:asciiname":"Bahu",
    "gn:country_code":"TL",
    "gn:dem":404,
    "gn:feature_class":"P",
    "gn:feature_code":"PPL",
    "gn:name":"Bahu",
    "gn:population":0,
    "gn:timezone":"Asia/Dili",
    "iso:country":"TL",
    "wof:name":"Bahu",
    "wof:placetype":"locality"
},
  "geometry": {"coordinates":[126.45,-8.46667],"type":"Point"}
}