{
  "type": "Feature",
  "properties": {
    "gn:admin1_code":"DI",
    "gn:admin2_code":"606.0",
    "gn:admin3_code":"60603.0",
    "gn:asciiname":"Lunukhun",
    "gn:country_code":"TL",
    "gn:dem":64,
    "gn:feature_class":"P",
    "gn:feature_code":"PPL",
    "gn:name":"Lunukhun",
    "gn:population":0,
    "gn:timezone":"Asia/Dili",
    "iso:country":"TL",
    "wof:name":"Lunukhun",
    "wof:placetype":"locality"
},
  "geometry": {"coordinates":[125.61906,-8.56533],"type":"Point"}
}