{
  "type": "Feature",
  "properties": {
    "gn:admin1_code":"BO",
    "gn:admin2_code":"404.0",
    "gn:admin3_code":"40401.0",
    "gn:asciiname":"Melelaran",
    "gn:country_code":"TL",
    "gn:dem":19,
    "gn:feature_class":"P",
    "gn:feature_code":"PPL",
    "gn:name":"Melelaran",
    "gn:population":0,
    "gn:timezone":"Asia/Dili",
    "iso:country":"TL",
    "wof:name":"Melelaran",
    "wof:placetype":"locality"
},
  "geometry": {"coordinates":[125.04111,-8.8625],"type":"Point"}
}