{
  "type": "Feature",
  "properties": {
    "gn:admin1_code":"LA",
    "gn:admin2_code":"903.0",
    "gn:admin3_code":"90305.0",
    "gn:asciiname":"Iraluroto",
    "gn:country_code":"TL",
    "gn:dem":77,
    "gn:feature_class":"P",
    "gn:feature_code":"PPL",
    "gn:name":"Iraluroto",
    "gn:population":0,
    "gn:timezone":"Asia/Dili",
    "iso:country":"TL",
    "wof:name":"Iraluroto",
    "wof:placetype":"locality"
},
  "geometry": {"coordinates":[126.84583000000001,-8.74472],"type":"Point"}
}