{
  "type": "Feature",
  "properties": {
    "gn:admin1_code":"BA",
    "gn:admin2_code":"302.0",
    "gn:admin3_code":"30202.0",
    "gn:asciiname":"Kaikasalan",
    "gn:country_code":"TL",
    "gn:dem":18,
    "gn:feature_class":"P",
    "gn:feature_code":"PPL",
    "gn:name":"Kaikasalan",
    "gn:population":0,
    "gn:timezone":"Asia/Dili",
    "iso:country":"TL",
    "name:und_x_variant":[
        "Kaikasalari"
    ],
    "wof:name":"Kaikasalan",
    "wof:placetype":"locality"
},
  "geometry": {"coordinates":[126.58508,-8.47791],"type":"Point"}
}