{
  "type": "Feature",
  "properties": {
    "gn:admin1_code":"MF",
    "gn:admin2_code":"1001.0",
    "gn:admin3_code":"100103.0",
    "gn:asciiname":"Turon",
    "gn:country_code":"TL",
    "gn:dem":301,
    "gn:feature_class":"P",
    "gn:feature_code":"PPL",
    "gn:name":"Turon",
    "gn:population":0,
    "gn:timezone":"Asia/Dili",
    "iso:country":"TL",
    "name:ceb_x_preferred":[
        "Turon"
    ],
    "name:deu_x_preferred":[
        "Turon"
    ],
    "name:epo_x_preferred":[
        "Tur\u00f3n"
    ],
    "name:ita_x_preferred":[
        "Turon"
    ],
    "name:nld_x_preferred":[
        "Turon"
    ],
    "name:spa_x_preferred":[
        "Tur\u00f3n"
    ],
    "name:swe_x_preferred":[
        "Turon"
    ],
    "name:uzb_x_preferred":[
        "Turon"
    ],
    "wof:name":"Turon",
    "wof:placetype":"locality"
},
  "geometry": {"coordinates":[125.66306000000002,-9.03639],"type":"Point"}
}