{
  "type": "Feature",
  "properties": {
    "gn:admin1_code":"MT",
    "gn:admin2_code":"1103.0",
    "gn:admin3_code":"110302.0",
    "gn:asciiname":"Hahihoho",
    "gn:country_code":"TL",
    "gn:dem":83,
    "gn:feature_class":"P",
    "gn:feature_code":"PPL",
    "gn:name":"Hahihoho",
    "gn:population":0,
    "gn:timezone":"Asia/Dili",
    "iso:country":"TL",
    "wof:name":"Hahihoho",
    "wof:placetype":"locality"
},
  "geometry": {"coordinates":[125.92222,-8.55222],"type":"Point"}
}