{
  "type": "Feature",
  "properties": {
    "gn:admin1_code":"AN",
    "gn:admin2_code":"104.0",
    "gn:admin3_code":"10402.0",
    "gn:asciiname":"Boramba",
    "gn:country_code":"TL",
    "gn:dem":332,
    "gn:feature_class":"P",
    "gn:feature_code":"PPL",
    "gn:name":"Boramba",
    "gn:population":0,
    "gn:timezone":"Asia/Dili",
    "iso:country":"TL",
    "wof:name":"Boramba",
    "wof:placetype":"locality"
},
  "geometry": {"coordinates":[125.64833,-9.11278],"type":"Point"}
}