{
  "type": "Feature",
  "properties": {
    "gn:admin1_code":"ER",
    "gn:admin2_code":"705.0",
    "gn:admin3_code":"70504.0",
    "gn:asciiname":"Betupu",
    "gn:country_code":"TL",
    "gn:dem":102,
    "gn:feature_class":"P",
    "gn:feature_code":"PPL",
    "gn:name":"Betupu",
    "gn:population":0,
    "gn:timezone":"Asia/Dili",
    "iso:country":"TL",
    "wof:name":"Betupu",
    "wof:placetype":"locality"
},
  "geometry": {"coordinates":[125.27278,-8.80139],"type":"Point"}
}