{
  "type": "Feature",
  "properties": {
    "gn:admin1_code":"BA",
    "gn:admin2_code":"301.0",
    "gn:admin3_code":"30102.0",
    "gn:asciiname":"Triloko",
    "gn:country_code":"TL",
    "gn:dem":270,
    "gn:feature_class":"P",
    "gn:feature_code":"PPL",
    "gn:name":"Triloko",
    "gn:population":0,
    "gn:timezone":"Asia/Dili",
    "iso:country":"TL",
    "wof:name":"Triloko",
    "wof:placetype":"locality"
},
  "geometry": {"coordinates":[126.32355,-8.48952],"type":"Point"}
}