{
  "type": "Feature",
  "properties": {
    "gn:admin1_code":"CO",
    "gn:admin2_code":"506.0",
    "gn:admin3_code":"50601.0",
    "gn:asciiname":"Fatukmetan",
    "gn:country_code":"TL",
    "gn:dem":465,
    "gn:feature_class":"P",
    "gn:feature_code":"PPL",
    "gn:name":"Fatukmetan",
    "gn:population":0,
    "gn:timezone":"Asia/Dili",
    "iso:country":"TL",
    "wof:name":"Fatukmetan",
    "wof:placetype":"locality"
},
  "geometry": {"coordinates":[125.09193999999999,-9.34833],"type":"Point"}
}