{
  "type": "Feature",
  "properties": {
    "gn:admin1_code":"BA",
    "gn:admin2_code":"304.0",
    "gn:admin3_code":"30403.0",
    "gn:asciiname":"Baguia",
    "gn:country_code":"TL",
    "gn:dem":322,
    "gn:feature_class":"P",
    "gn:feature_code":"PPL",
    "gn:name":"Baguia",
    "gn:population":0,
    "gn:timezone":"Asia/Dili",
    "iso:country":"TL",
    "wof:name":"Baguia",
    "wof:placetype":"locality"
},
  "geometry": {"coordinates":[126.66139,-8.62778],"type":"Point"}
}