{
  "type": "Feature",
  "properties": {
    "gn:admin1_code":"ER",
    "gn:admin2_code":"702.0",
    "gn:admin3_code":"70201.0",
    "gn:asciiname":"Ulmera",
    "gn:country_code":"TL",
    "gn:dem":1171,
    "gn:feature_class":"P",
    "gn:feature_code":"PPL",
    "gn:name":"Ulmera",
    "gn:population":0,
    "gn:timezone":"Asia/Dili",
    "iso:country":"TL",
    "name:und_x_variant":[
        "Vila de Emera",
        "Vila da Ermera",
        "Ermera"
    ],
    "wof:name":"Ulmera",
    "wof:placetype":"locality"
},
  "geometry": {"coordinates":[125.39694,-8.75222],"type":"Point"}
}