{
  "type": "Feature",
  "properties": {
    "gn:admin1_code":"ER",
    "gn:admin2_code":"702.0",
    "gn:admin3_code":"70201.0",
    "gn:asciiname":"Ulmera",
    "gn:country_code":"TL",
    "gn:dem":1171,
    "gn:feature_class":"P",
    "gn:feature_code":"PPL",
    "gn:name":"Ulmera",
    "gn:population":0,
    "gn:timezone":"Asia/Dili",
    "iso:country":"TL",
    "name:afr_x_preferred":[
        "Ermera"
    ],
    "name:deu_x_preferred":[
        "Ermera"
    ],
    "name:fra_x_preferred":[
        "Ermera"
    ],
    "name:ita_x_preferred":[
        "Ermera"
    ],
    "name:lit_x_preferred":[
        "Ermera"
    ],
    "name:nld_x_preferred":[
        "Ermera"
    ],
    "name:pol_x_preferred":[
        "Ermera"
    ],
    "name:por_x_preferred":[
        "Ermera"
    ],
    "name:tet_x_preferred":[
        "Ermera"
    ],
    "name:und_x_variant":[
        "Vila de Emera",
        "Vila da Ermera"
    ],
    "name:urd_x_preferred":[
        "\u0639\u0631\u0645\u06cc\u0631\u0627"
    ],
    "wof:name":"Ulmera",
    "wof:placetype":"locality"
},
  "geometry": {"coordinates":[125.39694,-8.75222],"type":"Point"}
}