{
  "type": "Feature",
  "properties": {
    "gn:admin1_code":"VI",
    "gn:admin2_code":"1301.0",
    "gn:admin3_code":"130103.0",
    "gn:asciiname":"Tanalale",
    "gn:country_code":"TL",
    "gn:dem":16,
    "gn:feature_class":"P",
    "gn:feature_code":"PPL",
    "gn:name":"Tanalale",
    "gn:population":0,
    "gn:timezone":"Asia/Dili",
    "iso:country":"TL",
    "wof:name":"Tanalale",
    "wof:placetype":"locality"
},
  "geometry": {"coordinates":[126.68832999999999,-8.75417],"type":"Point"}
}