{
  "type": "Feature",
  "properties": {
    "gn:admin1_code":"ER",
    "gn:admin2_code":"705.0",
    "gn:admin3_code":"70503.0",
    "gn:asciiname":"Aculau",
    "gn:country_code":"TL",
    "gn:dem":51,
    "gn:feature_class":"P",
    "gn:feature_code":"PPL",
    "gn:name":"Aculau",
    "gn:population":0,
    "gn:timezone":"Asia/Dili",
    "iso:country":"TL",
    "wof:name":"Aculau",
    "wof:placetype":"locality"
},
  "geometry": {"coordinates":[125.2075,-8.75833],"type":"Point"}
}