{
  "type": "Feature",
  "properties": {
    "gn:admin1_code":"MT",
    "gn:admin2_code":"1101.0",
    "gn:admin3_code":"110105.0",
    "gn:asciiname":"Iliheu",
    "gn:country_code":"TL",
    "gn:dem":131,
    "gn:feature_class":"P",
    "gn:feature_code":"PPL",
    "gn:name":"Iliheu",
    "gn:population":0,
    "gn:timezone":"Asia/Dili",
    "iso:country":"TL",
    "wof:name":"Iliheu",
    "wof:placetype":"locality"
},
  "geometry": {"coordinates":[125.95,-8.53333],"type":"Point"}
}