{
  "type": "Feature",
  "properties": {
    "gn:admin1_code":"MT",
    "gn:admin2_code":"1106.0",
    "gn:admin3_code":"110606.0",
    "gn:asciiname":"Ruhetun",
    "gn:country_code":"TL",
    "gn:dem":283,
    "gn:feature_class":"P",
    "gn:feature_code":"PPL",
    "gn:name":"Ruhetun",
    "gn:population":0,
    "gn:timezone":"Asia/Dili",
    "iso:country":"TL",
    "wof:name":"Ruhetun",
    "wof:placetype":"locality"
},
  "geometry": {"coordinates":[125.97611000000001,-8.64222],"type":"Point"}
}