{
  "type": "Feature",
  "properties": {
    "gn:admin1_code":"BO",
    "gn:admin2_code":"401.0",
    "gn:admin3_code":"40102.0",
    "gn:asciiname":"Dirumdesan",
    "gn:country_code":"TL",
    "gn:dem":232,
    "gn:feature_class":"P",
    "gn:feature_code":"PPL",
    "gn:name":"Dirumdesan",
    "gn:population":0,
    "gn:timezone":"Asia/Dili",
    "iso:country":"TL",
    "wof:name":"Dirumdesan",
    "wof:placetype":"locality"
},
  "geometry": {"coordinates":[125.22111,-8.98083],"type":"Point"}
}