{
  "type": "Feature",
  "properties": {
    "gn:admin1_code":"ER",
    "gn:admin2_code":"703.0",
    "gn:admin3_code":"70303.0",
    "gn:asciiname":"Hatugeo",
    "gn:country_code":"TL",
    "gn:dem":1699,
    "gn:feature_class":"P",
    "gn:feature_code":"PPL",
    "gn:name":"Hatugeo",
    "gn:population":0,
    "gn:timezone":"Asia/Dili",
    "iso:country":"TL",
    "wof:name":"Hatugeo",
    "wof:placetype":"locality"
},
  "geometry": {"coordinates":[125.43083,-8.88917],"type":"Point"}
}