{
  "type": "Feature",
  "properties": {
    "gn:admin1_code":"OE",
    "gn:admin2_code":"1202.0",
    "gn:admin3_code":"120201.0",
    "gn:asciiname":"Oelbabai",
    "gn:country_code":"TL",
    "gn:dem":581,
    "gn:feature_class":"P",
    "gn:feature_code":"PPL",
    "gn:name":"Oelbabai",
    "gn:population":0,
    "gn:timezone":"Asia/Dili",
    "iso:country":"TL",
    "wof:name":"Oelbabai",
    "wof:placetype":"locality"
},
  "geometry": {"coordinates":[124.23667,-9.35861],"type":"Point"}
}