{
  "type": "Feature",
  "properties": {
    "gn:admin1_code":"BA",
    "gn:admin2_code":"306.0",
    "gn:admin3_code":"30603.0",
    "gn:asciiname":"Kaubai",
    "gn:country_code":"TL",
    "gn:dem":841,
    "gn:feature_class":"P",
    "gn:feature_code":"PPL",
    "gn:name":"Kaubai",
    "gn:population":0,
    "gn:timezone":"Asia/Dili",
    "iso:country":"TL",
    "wof:name":"Kaubai",
    "wof:placetype":"locality"
},
  "geometry": {"coordinates":[126.4075,-8.64083],"type":"Point"}
}