{
  "type": "Feature",
  "properties": {
    "gn:admin1_code":"BO",
    "gn:admin2_code":"403.0",
    "gn:admin3_code":"40304.0",
    "gn:asciiname":"Oetapo",
    "gn:country_code":"TL",
    "gn:dem":312,
    "gn:feature_class":"P",
    "gn:feature_code":"PPL",
    "gn:name":"Oetapo",
    "gn:population":0,
    "gn:timezone":"Asia/Dili",
    "iso:country":"TL",
    "wof:name":"Oetapo",
    "wof:placetype":"locality"
},
  "geometry": {"coordinates":[125.06583000000001,-8.90806],"type":"Point"}
}