{
  "type": "Feature",
  "properties": {
    "gn:admin1_code":"LA",
    "gn:admin2_code":"902.0",
    "gn:admin3_code":"90210.0",
    "gn:asciiname":"Raano",
    "gn:country_code":"TL",
    "gn:dem":220,
    "gn:feature_class":"P",
    "gn:feature_code":"PPL",
    "gn:name":"Raano",
    "gn:population":0,
    "gn:timezone":"Asia/Dili",
    "iso:country":"TL",
    "wof:name":"Raano",
    "wof:placetype":"locality"
},
  "geometry": {"coordinates":[126.85444,-8.43667],"type":"Point"}
}