{
  "type": "Feature",
  "properties": {
    "gn:admin1_code":"VI",
    "gn:admin2_code":"1301.0",
    "gn:admin3_code":"130104.0",
    "gn:asciiname":"Uaimare",
    "gn:country_code":"TL",
    "gn:dem":366,
    "gn:feature_class":"P",
    "gn:feature_code":"PPL",
    "gn:name":"Uaimare",
    "gn:population":0,
    "gn:timezone":"Asia/Dili",
    "iso:country":"TL",
    "wof:name":"Uaimare",
    "wof:placetype":"locality"
},
  "geometry": {"coordinates":[126.66889,-8.66583],"type":"Point"}
}