{
  "type": "Feature",
  "properties": {
    "gn:admin1_code":"MT",
    "gn:admin2_code":"1102.0",
    "gn:admin3_code":"110201.0",
    "gn:asciiname":"Lenao",
    "gn:country_code":"TL",
    "gn:dem":23,
    "gn:feature_class":"P",
    "gn:feature_code":"PPL",
    "gn:name":"Lenao",
    "gn:population":0,
    "gn:timezone":"Asia/Dili",
    "iso:country":"TL",
    "wof:name":"Lenao",
    "wof:placetype":"locality"
},
  "geometry": {"coordinates":[126.16667,-8.53333],"type":"Point"}
}