{
  "type": "Feature",
  "properties": {
    "gn:admin1_code":"MT",
    "gn:admin2_code":"1103.0",
    "gn:admin3_code":"110302.0",
    "gn:asciiname":"Condar",
    "gn:country_code":"TL",
    "gn:dem":51,
    "gn:feature_class":"P",
    "gn:feature_code":"PPL",
    "gn:name":"Condar",
    "gn:population":0,
    "gn:timezone":"Asia/Dili",
    "iso:country":"TL",
    "wof:name":"Condar",
    "wof:placetype":"locality"
},
  "geometry": {"coordinates":[125.96138999999999,-8.53278],"type":"Point"}
}