{
  "type": "Feature",
  "properties": {
    "gn:admin1_code":"BO",
    "gn:admin2_code":"404.0",
    "gn:admin3_code":"40403.0",
    "gn:asciiname":"Goulete",
    "gn:country_code":"TL",
    "gn:dem":205,
    "gn:feature_class":"P",
    "gn:feature_code":"PPL",
    "gn:name":"Goulete",
    "gn:population":0,
    "gn:timezone":"Asia/Dili",
    "iso:country":"TL",
    "wof:name":"Goulete",
    "wof:placetype":"locality"
},
  "geometry": {"coordinates":[125.14583,-8.80861],"type":"Point"}
}