{
  "type": "Feature",
  "properties": {
    "gn:admin1_code":"OE",
    "gn:admin2_code":"1202.0",
    "gn:admin3_code":"120204.0",
    "gn:asciiname":"Netensuan",
    "gn:country_code":"TL",
    "gn:dem":577,
    "gn:feature_class":"P",
    "gn:feature_code":"PPL",
    "gn:name":"Netensuan",
    "gn:population":0,
    "gn:timezone":"Asia/Dili",
    "iso:country":"TL",
    "wof:name":"Netensuan",
    "wof:placetype":"locality"
},
  "geometry": {"coordinates":[124.26596000000001,-9.3463],"type":"Point"}
}