{
  "type": "Feature",
  "properties": {
    "gn:admin1_code":"OE",
    "gn:admin2_code":"1203.0",
    "gn:admin3_code":"120303.0",
    "gn:asciiname":"Pune",
    "gn:country_code":"TL",
    "gn:dem":330,
    "gn:feature_class":"P",
    "gn:feature_code":"PPL",
    "gn:name":"Pune",
    "gn:population":0,
    "gn:timezone":"Asia/Dili",
    "iso:country":"TL",
    "wof:name":"Pune",
    "wof:placetype":"locality"
},
  "geometry": {"coordinates":[124.31722000000001,-9.36944],"type":"Point"}
}