{
  "type": "Feature",
  "properties": {
    "gn:admin1_code":"ER",
    "gn:admin2_code":"704.0",
    "gn:admin3_code":"70408.0",
    "gn:asciiname":"Laubono",
    "gn:country_code":"TL",
    "gn:dem":499,
    "gn:feature_class":"P",
    "gn:feature_code":"PPL",
    "gn:name":"Laubono",
    "gn:population":0,
    "gn:timezone":"Asia/Dili",
    "iso:country":"TL",
    "wof:name":"Laubono",
    "wof:placetype":"locality"
},
  "geometry": {"coordinates":[125.34999999999999,-8.93333],"type":"Point"}
}