{
  "type": "Feature",
  "properties": {
    "gn:admin1_code":"BA",
    "gn:admin2_code":"304.0",
    "gn:admin3_code":"30401.0",
    "gn:asciiname":"Lacolu",
    "gn:country_code":"TL",
    "gn:dem":828,
    "gn:feature_class":"P",
    "gn:feature_code":"PPL",
    "gn:name":"Lacolu",
    "gn:population":0,
    "gn:timezone":"Asia/Dili",
    "iso:country":"TL",
    "wof:name":"Lacolu",
    "wof:placetype":"locality"
},
  "geometry": {"coordinates":[126.61972,-8.66944],"type":"Point"}
}