{
  "type": "Feature",
  "properties": {
    "gn:admin1_code":"ER",
    "gn:admin2_code":"705.0",
    "gn:admin3_code":"70507.0",
    "gn:asciiname":"Aibote",
    "gn:country_code":"TL",
    "gn:dem":765,
    "gn:feature_class":"P",
    "gn:feature_code":"PPL",
    "gn:name":"Aibote",
    "gn:population":0,
    "gn:timezone":"Asia/Dili",
    "iso:country":"TL",
    "wof:name":"Aibote",
    "wof:placetype":"locality"
},
  "geometry": {"coordinates":[125.31694,-8.80333],"type":"Point"}
}