{
  "type": "Feature",
  "properties": {
    "gn:admin1_code":"BA",
    "gn:admin2_code":"303.0",
    "gn:admin3_code":"30303.0",
    "gn:asciiname":"Lebene",
    "gn:country_code":"TL",
    "gn:dem":550,
    "gn:feature_class":"P",
    "gn:feature_code":"PPL",
    "gn:name":"Lebene",
    "gn:population":0,
    "gn:timezone":"Asia/Dili",
    "iso:country":"TL",
    "wof:name":"Lebene",
    "wof:placetype":"locality"
},
  "geometry": {"coordinates":[126.54833000000001,-8.59556],"type":"Point"}
}