{
  "type": "Feature",
  "properties": {
    "gn:admin1_code":"VI",
    "gn:admin2_code":"1304.0",
    "gn:admin3_code":"130406.0",
    "gn:asciiname":"Umaliurai",
    "gn:country_code":"TL",
    "gn:dem":75,
    "gn:feature_class":"P",
    "gn:feature_code":"PPL",
    "gn:name":"Umaliurai",
    "gn:population":0,
    "gn:timezone":"Asia/Dili",
    "iso:country":"TL",
    "wof:name":"Umaliurai",
    "wof:placetype":"locality"
},
  "geometry": {"coordinates":[126.35193999999998,-8.85444],"type":"Point"}
}