{
  "type": "Feature",
  "properties": {
    "gn:admin1_code":"AL",
    "gn:admin2_code":"201.0",
    "gn:admin3_code":"20108.0",
    "gn:asciiname":"Aitoi",
    "gn:country_code":"TL",
    "gn:dem":943,
    "gn:feature_class":"P",
    "gn:feature_code":"PPL",
    "gn:name":"Aitoi",
    "gn:population":0,
    "gn:timezone":"Asia/Dili",
    "iso:country":"TL",
    "wof:name":"Aitoi",
    "wof:placetype":"locality"
},
  "geometry": {"coordinates":[125.56537,-8.71445],"type":"Point"}
}