{
  "type": "Feature",
  "properties": {
    "gn:admin1_code":"ER",
    "gn:admin2_code":"703.0",
    "gn:admin3_code":"70302.0",
    "gn:asciiname":"Hauho",
    "gn:country_code":"TL",
    "gn:dem":1185,
    "gn:feature_class":"P",
    "gn:feature_code":"PPL",
    "gn:name":"Hauho",
    "gn:population":0,
    "gn:timezone":"Asia/Dili",
    "iso:country":"TL",
    "wof:name":"Hauho",
    "wof:placetype":"locality"
},
  "geometry": {"coordinates":[125.40722,-8.82222],"type":"Point"}
}