{
  "type": "Feature",
  "properties": {
    "gn:admin1_code":"ER",
    "gn:admin2_code":"703.0",
    "gn:admin3_code":"70302.0",
    "gn:asciiname":"Hauho",
    "gn:country_code":"TL",
    "gn:dem":1185,
    "gn:feature_class":"P",
    "gn:feature_code":"PPL",
    "gn:name":"Hauho",
    "gn:population":0,
    "gn:timezone":"Asia/Dili",
    "iso:country":"TL",
    "name:ceb_x_preferred":[
        "Hauho"
    ],
    "name:deu_x_preferred":[
        "Hauho"
    ],
    "name:est_x_preferred":[
        "Hauho vald"
    ],
    "name:eus_x_preferred":[
        "Hauho"
    ],
    "name:fin_x_preferred":[
        "Hauho"
    ],
    "name:fra_x_preferred":[
        "Hauho"
    ],
    "name:ita_x_preferred":[
        "Hauho"
    ],
    "name:nld_x_preferred":[
        "Hauho"
    ],
    "name:nor_x_preferred":[
        "Hauho"
    ],
    "name:por_x_preferred":[
        "Hauho"
    ],
    "name:ron_x_preferred":[
        "Hauho"
    ],
    "name:sme_x_preferred":[
        "Hauho"
    ],
    "name:swe_x_preferred":[
        "Hauho"
    ],
    "wof:name":"Hauho",
    "wof:placetype":"locality"
},
  "geometry": {"coordinates":[125.40722,-8.82222],"type":"Point"}
}