{
  "type": "Feature",
  "properties": {
    "gn:admin1_code":"LI",
    "gn:admin2_code":"803.0",
    "gn:admin3_code":"80301.0",
    "gn:asciiname":"Glai",
    "gn:country_code":"TL",
    "gn:dem":63,
    "gn:feature_class":"P",
    "gn:feature_code":"PPL",
    "gn:name":"Glai",
    "gn:population":0,
    "gn:timezone":"Asia/Dili",
    "iso:country":"TL",
    "wof:name":"Glai",
    "wof:placetype":"locality"
},
  "geometry": {"coordinates":[125.20083,-8.73389],"type":"Point"}
}