{
  "type": "Feature",
  "properties": {
    "gn:admin1_code":"DI",
    "gn:admin2_code":"604.0",
    "gn:admin3_code":"60404.0",
    "gn:asciiname":"Maulako",
    "gn:country_code":"TL",
    "gn:dem":330,
    "gn:feature_class":"P",
    "gn:feature_code":"PPL",
    "gn:name":"Maulako",
    "gn:population":0,
    "gn:timezone":"Asia/Dili",
    "iso:country":"TL",
    "wof:name":"Maulako",
    "wof:placetype":"locality"
},
  "geometry": {"coordinates":[125.57861,-8.28083],"type":"Point"}
}