{
  "type": "Feature",
  "properties": {
    "gn:admin1_code":"MF",
    "gn:admin2_code":"1001.0",
    "gn:admin3_code":"100102.0",
    "gn:asciiname":"Fahiluhan",
    "gn:country_code":"TL",
    "gn:dem":1100,
    "gn:feature_class":"P",
    "gn:feature_code":"PPL",
    "gn:name":"Fahiluhan",
    "gn:population":0,
    "gn:timezone":"Asia/Dili",
    "iso:country":"TL",
    "wof:name":"Fahiluhan",
    "wof:placetype":"locality"
},
  "geometry": {"coordinates":[125.62611,-8.93611],"type":"Point"}
}