{
  "type": "Feature",
  "properties": {
    "gn:admin1_code":"VI",
    "gn:admin2_code":"1304.0",
    "gn:admin3_code":"130403.0",
    "gn:asciiname":"Maroman",
    "gn:country_code":"TL",
    "gn:dem":38,
    "gn:feature_class":"P",
    "gn:feature_code":"PPL",
    "gn:name":"Maroman",
    "gn:population":0,
    "gn:timezone":"Asia/Dili",
    "iso:country":"TL",
    "wof:name":"Maroman",
    "wof:placetype":"locality"
},
  "geometry": {"coordinates":[126.36861,-8.88111],"type":"Point"}
}