{
  "type": "Feature",
  "properties": {
    "gn:admin1_code":"AN",
    "gn:admin2_code":"102.0",
    "gn:admin3_code":"10201.0",
    "gn:asciiname":"Haotio",
    "gn:country_code":"TL",
    "gn:dem":1465,
    "gn:feature_class":"P",
    "gn:feature_code":"PPL",
    "gn:name":"Haotio",
    "gn:population":0,
    "gn:timezone":"Asia/Dili",
    "iso:country":"TL",
    "wof:name":"Haotio",
    "wof:placetype":"locality"
},
  "geometry": {"coordinates":[125.58472,-8.91056],"type":"Point"}
}