{
  "type": "Feature",
  "properties": {
    "gn:admin1_code":"AN",
    "gn:admin2_code":"103.0",
    "gn:admin3_code":"10301.0",
    "gn:asciiname":"Rileko",
    "gn:country_code":"TL",
    "gn:dem":1588,
    "gn:feature_class":"P",
    "gn:feature_code":"PPL",
    "gn:name":"Rileko",
    "gn:population":0,
    "gn:timezone":"Asia/Dili",
    "iso:country":"TL",
    "wof:name":"Rileko",
    "wof:placetype":"locality"
},
  "geometry": {"coordinates":[125.59166999999999,-8.83222],"type":"Point"}
}