{
  "type": "Feature",
  "properties": {
    "gn:admin1_code":"ER",
    "gn:admin2_code":"705.0",
    "gn:admin3_code":"70502.0",
    "gn:asciiname":"Gomhaei",
    "gn:country_code":"TL",
    "gn:dem":1379,
    "gn:feature_class":"P",
    "gn:feature_code":"PPL",
    "gn:name":"Gomhaei",
    "gn:population":0,
    "gn:timezone":"Asia/Dili",
    "iso:country":"TL",
    "wof:name":"Gomhaei",
    "wof:placetype":"locality"
},
  "geometry": {"coordinates":[125.37639,-8.78361],"type":"Point"}
}