{
  "type": "Feature",
  "properties": {
    "gn:admin1_code":"BO",
    "gn:admin2_code":"406.0",
    "gn:admin3_code":"40608.0",
    "gn:asciiname":"Helikei",
    "gn:country_code":"TL",
    "gn:dem":554,
    "gn:feature_class":"P",
    "gn:feature_code":"PPL",
    "gn:name":"Helikei",
    "gn:population":0,
    "gn:timezone":"Asia/Dili",
    "iso:country":"TL",
    "wof:name":"Helikei",
    "wof:placetype":"locality"
},
  "geometry": {"coordinates":[125.36297,-9.07086],"type":"Point"}
}