{
  "type": "Feature",
  "properties": {
    "gn:admin1_code":"BO",
    "gn:admin2_code":"406.0",
    "gn:admin3_code":"40613.0",
    "gn:asciiname":"Holgen",
    "gn:country_code":"TL",
    "gn:dem":1007,
    "gn:feature_class":"P",
    "gn:feature_code":"PPL",
    "gn:name":"Holgen",
    "gn:population":0,
    "gn:timezone":"Asia/Dili",
    "iso:country":"TL",
    "wof:name":"Holgen",
    "wof:placetype":"locality"
},
  "geometry": {"coordinates":[125.28694,-9.02861],"type":"Point"}
}