{
  "type": "Feature",
  "properties": {
    "gn:admin1_code":"LI",
    "gn:admin2_code":"803.0",
    "gn:admin3_code":"80301.0",
    "gn:asciiname":"Watubau",
    "gn:country_code":"TL",
    "gn:dem":700,
    "gn:feature_class":"P",
    "gn:feature_code":"PPL",
    "gn:name":"Watubau",
    "gn:population":0,
    "gn:timezone":"Asia/Dili",
    "iso:country":"TL",
    "wof:name":"Watubau",
    "wof:placetype":"locality"
},
  "geometry": {"coordinates":[125.2625,-8.64972],"type":"Point"}
}