{
  "type": "Feature",
  "properties": {
    "gn:admin1_code":"BO",
    "gn:admin2_code":"402.0",
    "gn:admin3_code":"40202.0",
    "gn:asciiname":"Malilia",
    "gn:country_code":"TL",
    "gn:dem":340,
    "gn:feature_class":"P",
    "gn:feature_code":"PPL",
    "gn:name":"Malilia",
    "gn:population":0,
    "gn:timezone":"Asia/Dili",
    "iso:country":"TL",
    "wof:name":"Malilia",
    "wof:placetype":"locality"
},
  "geometry": {"coordinates":[125.30028,-8.90944],"type":"Point"}
}