{
  "type": "Feature",
  "properties": {
    "gn:admin1_code":"MF",
    "gn:admin2_code":"1001.0",
    "gn:admin3_code":"100105.0",
    "gn:asciiname":"Dai-Sua",
    "gn:country_code":"TL",
    "gn:dem":195,
    "gn:feature_class":"P",
    "gn:feature_code":"PPL",
    "gn:name":"Dai-Sua",
    "gn:population":0,
    "gn:timezone":"Asia/Dili",
    "iso:country":"TL",
    "wof:name":"Dai-Sua",
    "wof:placetype":"locality"
},
  "geometry": {"coordinates":[125.68333,-9.06667],"type":"Point"}
}