{
  "type": "Feature",
  "properties": {
    "gn:admin1_code":"MF",
    "gn:admin2_code":"1002.0",
    "gn:admin3_code":"100203.0",
    "gn:asciiname":"Feriksare",
    "gn:country_code":"TL",
    "gn:dem":55,
    "gn:feature_class":"P",
    "gn:feature_code":"PPL",
    "gn:name":"Feriksare",
    "gn:population":0,
    "gn:timezone":"Asia/Dili",
    "iso:country":"TL",
    "wof:name":"Feriksare",
    "wof:placetype":"locality"
},
  "geometry": {"coordinates":[125.78348,-9.10346],"type":"Point"}
}