{
  "type": "Feature",
  "properties": {
    "gn:admin1_code":"VI",
    "gn:admin2_code":"1304.0",
    "gn:admin3_code":"130407.0",
    "gn:asciiname":"Cabaira-Oan",
    "gn:country_code":"TL",
    "gn:dem":46,
    "gn:feature_class":"P",
    "gn:feature_code":"PPL",
    "gn:name":"Cabaira-Oan",
    "gn:population":0,
    "gn:timezone":"Asia/Dili",
    "iso:country":"TL",
    "wof:name":"Cabaira-Oan",
    "wof:placetype":"locality"
},
  "geometry": {"coordinates":[126.36667,-8.86667],"type":"Point"}
}