{
  "type": "Feature",
  "properties": {
    "gn:admin1_code":"ER",
    "gn:admin2_code":"704.0",
    "gn:admin3_code":"70410.0",
    "gn:asciiname":"Olekata",
    "gn:country_code":"TL",
    "gn:dem":1310,
    "gn:feature_class":"P",
    "gn:feature_code":"PPL",
    "gn:name":"Olekata",
    "gn:population":0,
    "gn:timezone":"Asia/Dili",
    "iso:country":"TL",
    "wof:name":"Olekata",
    "wof:placetype":"locality"
},
  "geometry": {"coordinates":[125.40167,-8.89139],"type":"Point"}
}