{
  "type": "Feature",
  "properties": {
    "gn:admin1_code":"AN",
    "gn:admin2_code":"103.0",
    "gn:admin3_code":"10305.0",
    "gn:asciiname":"Dimtete",
    "gn:country_code":"TL",
    "gn:dem":1434,
    "gn:feature_class":"P",
    "gn:feature_code":"PPL",
    "gn:name":"Dimtete",
    "gn:population":0,
    "gn:timezone":"Asia/Dili",
    "iso:country":"TL",
    "wof:name":"Dimtete",
    "wof:placetype":"locality"
},
  "geometry": {"coordinates":[125.64888999999999,-8.85944],"type":"Point"}
}