{
  "type": "Feature",
  "properties": {
    "gn:admin1_code":"BA",
    "gn:admin2_code":"302.0",
    "gn:admin3_code":"30208.0",
    "gn:asciiname":"Riadac",
    "gn:country_code":"TL",
    "gn:dem":543,
    "gn:feature_class":"P",
    "gn:feature_code":"PPL",
    "gn:name":"Riadac",
    "gn:population":0,
    "gn:timezone":"Asia/Dili",
    "iso:country":"TL",
    "name:und_x_variant":[
        "Riadae"
    ],
    "wof:name":"Riadac",
    "wof:placetype":"locality"
},
  "geometry": {"coordinates":[126.68902,-8.48702],"type":"Point"}
}