{
  "type": "Feature",
  "properties": {
    "gn:admin1_code":"OE",
    "gn:admin2_code":"1202.0",
    "gn:admin3_code":"120201.0",
    "gn:asciiname":"Nitibe",
    "gn:country_code":"TL",
    "gn:dem":696,
    "gn:feature_class":"P",
    "gn:feature_code":"PPL",
    "gn:name":"Nitibe",
    "gn:population":0,
    "gn:timezone":"Asia/Dili",
    "iso:country":"TL",
    "name:und_x_variant":[
        "N\u00edtibe",
        "Nitibe"
    ],
    "wof:name":"Nitibe",
    "wof:placetype":"locality"
},
  "geometry": {"coordinates":[124.23063,-9.34535],"type":"Point"}
}