{
  "type": "Feature",
  "properties": {
    "gn:admin1_code":"MT",
    "gn:admin2_code":"1103.0",
    "gn:admin3_code":"110301.0",
    "gn:asciiname":"Umanaruk",
    "gn:country_code":"TL",
    "gn:dem":86,
    "gn:feature_class":"P",
    "gn:feature_code":"PPL",
    "gn:name":"Umanaruk",
    "gn:population":0,
    "gn:timezone":"Asia/Dili",
    "iso:country":"TL",
    "wof:name":"Umanaruk",
    "wof:placetype":"locality"
},
  "geometry": {"coordinates":[125.91583,-8.55611],"type":"Point"}
}