{
  "type": "Feature",
  "properties": {
    "gn:admin1_code":"BA",
    "gn:admin2_code":"302.0",
    "gn:admin3_code":"30202.0",
    "gn:asciiname":"Telibudae",
    "gn:country_code":"TL",
    "gn:dem":21,
    "gn:feature_class":"P",
    "gn:feature_code":"PPL",
    "gn:name":"Telibudae",
    "gn:population":0,
    "gn:timezone":"Asia/Dili",
    "iso:country":"TL",
    "wof:name":"Telibudae",
    "wof:placetype":"locality"
},
  "geometry": {"coordinates":[126.5938,-8.47743],"type":"Point"}
}