{
  "type": "Feature",
  "properties": {
    "gn:admin1_code":"CO",
    "gn:admin2_code":"507.0",
    "gn:admin3_code":"50701.0",
    "gn:asciiname":"Beilako A",
    "gn:country_code":"TL",
    "gn:dem":18,
    "gn:feature_class":"P",
    "gn:feature_code":"PPL",
    "gn:name":"Beilako A",
    "gn:population":0,
    "gn:timezone":"Asia/Dili",
    "iso:country":"TL",
    "wof:name":"Beilako A",
    "wof:placetype":"locality"
},
  "geometry": {"coordinates":[125.47808000000001,-9.19223],"type":"Point"}
}