{
  "type": "Feature",
  "properties": {
    "gn:admin1_code":"BA",
    "gn:admin2_code":"301.0",
    "gn:admin3_code":"30111.0",
    "gn:asciiname":"Anauaru",
    "gn:country_code":"TL",
    "gn:dem":281,
    "gn:feature_class":"P",
    "gn:feature_code":"PPL",
    "gn:name":"Anauaru",
    "gn:population":0,
    "gn:timezone":"Asia/Dili",
    "iso:country":"TL",
    "wof:name":"Anauaru",
    "wof:placetype":"locality"
},
  "geometry": {"coordinates":[126.44458,-8.45371],"type":"Point"}
}