{
  "type": "Feature",
  "properties": {
    "gn:admin1_code":"ER",
    "gn:admin2_code":"705.0",
    "gn:admin3_code":"70506.0",
    "gn:asciiname":"Samara",
    "gn:country_code":"TL",
    "gn:dem":185,
    "gn:feature_class":"P",
    "gn:feature_code":"PPL",
    "gn:name":"Samara",
    "gn:population":0,
    "gn:timezone":"Asia/Dili",
    "iso:country":"TL",
    "wof:name":"Samara",
    "wof:placetype":"locality"
},
  "geometry": {"coordinates":[125.29694000000001,-8.84056],"type":"Point"}
}