{
  "type": "Feature",
  "properties": {
    "gn:admin1_code":"ER",
    "gn:admin2_code":"705.0",
    "gn:admin3_code":"70508.0",
    "gn:asciiname":"Talo",
    "gn:country_code":"TL",
    "gn:dem":1199,
    "gn:feature_class":"P",
    "gn:feature_code":"PPL",
    "gn:name":"Talo",
    "gn:population":0,
    "gn:timezone":"Asia/Dili",
    "iso:country":"TL",
    "wof:name":"Talo",
    "wof:placetype":"locality"
},
  "geometry": {"coordinates":[125.35222,-8.80806],"type":"Point"}
}