{
  "type": "Feature",
  "properties": {
    "gn:admin1_code":"LA",
    "gn:admin2_code":"901.0",
    "gn:admin3_code":"90102.0",
    "gn:asciiname":"Trisula",
    "gn:country_code":"TL",
    "gn:dem":405,
    "gn:feature_class":"P",
    "gn:feature_code":"PPL",
    "gn:name":"Trisula",
    "gn:population":0,
    "gn:timezone":"Asia/Dili",
    "iso:country":"TL",
    "wof:name":"Trisula",
    "wof:placetype":"locality"
},
  "geometry": {"coordinates":[127.00139,-8.44083],"type":"Point"}
}