{
  "type": "Feature",
  "properties": {
    "gn:admin1_code":"OE",
    "gn:admin2_code":"1202.0",
    "gn:admin3_code":"120204.0",
    "gn:asciiname":"Kuanisi",
    "gn:country_code":"TL",
    "gn:dem":605,
    "gn:feature_class":"P",
    "gn:feature_code":"PPL",
    "gn:name":"Kuanisi",
    "gn:population":0,
    "gn:timezone":"Asia/Dili",
    "iso:country":"TL",
    "wof:name":"Kuanisi",
    "wof:placetype":"locality"
},
  "geometry": {"coordinates":[124.2775,-9.34472],"type":"Point"}
}