{
  "type": "Feature",
  "properties": {
    "gn:admin1_code":"DI",
    "gn:asciiname":"Maker",
    "gn:country_code":"TL",
    "gn:dem":239,
    "gn:feature_class":"P",
    "gn:feature_code":"PPL",
    "gn:name":"Maker",
    "gn:population":0,
    "gn:timezone":"Asia/Dili",
    "iso:country":"TL",
    "name:deu_x_preferred":[
        "Maker"
    ],
    "name:kor_x_preferred":[
        "\uba54\uc774\ucee4"
    ],
    "name:por_x_preferred":[
        "Maker"
    ],
    "wof:name":"Maker",
    "wof:placetype":"locality"
},
  "geometry": {"coordinates":[125.51333,-8.25028],"type":"Point"}
}