{
  "type": "Feature",
  "properties": {
    "gn:admin1_code":"BO",
    "gn:admin2_code":"403.0",
    "gn:admin3_code":"40306.0",
    "gn:asciiname":"Motamorak",
    "gn:country_code":"TL",
    "gn:dem":47,
    "gn:feature_class":"P",
    "gn:feature_code":"PPL",
    "gn:name":"Motamorak",
    "gn:population":0,
    "gn:timezone":"Asia/Dili",
    "iso:country":"TL",
    "wof:name":"Motamorak",
    "wof:placetype":"locality"
},
  "geometry": {"coordinates":[124.99333,-8.96306],"type":"Point"}
}