{
  "type": "Feature",
  "properties": {
    "gn:admin1_code":"ER",
    "gn:admin2_code":"703.0",
    "gn:admin3_code":"70304.0",
    "gn:asciiname":"Hatulete",
    "gn:country_code":"TL",
    "gn:dem":1767,
    "gn:feature_class":"P",
    "gn:feature_code":"PPL",
    "gn:name":"Hatulete",
    "gn:population":0,
    "gn:timezone":"Asia/Dili",
    "iso:country":"TL",
    "wof:name":"Hatulete",
    "wof:placetype":"locality"
},
  "geometry": {"coordinates":[125.43528000000001,-8.89028],"type":"Point"}
}