{
  "type": "Feature",
  "properties": {
    "gn:admin1_code":"VI",
    "gn:admin2_code":"1303.0",
    "gn:admin3_code":"130302.0",
    "gn:asciiname":"Uaitame",
    "gn:country_code":"TL",
    "gn:dem":21,
    "gn:feature_class":"P",
    "gn:feature_code":"PPL",
    "gn:name":"Uaitame",
    "gn:population":0,
    "gn:timezone":"Asia/Dili",
    "iso:country":"TL",
    "wof:name":"Uaitame",
    "wof:placetype":"locality"
},
  "geometry": {"coordinates":[126.55083,-8.80139],"type":"Point"}
}