{
  "type": "Feature",
  "properties": {
    "gn:admin1_code":"BO",
    "gn:admin2_code":"405.0",
    "gn:admin3_code":"40501.0",
    "gn:asciiname":"Opa",
    "gn:country_code":"TL",
    "gn:dem":530,
    "gn:feature_class":"P",
    "gn:feature_code":"PPL",
    "gn:name":"Opa",
    "gn:population":0,
    "gn:timezone":"Asia/Dili",
    "iso:country":"TL",
    "wof:name":"Opa",
    "wof:placetype":"locality"
},
  "geometry": {"coordinates":[125.27435,-9.19294],"type":"Point"}
}