{
  "type": "Feature",
  "properties": {
    "gn:admin1_code":"ER",
    "gn:admin2_code":"702.0",
    "gn:admin3_code":"70208.0",
    "gn:asciiname":"Mokorema",
    "gn:country_code":"TL",
    "gn:dem":1103,
    "gn:feature_class":"P",
    "gn:feature_code":"PPL",
    "gn:name":"Mokorema",
    "gn:population":0,
    "gn:timezone":"Asia/Dili",
    "iso:country":"TL",
    "wof:name":"Mokorema",
    "wof:placetype":"locality"
},
  "geometry": {"coordinates":[125.46361,-8.74722],"type":"Point"}
}