{
  "type": "Feature",
  "properties": {
    "gn:admin1_code":"BA",
    "gn:admin2_code":"302.0",
    "gn:admin3_code":"30201.0",
    "gn:asciiname":"Samagata",
    "gn:country_code":"TL",
    "gn:dem":385,
    "gn:feature_class":"P",
    "gn:feature_code":"PPL",
    "gn:name":"Samagata",
    "gn:population":0,
    "gn:timezone":"Asia/Dili",
    "iso:country":"TL",
    "wof:name":"Samagata",
    "wof:placetype":"locality"
},
  "geometry": {"coordinates":[126.69777999999999,-8.55861],"type":"Point"}
}