{
  "type": "Feature",
  "properties": {
    "gn:admin1_code":"LA",
    "gn:admin2_code":"901.0",
    "gn:admin3_code":"90101.0",
    "gn:asciiname":"Assalaino",
    "gn:country_code":"TL",
    "gn:dem":407,
    "gn:feature_class":"P",
    "gn:feature_code":"PPL",
    "gn:name":"Assalaino",
    "gn:population":0,
    "gn:timezone":"Asia/Dili",
    "iso:country":"TL",
    "wof:name":"Assalaino",
    "wof:placetype":"locality"
},
  "geometry": {"coordinates":[127.005,-8.43333],"type":"Point"}
}