{
  "type": "Feature",
  "properties": {
    "gn:admin1_code":"OE",
    "gn:admin2_code":"1201.0",
    "gn:admin3_code":"120104.0",
    "gn:asciiname":"Oetulu",
    "gn:country_code":"TL",
    "gn:dem":33,
    "gn:feature_class":"P",
    "gn:feature_code":"PPL",
    "gn:name":"Oetulu",
    "gn:population":0,
    "gn:timezone":"Asia/Dili",
    "iso:country":"TL",
    "wof:name":"Oetulu",
    "wof:placetype":"locality"
},
  "geometry": {"coordinates":[124.36671,-9.21507],"type":"Point"}
}