{
  "type": "Feature",
  "properties": {
    "gn:admin1_code":"BA",
    "gn:admin2_code":"301.0",
    "gn:admin3_code":"30111.0",
    "gn:asciiname":"Suliwa",
    "gn:country_code":"TL",
    "gn:dem":101,
    "gn:feature_class":"P",
    "gn:feature_code":"PPL",
    "gn:name":"Suliwa",
    "gn:population":0,
    "gn:timezone":"Asia/Dili",
    "iso:country":"TL",
    "wof:name":"Suliwa",
    "wof:placetype":"locality"
},
  "geometry": {"coordinates":[126.48793000000001,-8.47017],"type":"Point"}
}