{
  "type": "Feature",
  "properties": {
    "gn:admin1_code":"AN",
    "gn:admin2_code":"101.0",
    "gn:admin3_code":"10105.0",
    "gn:asciiname":"Pebago",
    "gn:country_code":"TL",
    "gn:dem":134,
    "gn:feature_class":"P",
    "gn:feature_code":"PPL",
    "gn:name":"Pebago",
    "gn:population":0,
    "gn:timezone":"Asia/Dili",
    "iso:country":"TL",
    "wof:name":"Pebago",
    "wof:placetype":"locality"
},
  "geometry": {"coordinates":[125.54306,-9.13444],"type":"Point"}
}