{
  "type": "Feature",
  "properties": {
    "gn:admin1_code":"VI",
    "gn:admin2_code":"1303.0",
    "gn:admin3_code":"130304.0",
    "gn:asciiname":"Docoate",
    "gn:country_code":"TL",
    "gn:dem":1032,
    "gn:feature_class":"P",
    "gn:feature_code":"PPL",
    "gn:name":"Docoate",
    "gn:population":0,
    "gn:timezone":"Asia/Dili",
    "iso:country":"TL",
    "wof:name":"Docoate",
    "wof:placetype":"locality"
},
  "geometry": {"coordinates":[126.63443999999998,-8.70417],"type":"Point"}
}