{
  "type": "Feature",
  "properties": {
    "gn:admin1_code":"OE",
    "gn:admin2_code":"1203.0",
    "gn:admin3_code":"120301.0",
    "gn:asciiname":"Biele",
    "gn:country_code":"TL",
    "gn:dem":370,
    "gn:feature_class":"P",
    "gn:feature_code":"PPL",
    "gn:name":"Biele",
    "gn:population":0,
    "gn:timezone":"Asia/Dili",
    "iso:country":"TL",
    "name:deu_x_preferred":[
        "Biele"
    ],
    "name:fra_x_preferred":[
        "Biele"
    ],
    "name:pol_x_preferred":[
        "Biele"
    ],
    "name:ukr_x_preferred":[
        "\u0411\u0435\u043b\u0435"
    ],
    "wof:name":"Biele",
    "wof:placetype":"locality"
},
  "geometry": {"coordinates":[124.38111000000001,-9.3375],"type":"Point"}
}