{
  "type": "Feature",
  "properties": {
    "gn:admin1_code":"ER",
    "gn:admin2_code":"704.0",
    "gn:admin3_code":"70401.0",
    "gn:asciiname":"Aliatu",
    "gn:country_code":"TL",
    "gn:dem":1411,
    "gn:feature_class":"P",
    "gn:feature_code":"PPL",
    "gn:name":"Aliatu",
    "gn:population":0,
    "gn:timezone":"Asia/Dili",
    "iso:country":"TL",
    "wof:name":"Aliatu",
    "wof:placetype":"locality"
},
  "geometry": {"coordinates":[125.40667000000001,-8.92667],"type":"Point"}
}