{
  "type": "Feature",
  "properties": {
    "gn:admin1_code":"BO",
    "gn:admin2_code":"404.0",
    "gn:admin3_code":"40401.0",
    "gn:asciiname":"Nunagbae",
    "gn:country_code":"TL",
    "gn:dem":30,
    "gn:feature_class":"P",
    "gn:feature_code":"PPL",
    "gn:name":"Nunagbae",
    "gn:population":0,
    "gn:timezone":"Asia/Dili",
    "iso:country":"TL",
    "wof:name":"Nunagbae",
    "wof:placetype":"locality"
},
  "geometry": {"coordinates":[125.11306,-8.74472],"type":"Point"}
}