{
  "type": "Feature",
  "properties": {
    "gn:admin1_code":"OE",
    "gn:admin2_code":"1202.0",
    "gn:admin3_code":"120205.0",
    "gn:asciiname":"Noetoko",
    "gn:country_code":"TL",
    "gn:dem":207,
    "gn:feature_class":"P",
    "gn:feature_code":"PPL",
    "gn:name":"Noetoko",
    "gn:population":0,
    "gn:timezone":"Asia/Dili",
    "iso:country":"TL",
    "wof:name":"Noetoko",
    "wof:placetype":"locality"
},
  "geometry": {"coordinates":[124.30556,-9.37167],"type":"Point"}
}