{
  "type": "Feature",
  "properties": {
    "gn:admin1_code":"ER",
    "gn:admin2_code":"703.0",
    "gn:admin3_code":"70302.0",
    "gn:asciiname":"Riatoni",
    "gn:country_code":"TL",
    "gn:dem":1182,
    "gn:feature_class":"P",
    "gn:feature_code":"PPL",
    "gn:name":"Riatoni",
    "gn:population":0,
    "gn:timezone":"Asia/Dili",
    "iso:country":"TL",
    "wof:name":"Riatoni",
    "wof:placetype":"locality"
},
  "geometry": {"coordinates":[125.43889,-8.85167],"type":"Point"}
}