{
  "type": "Feature",
  "properties": {
    "gn:admin1_code":"CO",
    "gn:admin2_code":"501.0",
    "gn:admin3_code":"50102.0",
    "gn:asciiname":"Fatuloro",
    "gn:country_code":"TL",
    "gn:dem":600,
    "gn:feature_class":"P",
    "gn:feature_code":"PPL",
    "gn:name":"Fatuloro",
    "gn:population":0,
    "gn:timezone":"Asia/Dili",
    "iso:country":"TL",
    "wof:name":"Fatuloro",
    "wof:placetype":"locality"
},
  "geometry": {"coordinates":[125.17887,-9.22748],"type":"Point"}
}