{
  "type": "Feature",
  "properties": {
    "gn:admin1_code":"AN",
    "gn:admin2_code":"103.0",
    "gn:admin3_code":"10309.0",
    "gn:asciiname":"Tutufili",
    "gn:country_code":"TL",
    "gn:dem":1462,
    "gn:feature_class":"P",
    "gn:feature_code":"PPL",
    "gn:name":"Tutufili",
    "gn:population":0,
    "gn:timezone":"Asia/Dili",
    "iso:country":"TL",
    "wof:name":"Tutufili",
    "wof:placetype":"locality"
},
  "geometry": {"coordinates":[125.61499999999999,-8.8125],"type":"Point"}
}