{
  "type": "Feature",
  "properties": {
    "gn:admin1_code":"AN",
    "gn:admin2_code":"102.0",
    "gn:admin3_code":"10201.0",
    "gn:asciiname":"Qeorema",
    "gn:country_code":"TL",
    "gn:dem":2125,
    "gn:feature_class":"P",
    "gn:feature_code":"PPL",
    "gn:name":"Qeorema",
    "gn:population":0,
    "gn:timezone":"Asia/Dili",
    "iso:country":"TL",
    "wof:name":"Qeorema",
    "wof:placetype":"locality"
},
  "geometry": {"coordinates":[125.53610999999999,-8.88278],"type":"Point"}
}