{
  "type": "Feature",
  "properties": {
    "gn:admin1_code":"AL",
    "gn:admin2_code":"201.0",
    "gn:admin3_code":"20106.0",
    "gn:asciiname":"Likitura",
    "gn:country_code":"TL",
    "gn:dem":1492,
    "gn:feature_class":"P",
    "gn:feature_code":"PPL",
    "gn:name":"Likitura",
    "gn:population":0,
    "gn:timezone":"Asia/Dili",
    "iso:country":"TL",
    "wof:name":"Likitura",
    "wof:placetype":"locality"
},
  "geometry": {"coordinates":[125.59972,-8.81611],"type":"Point"}
}