{
  "type": "Feature",
  "properties": {
    "gn:admin1_code":"BA",
    "gn:admin2_code":"304.0",
    "gn:admin3_code":"30409.0",
    "gn:asciiname":"Onortibalari",
    "gn:country_code":"TL",
    "gn:dem":442,
    "gn:feature_class":"P",
    "gn:feature_code":"PPL",
    "gn:name":"Onortibalari",
    "gn:population":0,
    "gn:timezone":"Asia/Dili",
    "iso:country":"TL",
    "name:und_x_variant":[
        "Onor Tiba Lari",
        "Onortibalari"
    ],
    "wof:name":"Onortibalari",
    "wof:placetype":"locality"
},
  "geometry": {"coordinates":[126.68416999999999,-8.56778],"type":"Point"}
}