{
  "type": "Feature",
  "properties": {
    "gn:admin1_code":"LA",
    "gn:admin2_code":"901.0",
    "gn:admin3_code":"90109.0",
    "gn:asciiname":"Raca",
    "gn:country_code":"TL",
    "gn:dem":441,
    "gn:feature_class":"P",
    "gn:feature_code":"PPL",
    "gn:name":"Raca",
    "gn:population":0,
    "gn:timezone":"Asia/Dili",
    "iso:country":"TL",
    "name:ceb_x_preferred":[
        "Raca"
    ],
    "name:deu_x_preferred":[
        "Raca"
    ],
    "name:hsb_x_preferred":[
        "Raca"
    ],
    "name:ita_x_preferred":[
        "Raca"
    ],
    "name:nld_x_preferred":[
        "Raca"
    ],
    "name:spa_x_preferred":[
        "Raca"
    ],
    "name:sqi_x_preferred":[
        "Ra\u00e7a"
    ],
    "name:swe_x_preferred":[
        "Raca"
    ],
    "wof:name":"Raca",
    "wof:placetype":"locality"
},
  "geometry": {"coordinates":[126.97861,-8.43667],"type":"Point"}
}