{
  "type": "Feature",
  "properties": {
    "gn:admin1_code":"VI",
    "gn:admin2_code":"1303.0",
    "gn:admin3_code":"130305.0",
    "gn:asciiname":"Daralari",
    "gn:country_code":"TL",
    "gn:dem":7,
    "gn:feature_class":"P",
    "gn:feature_code":"PPL",
    "gn:name":"Daralari",
    "gn:population":0,
    "gn:timezone":"Asia/Dili",
    "iso:country":"TL",
    "wof:name":"Daralari",
    "wof:placetype":"locality"
},
  "geometry": {"coordinates":[126.5775,-8.80478],"type":"Point"}
}