{
  "type": "Feature",
  "properties": {
    "gn:admin1_code":"BA",
    "gn:admin2_code":"303.0",
    "gn:admin3_code":"30305.0",
    "gn:asciiname":"Luborice",
    "gn:country_code":"TL",
    "gn:dem":425,
    "gn:feature_class":"P",
    "gn:feature_code":"PPL",
    "gn:name":"Luborice",
    "gn:population":0,
    "gn:timezone":"Asia/Dili",
    "iso:country":"TL",
    "wof:name":"Luborice",
    "wof:placetype":"locality"
},
  "geometry": {"coordinates":[126.52028,-8.58472],"type":"Point"}
}