{
  "type": "Feature",
  "properties": {
    "gn:admin1_code":"BO",
    "gn:admin2_code":"404.0",
    "gn:admin3_code":"40404.0",
    "gn:asciiname":"Arlaeben",
    "gn:country_code":"TL",
    "gn:dem":98,
    "gn:feature_class":"P",
    "gn:feature_code":"PPL",
    "gn:name":"Arlaeben",
    "gn:population":0,
    "gn:timezone":"Asia/Dili",
    "iso:country":"TL",
    "wof:name":"Arlaeben",
    "wof:placetype":"locality"
},
  "geometry": {"coordinates":[125.16249999999999,-8.89111],"type":"Point"}
}