{
  "type": "Feature",
  "properties": {
    "gn:admin1_code":"CO",
    "gn:admin2_code":"503.0",
    "gn:admin3_code":"50301.0",
    "gn:asciiname":"Fatuklaran",
    "gn:country_code":"TL",
    "gn:dem":531,
    "gn:feature_class":"P",
    "gn:feature_code":"PPL",
    "gn:name":"Fatuklaran",
    "gn:population":0,
    "gn:timezone":"Asia/Dili",
    "iso:country":"TL",
    "wof:name":"Fatuklaran",
    "wof:placetype":"locality"
},
  "geometry": {"coordinates":[125.09305999999999,-9.29417],"type":"Point"}
}