{
  "type": "Feature",
  "properties": {
    "gn:admin1_code":"BA",
    "gn:admin2_code":"302.0",
    "gn:admin3_code":"30204.0",
    "gn:asciiname":"Bubodefo",
    "gn:country_code":"TL",
    "gn:dem":499,
    "gn:feature_class":"P",
    "gn:feature_code":"PPL",
    "gn:name":"Bubodefo",
    "gn:population":0,
    "gn:timezone":"Asia/Dili",
    "iso:country":"TL",
    "wof:name":"Bubodefo",
    "wof:placetype":"locality"
},
  "geometry": {"coordinates":[126.65971999999999,-8.48472],"type":"Point"}
}