{
  "type": "Feature",
  "properties": {
    "gn:admin1_code":"LI",
    "gn:admin2_code":"803.0",
    "gn:admin3_code":"80303.0",
    "gn:asciiname":"Raeme",
    "gn:country_code":"TL",
    "gn:dem":642,
    "gn:feature_class":"P",
    "gn:feature_code":"PPL",
    "gn:name":"Raeme",
    "gn:population":0,
    "gn:timezone":"Asia/Dili",
    "iso:country":"TL",
    "wof:name":"Raeme",
    "wof:placetype":"locality"
},
  "geometry": {"coordinates":[125.26582999999999,-8.63944],"type":"Point"}
}