{
  "type": "Feature",
  "properties": {
    "gn:admin1_code":"OE",
    "gn:admin2_code":"1202.0",
    "gn:admin3_code":"120204.0",
    "gn:asciiname":"Bebo",
    "gn:country_code":"TL",
    "gn:dem":641,
    "gn:feature_class":"P",
    "gn:feature_code":"PPL",
    "gn:name":"Bebo",
    "gn:population":0,
    "gn:timezone":"Asia/Dili",
    "iso:country":"TL",
    "name:ara_x_preferred":[
        "\u0628\u064a\u0628\u0648"
    ],
    "name:ben_x_preferred":[
        "\u09ac\u09c7\u09ac\u09cb"
    ],
    "name:cym_x_preferred":[
        "Bebo"
    ],
    "name:deu_x_preferred":[
        "Bebo"
    ],
    "name:fra_x_preferred":[
        "Bebo"
    ],
    "name:gle_x_preferred":[
        "Bebo"
    ],
    "name:ind_x_preferred":[
        "Bebo"
    ],
    "name:ita_x_preferred":[
        "Bebo"
    ],
    "name:jpn_x_preferred":[
        "Bebo"
    ],
    "name:kor_x_preferred":[
        "Bebo"
    ],
    "name:msa_x_preferred":[
        "Bebo"
    ],
    "name:pol_x_preferred":[
        "Bebo"
    ],
    "name:por_x_preferred":[
        "Bebo"
    ],
    "name:spa_x_preferred":[
        "Bebo"
    ],
    "name:swe_x_preferred":[
        "Bebo"
    ],
    "name:tha_x_preferred":[
        "Bebo"
    ],
    "name:zho_x_preferred":[
        "Bebo"
    ],
    "wof:name":"Bebo",
    "wof:placetype":"locality"
},
  "geometry": {"coordinates":[124.28167000000001,-9.35222],"type":"Point"}
}