{
  "type": "Feature",
  "properties": {
    "gn:admin1_code":"OE",
    "gn:admin2_code":"1202.0",
    "gn:admin3_code":"120204.0",
    "gn:asciiname":"Bebo",
    "gn:country_code":"TL",
    "gn:dem":641,
    "gn:feature_class":"P",
    "gn:feature_code":"PPL",
    "gn:name":"Bebo",
    "gn:population":0,
    "gn:timezone":"Asia/Dili",
    "iso:country":"TL",
    "wof:name":"Bebo",
    "wof:placetype":"locality"
},
  "geometry": {"coordinates":[124.28167000000001,-9.35222],"type":"Point"}
}