{
  "type": "Feature",
  "properties": {
    "gn:admin1_code":"DI",
    "gn:admin2_code":"603.0",
    "gn:admin3_code":"60301.0",
    "gn:asciiname":"Manuleu",
    "gn:country_code":"TL",
    "gn:dem":13,
    "gn:feature_class":"P",
    "gn:feature_code":"PPL",
    "gn:name":"Manuleu",
    "gn:population":0,
    "gn:timezone":"Asia/Dili",
    "iso:country":"TL",
    "wof:name":"Manuleu",
    "wof:placetype":"locality"
},
  "geometry": {"coordinates":[125.74417,-8.53111],"type":"Point"}
}