{
  "type": "Feature",
  "properties": {
    "gn:admin1_code":"VI",
    "gn:admin2_code":"1304.0",
    "gn:admin3_code":"130404.0",
    "gn:asciiname":"Maneklaran",
    "gn:country_code":"TL",
    "gn:dem":11,
    "gn:feature_class":"P",
    "gn:feature_code":"PPL",
    "gn:name":"Maneklaran",
    "gn:population":0,
    "gn:timezone":"Asia/Dili",
    "iso:country":"TL",
    "wof:name":"Maneklaran",
    "wof:placetype":"locality"
},
  "geometry": {"coordinates":[126.26917,-8.96333],"type":"Point"}
}