{
  "type": "Feature",
  "properties": {
    "gn:admin1_code":"CO",
    "gn:admin2_code":"506.0",
    "gn:admin3_code":"50601.0",
    "gn:asciiname":"Nikir",
    "gn:country_code":"TL",
    "gn:dem":522,
    "gn:feature_class":"P",
    "gn:feature_code":"PPL",
    "gn:name":"Nikir",
    "gn:population":0,
    "gn:timezone":"Asia/Dili",
    "iso:country":"TL",
    "wof:name":"Nikir",
    "wof:placetype":"locality"
},
  "geometry": {"coordinates":[125.07404,-9.34483],"type":"Point"}
}