{
  "type": "Feature",
  "properties": {
    "gn:admin1_code":"MF",
    "gn:admin2_code":"1002.0",
    "gn:admin3_code":"100204.0",
    "gn:asciiname":"Kelapa",
    "gn:country_code":"TL",
    "gn:dem":215,
    "gn:feature_class":"P",
    "gn:feature_code":"PPL",
    "gn:name":"Kelapa",
    "gn:population":0,
    "gn:timezone":"Asia/Dili",
    "iso:country":"TL",
    "name:ceb_x_preferred":[
        "Kelapa"
    ],
    "name:nld_x_preferred":[
        "Kelapa"
    ],
    "name:swe_x_preferred":[
        "Kelapa"
    ],
    "wof:name":"Kelapa",
    "wof:placetype":"locality"
},
  "geometry": {"coordinates":[125.78778,-9.01806],"type":"Point"}
}