{
  "type": "Feature",
  "properties": {
    "gn:admin1_code":"OE",
    "gn:admin2_code":"1201.0",
    "gn:admin3_code":"120108.0",
    "gn:asciiname":"Kafun",
    "gn:country_code":"TL",
    "gn:dem":96,
    "gn:feature_class":"P",
    "gn:feature_code":"PPL",
    "gn:name":"Kafun",
    "gn:population":0,
    "gn:timezone":"Asia/Dili",
    "iso:country":"TL",
    "wof:name":"Kafun",
    "wof:placetype":"locality"
},
  "geometry": {"coordinates":[124.38861,-9.28694],"type":"Point"}
}