{
  "type": "Feature",
  "properties": {
    "gn:admin1_code":"VI",
    "gn:admin2_code":"1302.0",
    "gn:admin3_code":"130203.0",
    "gn:asciiname":"Samalari",
    "gn:country_code":"TL",
    "gn:dem":449,
    "gn:feature_class":"P",
    "gn:feature_code":"PPL",
    "gn:name":"Samalari",
    "gn:population":0,
    "gn:timezone":"Asia/Dili",
    "iso:country":"TL",
    "wof:name":"Samalari",
    "wof:placetype":"locality"
},
  "geometry": {"coordinates":[126.48083,-8.69722],"type":"Point"}
}