{
  "type": "Feature",
  "properties": {
    "gn:admin1_code":"OE",
    "gn:admin2_code":"1201.0",
    "gn:admin3_code":"120106.0",
    "gn:asciiname":"Lalisuc",
    "gn:country_code":"TL",
    "gn:dem":41,
    "gn:feature_class":"P",
    "gn:feature_code":"PPL",
    "gn:name":"Lalisuc",
    "gn:population":0,
    "gn:timezone":"Asia/Dili",
    "iso:country":"TL",
    "wof:name":"Lalisuc",
    "wof:placetype":"locality"
},
  "geometry": {"coordinates":[124.34275,-9.25038],"type":"Point"}
}