{
  "type": "Feature",
  "properties": {
    "gn:admin1_code":"BA",
    "gn:admin2_code":"306.0",
    "gn:admin3_code":"30601.0",
    "gn:asciiname":"Uatubelaoli",
    "gn:country_code":"TL",
    "gn:dem":527,
    "gn:feature_class":"P",
    "gn:feature_code":"PPL",
    "gn:name":"Uatubelaoli",
    "gn:population":0,
    "gn:timezone":"Asia/Dili",
    "iso:country":"TL",
    "wof:name":"Uatubelaoli",
    "wof:placetype":"locality"
},
  "geometry": {"coordinates":[126.39667,-8.60389],"type":"Point"}
}