{
  "type": "Feature",
  "properties": {
    "gn:admin1_code":"BO",
    "gn:admin2_code":"402.0",
    "gn:admin3_code":"40205.0",
    "gn:asciiname":"Ritiogoro",
    "gn:country_code":"TL",
    "gn:dem":52,
    "gn:feature_class":"P",
    "gn:feature_code":"PPL",
    "gn:name":"Ritiogoro",
    "gn:population":0,
    "gn:timezone":"Asia/Dili",
    "iso:country":"TL",
    "wof:name":"Ritiogoro",
    "wof:placetype":"locality"
},
  "geometry": {"coordinates":[125.22278,-8.79472],"type":"Point"}
}