{
  "type": "Feature",
  "properties": {
    "gn:admin1_code":"VI",
    "gn:admin2_code":"1304.0",
    "gn:admin3_code":"130405.0",
    "gn:asciiname":"Beaco",
    "gn:country_code":"TL",
    "gn:dem":8,
    "gn:feature_class":"P",
    "gn:feature_code":"PPL",
    "gn:name":"Beaco",
    "gn:population":0,
    "gn:timezone":"Asia/Dili",
    "iso:country":"TL",
    "name:und_x_variant":[
        "Beasso",
        "Beago",
        "Beaco"
    ],
    "wof:name":"Beaco",
    "wof:placetype":"locality"
},
  "geometry": {"coordinates":[126.44944,-8.94417],"type":"Point"}
}