{
  "type": "Feature",
  "properties": {
    "gn:admin1_code":"BO",
    "gn:admin2_code":"404.0",
    "gn:admin3_code":"40404.0",
    "gn:asciiname":"Lahululi",
    "gn:country_code":"TL",
    "gn:dem":77,
    "gn:feature_class":"P",
    "gn:feature_code":"PPL",
    "gn:name":"Lahululi",
    "gn:population":0,
    "gn:timezone":"Asia/Dili",
    "iso:country":"TL",
    "wof:name":"Lahululi",
    "wof:placetype":"locality"
},
  "geometry": {"coordinates":[125.18056,-8.85889],"type":"Point"}
}