{
  "type": "Feature",
  "properties": {
    "gn:admin1_code":"CO",
    "gn:admin2_code":"505.0",
    "gn:admin3_code":"50504.0",
    "gn:asciiname":"Sanfuk",
    "gn:cc2":"TL",
    "gn:country_code":"TL",
    "gn:dem":21,
    "gn:feature_class":"P",
    "gn:feature_code":"PPL",
    "gn:name":"Sanfuk",
    "gn:population":0,
    "gn:timezone":"Asia/Dili",
    "iso:country":"TL",
    "name:und_x_variant":[
        "Sanfuc",
        "Sanfuk"
    ],
    "wof:name":"Sanfuk",
    "wof:placetype":"locality"
},
  "geometry": {"coordinates":[125.29639,-9.305],"type":"Point"}
}