{
  "type": "Feature",
  "properties": {
    "gn:admin1_code":"MF",
    "gn:admin2_code":"1001.0",
    "gn:admin3_code":"100101.0",
    "gn:asciiname":"Catolada",
    "gn:country_code":"TL",
    "gn:dem":697,
    "gn:feature_class":"P",
    "gn:feature_code":"PPL",
    "gn:name":"Catolada",
    "gn:population":0,
    "gn:timezone":"Asia/Dili",
    "iso:country":"TL",
    "wof:name":"Catolada",
    "wof:placetype":"locality"
},
  "geometry": {"coordinates":[125.6266,-8.9831],"type":"Point"}
}