{
  "type": "Feature",
  "properties": {
    "gn:admin1_code":"MF",
    "gn:admin2_code":"1001.0",
    "gn:admin3_code":"100103.0",
    "gn:asciiname":"Bahulu",
    "gn:country_code":"TL",
    "gn:dem":379,
    "gn:feature_class":"P",
    "gn:feature_code":"PPL",
    "gn:name":"Bahulu",
    "gn:population":0,
    "gn:timezone":"Asia/Dili",
    "iso:country":"TL",
    "name:ind_x_preferred":[
        "Bahulu"
    ],
    "name:msa_x_preferred":[
        "Bahulu"
    ],
    "wof:name":"Bahulu",
    "wof:placetype":"locality"
},
  "geometry": {"coordinates":[125.65621000000002,-9.02507],"type":"Point"}
}