{
  "type": "Feature",
  "properties": {
    "gn:admin1_code":"AN",
    "gn:admin2_code":"101.0",
    "gn:admin3_code":"10104.0",
    "gn:asciiname":"Berluli",
    "gn:country_code":"TL",
    "gn:dem":912,
    "gn:feature_class":"P",
    "gn:feature_code":"PPL",
    "gn:name":"Berluli",
    "gn:population":0,
    "gn:timezone":"Asia/Dili",
    "iso:country":"TL",
    "wof:name":"Berluli",
    "wof:placetype":"locality"
},
  "geometry": {"coordinates":[125.51833000000001,-8.98583],"type":"Point"}
}