{
  "type": "Feature",
  "properties": {
    "gn:admin1_code":"LA",
    "gn:admin2_code":"902.0",
    "gn:admin3_code":"90206.0",
    "gn:asciiname":"Narunteno",
    "gn:country_code":"TL",
    "gn:dem":160,
    "gn:feature_class":"P",
    "gn:feature_code":"PPL",
    "gn:name":"Narunteno",
    "gn:population":0,
    "gn:timezone":"Asia/Dili",
    "iso:country":"TL",
    "wof:name":"Narunteno",
    "wof:placetype":"locality"
},
  "geometry": {"coordinates":[126.91,-8.39833],"type":"Point"}
}