{
  "type": "Feature",
  "properties": {
    "gn:admin1_code":"BA",
    "gn:admin2_code":"304.0",
    "gn:admin3_code":"30406.0",
    "gn:asciiname":"Tirifalo",
    "gn:country_code":"TL",
    "gn:dem":342,
    "gn:feature_class":"P",
    "gn:feature_code":"PPL",
    "gn:name":"Tirifalo",
    "gn:population":0,
    "gn:timezone":"Asia/Dili",
    "iso:country":"TL",
    "wof:name":"Tirifalo",
    "wof:placetype":"locality"
},
  "geometry": {"coordinates":[126.71361,-8.62889],"type":"Point"}
}