{
  "type": "Feature",
  "properties": {
    "gn:admin1_code":"OE",
    "gn:admin2_code":"1204.0",
    "gn:admin3_code":"120401.0",
    "gn:asciiname":"Nuahake",
    "gn:country_code":"TL",
    "gn:dem":768,
    "gn:feature_class":"P",
    "gn:feature_code":"PPL",
    "gn:name":"Nuahake",
    "gn:population":0,
    "gn:timezone":"Asia/Dili",
    "iso:country":"TL",
    "wof:name":"Nuahake",
    "wof:placetype":"locality"
},
  "geometry": {"coordinates":[124.32138999999999,-9.46861],"type":"Point"}
}