{
  "type": "Feature",
  "properties": {
    "gn:admin1_code":"CO",
    "gn:admin2_code":"505.0",
    "gn:admin3_code":"50502.0",
    "gn:asciiname":"Suai",
    "gn:country_code":"TL",
    "gn:dem":73,
    "gn:feature_class":"P",
    "gn:feature_code":"PPLA",
    "gn:name":"Suai",
    "gn:population":21539,
    "gn:timezone":"Asia/Dili",
    "iso:country":"TL",
    "name:ceb_x_preferred":[
        "Suai"
    ],
    "name:deu_x_preferred":[
        "Suai"
    ],
    "name:fra_x_preferred":[
        "Suai"
    ],
    "name:ind_x_preferred":[
        "Suai"
    ],
    "name:ita_x_preferred":[
        "Suai"
    ],
    "name:kor_x_preferred":[
        "\uc218\uc544\uc774"
    ],
    "name:nld_x_preferred":[
        "Suai"
    ],
    "name:pol_x_preferred":[
        "Suai"
    ],
    "name:por_x_preferred":[
        "Suai"
    ],
    "name:rus_x_preferred":[
        "\u0421\u0443\u0430\u0438"
    ],
    "name:spa_x_preferred":[
        "Suai"
    ],
    "name:swe_x_preferred":[
        "Suai"
    ],
    "name:tet_x_preferred":[
        "Suai"
    ],
    "name:und_x_variant":[
        "Swai",
        "Soeai",
        "Suai"
    ],
    "name:urd_x_preferred":[
        "\u0633\u0648\u0627\u0626\u06cc"
    ],
    "name:war_x_preferred":[
        "Suai"
    ],
    "name:zho_x_preferred":[
        "\u8607\u827e"
    ],
    "wof:name":"Suai",
    "wof:placetype":"locality",
    "wof:population":21539
},
  "geometry": {"coordinates":[125.25648,-9.31286],"type":"Point"}
}