{
  "type": "Feature",
  "properties": {
    "gn:admin1_code":"LI",
    "gn:admin2_code":"801.0",
    "gn:admin3_code":"80109.0",
    "gn:asciiname":"Libaloa",
    "gn:country_code":"TL",
    "gn:dem":477,
    "gn:feature_class":"P",
    "gn:feature_code":"PPL",
    "gn:name":"Libaloa",
    "gn:population":0,
    "gn:timezone":"Asia/Dili",
    "iso:country":"TL",
    "wof:name":"Libaloa",
    "wof:placetype":"locality"
},
  "geometry": {"coordinates":[125.43778,-8.64694],"type":"Point"}
}