{
  "type": "Feature",
  "properties": {
    "gn:admin1_code":"BA",
    "gn:admin2_code":"301.0",
    "gn:admin3_code":"30107.0",
    "gn:asciiname":"Fatumaca",
    "gn:country_code":"TL",
    "gn:dem":617,
    "gn:feature_class":"P",
    "gn:feature_code":"PPL",
    "gn:name":"Fatumaca",
    "gn:population":0,
    "gn:timezone":"Asia/Dili",
    "iso:country":"TL",
    "wof:name":"Fatumaca",
    "wof:placetype":"locality"
},
  "geometry": {"coordinates":[126.38558999999999,-8.56587],"type":"Point"}
}