{
  "type": "Feature",
  "properties": {
    "gn:admin1_code":"DI",
    "gn:admin2_code":"601.0",
    "gn:admin3_code":"60107.0",
    "gn:asciiname":"Fatometa",
    "gn:country_code":"TL",
    "gn:dem":102,
    "gn:feature_class":"P",
    "gn:feature_code":"PPL",
    "gn:name":"Fatometa",
    "gn:population":0,
    "gn:timezone":"Asia/Dili",
    "iso:country":"TL",
    "wof:name":"Fatometa",
    "wof:placetype":"locality"
},
  "geometry": {"coordinates":[125.54337,-8.58439],"type":"Point"}
}