{
  "type": "Feature",
  "properties": {
    "gn:admin1_code":"LI",
    "gn:admin2_code":"803.0",
    "gn:admin3_code":"80307.0",
    "gn:asciiname":"Kaikasa",
    "gn:country_code":"TL",
    "gn:dem":546,
    "gn:feature_class":"P",
    "gn:feature_code":"PPL",
    "gn:name":"Kaikasa",
    "gn:population":0,
    "gn:timezone":"Asia/Dili",
    "iso:country":"TL",
    "wof:name":"Kaikasa",
    "wof:placetype":"locality"
},
  "geometry": {"coordinates":[125.155,-8.64611],"type":"Point"}
}