{
  "type": "Feature",
  "properties": {
    "gn:admin1_code":"ER",
    "gn:admin2_code":"705.0",
    "gn:admin3_code":"70502.0",
    "gn:asciiname":"Coliate",
    "gn:country_code":"TL",
    "gn:dem":1186,
    "gn:feature_class":"P",
    "gn:feature_code":"PPL",
    "gn:name":"Coliate",
    "gn:population":0,
    "gn:timezone":"Asia/Dili",
    "iso:country":"TL",
    "wof:name":"Coliate",
    "wof:placetype":"locality"
},
  "geometry": {"coordinates":[125.37354000000001,-8.83138],"type":"Point"}
}