{
  "type": "Feature",
  "properties": {
    "gn:admin1_code":"BA",
    "gn:admin2_code":"301.0",
    "gn:admin3_code":"30102.0",
    "gn:asciiname":"Bandadili",
    "gn:country_code":"TL",
    "gn:dem":361,
    "gn:feature_class":"P",
    "gn:feature_code":"PPL",
    "gn:name":"Bandadili",
    "gn:population":0,
    "gn:timezone":"Asia/Dili",
    "iso:country":"TL",
    "wof:name":"Bandadili",
    "wof:placetype":"locality"
},
  "geometry": {"coordinates":[126.33358,-8.49031],"type":"Point"}
}