{
  "type": "Feature",
  "properties": {
    "gn:admin1_code":"MF",
    "gn:admin2_code":"1001.0",
    "gn:admin3_code":"100101.0",
    "gn:asciiname":"Kotalala",
    "gn:country_code":"TL",
    "gn:dem":502,
    "gn:feature_class":"P",
    "gn:feature_code":"PPL",
    "gn:name":"Kotalala",
    "gn:population":0,
    "gn:timezone":"Asia/Dili",
    "iso:country":"TL",
    "wof:name":"Kotalala",
    "wof:placetype":"locality"
},
  "geometry": {"coordinates":[125.64943999999998,-8.99889],"type":"Point"}
}