{
  "type": "Feature",
  "properties": {
    "gn:admin1_code":"LI",
    "gn:admin2_code":"801.0",
    "gn:admin3_code":"80103.0",
    "gn:asciiname":"Rihiu",
    "gn:country_code":"TL",
    "gn:dem":378,
    "gn:feature_class":"P",
    "gn:feature_code":"PPL",
    "gn:name":"Rihiu",
    "gn:population":0,
    "gn:timezone":"Asia/Dili",
    "iso:country":"TL",
    "wof:name":"Rihiu",
    "wof:placetype":"locality"
},
  "geometry": {"coordinates":[125.47556000000002,-8.62056],"type":"Point"}
}