{
  "type": "Feature",
  "properties": {
    "gn:admin1_code":"VI",
    "gn:admin2_code":"1304.0",
    "gn:admin3_code":"130408.0",
    "gn:asciiname":"Biadae",
    "gn:country_code":"TL",
    "gn:dem":17,
    "gn:feature_class":"P",
    "gn:feature_code":"PPL",
    "gn:name":"Biadae",
    "gn:population":0,
    "gn:timezone":"Asia/Dili",
    "iso:country":"TL",
    "wof:name":"Biadae",
    "wof:placetype":"locality"
},
  "geometry": {"coordinates":[126.50861,-8.86639],"type":"Point"}
}