{
  "type": "Feature",
  "properties": {
    "gn:admin1_code":"LA",
    "gn:admin2_code":"902.0",
    "gn:admin3_code":"90207.0",
    "gn:asciiname":"Cirata",
    "gn:country_code":"TL",
    "gn:dem":494,
    "gn:feature_class":"P",
    "gn:feature_code":"PPL",
    "gn:name":"Cirata",
    "gn:population":0,
    "gn:timezone":"Asia/Dili",
    "iso:country":"TL",
    "wof:name":"Cirata",
    "wof:placetype":"locality"
},
  "geometry": {"coordinates":[126.88417,-8.46556],"type":"Point"}
}