{
  "type": "Feature",
  "properties": {
    "gn:admin1_code":"LA",
    "gn:admin2_code":"901.0",
    "gn:admin3_code":"90108.0",
    "gn:asciiname":"Muapitine",
    "gn:country_code":"TL",
    "gn:dem":339,
    "gn:feature_class":"P",
    "gn:feature_code":"PPL",
    "gn:name":"Muapitine",
    "gn:population":0,
    "gn:timezone":"Asia/Dili",
    "iso:country":"TL",
    "wof:name":"Muapitine",
    "wof:placetype":"locality"
},
  "geometry": {"coordinates":[127.09999999999999,-8.4975],"type":"Point"}
}