{
  "type": "Feature",
  "properties": {
    "gn:admin1_code":"OE",
    "gn:admin2_code":"1201.0",
    "gn:admin3_code":"120104.0",
    "gn:asciiname":"Misi",
    "gn:country_code":"TL",
    "gn:dem":10,
    "gn:feature_class":"P",
    "gn:feature_code":"PPL",
    "gn:name":"Misi",
    "gn:population":0,
    "gn:timezone":"Asia/Dili",
    "iso:country":"TL",
    "wof:name":"Misi",
    "wof:placetype":"locality"
},
  "geometry": {"coordinates":[124.37065,-9.20206],"type":"Point"}
}