{
  "type": "Feature",
  "properties": {
    "gn:admin1_code":"ER",
    "gn:admin2_code":"702.0",
    "gn:admin3_code":"70201.0",
    "gn:asciiname":"Loblala",
    "gn:country_code":"TL",
    "gn:dem":1429,
    "gn:feature_class":"P",
    "gn:feature_code":"PPL",
    "gn:name":"Loblala",
    "gn:population":0,
    "gn:timezone":"Asia/Dili",
    "iso:country":"TL",
    "wof:name":"Loblala",
    "wof:placetype":"locality"
},
  "geometry": {"coordinates":[125.38556,-8.75222],"type":"Point"}
}