{
  "type": "Feature",
  "properties": {
    "gn:admin1_code":"MF",
    "gn:admin2_code":"1001.0",
    "gn:admin3_code":"100101.0",
    "gn:asciiname":"Manico",
    "gn:country_code":"TL",
    "gn:dem":515,
    "gn:feature_class":"P",
    "gn:feature_code":"PPL",
    "gn:name":"Manico",
    "gn:population":0,
    "gn:timezone":"Asia/Dili",
    "iso:country":"TL",
    "wof:name":"Manico",
    "wof:placetype":"locality"
},
  "geometry": {"coordinates":[125.64610999999999,-9.00028],"type":"Point"}
}