{
  "type": "Feature",
  "properties": {
    "gn:admin1_code":"BA",
    "gn:admin2_code":"301.0",
    "gn:admin3_code":"30103.0",
    "gn:asciiname":"Diwake",
    "gn:country_code":"TL",
    "gn:dem":109,
    "gn:feature_class":"P",
    "gn:feature_code":"PPL",
    "gn:name":"Diwake",
    "gn:population":0,
    "gn:timezone":"Asia/Dili",
    "iso:country":"TL",
    "wof:name":"Diwake",
    "wof:placetype":"locality"
},
  "geometry": {"coordinates":[126.46146,-8.44883],"type":"Point"}
}