{
  "type": "Feature",
  "properties": {
    "gn:admin1_code":"CO",
    "gn:admin2_code":"505.0",
    "gn:admin3_code":"50503.0",
    "gn:asciiname":"Nularan",
    "gn:country_code":"TL",
    "gn:dem":5,
    "gn:feature_class":"P",
    "gn:feature_code":"PPL",
    "gn:name":"Nularan",
    "gn:population":0,
    "gn:timezone":"Asia/Dili",
    "iso:country":"TL",
    "wof:name":"Nularan",
    "wof:placetype":"locality"
},
  "geometry": {"coordinates":[125.27417,-9.34167],"type":"Point"}
}