{
  "type": "Feature",
  "properties": {
    "gn:admin1_code":"ER",
    "gn:admin2_code":"704.0",
    "gn:admin3_code":"70412.0",
    "gn:asciiname":"Koileki",
    "gn:country_code":"TL",
    "gn:dem":1371,
    "gn:feature_class":"P",
    "gn:feature_code":"PPL",
    "gn:name":"Koileki",
    "gn:population":0,
    "gn:timezone":"Asia/Dili",
    "iso:country":"TL",
    "wof:name":"Koileki",
    "wof:placetype":"locality"
},
  "geometry": {"coordinates":[125.42111,-8.91111],"type":"Point"}
}