{
  "type": "Feature",
  "properties": {
    "gn:admin1_code":"VI",
    "gn:admin2_code":"1305.0",
    "gn:admin3_code":"130502.0",
    "gn:asciiname":"Aisucunuc",
    "gn:country_code":"TL",
    "gn:dem":53,
    "gn:feature_class":"P",
    "gn:feature_code":"PPL",
    "gn:name":"Aisucunuc",
    "gn:population":0,
    "gn:timezone":"Asia/Dili",
    "iso:country":"TL",
    "wof:name":"Aisucunuc",
    "wof:placetype":"locality"
},
  "geometry": {"coordinates":[126.22499999999999,-8.88972],"type":"Point"}
}