{
  "type": "Feature",
  "properties": {
    "gn:admin1_code":"BO",
    "gn:admin2_code":"404.0",
    "gn:admin3_code":"40402.0",
    "gn:asciiname":"Kakamata",
    "gn:country_code":"TL",
    "gn:dem":65,
    "gn:feature_class":"P",
    "gn:feature_code":"PPL",
    "gn:name":"Kakamata",
    "gn:population":0,
    "gn:timezone":"Asia/Dili",
    "iso:country":"TL",
    "wof:name":"Kakamata",
    "wof:placetype":"locality"
},
  "geometry": {"coordinates":[125.20111,-8.77111],"type":"Point"}
}