{
  "type": "Feature",
  "properties": {
    "gn:admin1_code":"CO",
    "gn:admin2_code":"502.0",
    "gn:admin3_code":"50202.0",
    "gn:asciiname":"Bibitali",
    "gn:country_code":"TL",
    "gn:dem":1005,
    "gn:feature_class":"P",
    "gn:feature_code":"PPL",
    "gn:name":"Bibitali",
    "gn:population":0,
    "gn:timezone":"Asia/Dili",
    "iso:country":"TL",
    "wof:name":"Bibitali",
    "wof:placetype":"locality"
},
  "geometry": {"coordinates":[125.01403999999999,-9.25356],"type":"Point"}
}