{
  "type": "Feature",
  "properties": {
    "gn:admin1_code":"BA",
    "gn:admin2_code":"305.0",
    "gn:admin3_code":"30506.0",
    "gn:asciiname":"Uaiharchoo",
    "gn:country_code":"TL",
    "gn:dem":757,
    "gn:feature_class":"P",
    "gn:feature_code":"PPL",
    "gn:name":"Uaiharchoo",
    "gn:population":0,
    "gn:timezone":"Asia/Dili",
    "iso:country":"TL",
    "wof:name":"Uaiharchoo",
    "wof:placetype":"locality"
},
  "geometry": {"coordinates":[126.33556000000002,-8.56722],"type":"Point"}
}