{
  "type": "Feature",
  "properties": {
    "gn:admin1_code":"OE",
    "gn:admin2_code":"1201.0",
    "gn:admin3_code":"120101.0",
    "gn:asciiname":"Fatuke",
    "gn:country_code":"TL",
    "gn:dem":13,
    "gn:feature_class":"P",
    "gn:feature_code":"PPL",
    "gn:name":"Fatuke",
    "gn:population":0,
    "gn:timezone":"Asia/Dili",
    "iso:country":"TL",
    "wof:name":"Fatuke",
    "wof:placetype":"locality"
},
  "geometry": {"coordinates":[124.46299,-9.17907],"type":"Point"}
}