{
  "type": "Feature",
  "properties": {
    "gn:admin1_code":"DI",
    "gn:admin2_code":"601.0",
    "gn:admin3_code":"60101.0",
    "gn:asciiname":"Nahaek",
    "gn:country_code":"TL",
    "gn:dem":425,
    "gn:feature_class":"P",
    "gn:feature_code":"PPL",
    "gn:name":"Nahaek",
    "gn:population":0,
    "gn:timezone":"Asia/Dili",
    "iso:country":"TL",
    "wof:name":"Nahaek",
    "wof:placetype":"locality"
},
  "geometry": {"coordinates":[125.58056000000001,-8.59111],"type":"Point"}
}