{
  "type": "Feature",
  "properties": {
    "gn:admin1_code":"ER",
    "gn:admin2_code":"703.0",
    "gn:admin3_code":"70307.0",
    "gn:asciiname":"Kaibui",
    "gn:country_code":"TL",
    "gn:dem":1195,
    "gn:feature_class":"P",
    "gn:feature_code":"PPL",
    "gn:name":"Kaibui",
    "gn:population":0,
    "gn:timezone":"Asia/Dili",
    "iso:country":"TL",
    "wof:name":"Kaibui",
    "wof:placetype":"locality"
},
  "geometry": {"coordinates":[125.43944,-8.78278],"type":"Point"}
}