{
  "type": "Feature",
  "properties": {
    "gn:admin1_code":"CO",
    "gn:admin2_code":"507.0",
    "gn:admin3_code":"50708.0",
    "gn:asciiname":"Baordaikun",
    "gn:country_code":"TL",
    "gn:dem":46,
    "gn:feature_class":"P",
    "gn:feature_code":"PPL",
    "gn:name":"Baordaikun",
    "gn:population":0,
    "gn:timezone":"Asia/Dili",
    "iso:country":"TL",
    "wof:name":"Baordaikun",
    "wof:placetype":"locality"
},
  "geometry": {"coordinates":[125.41239,-9.20013],"type":"Point"}
}