{
  "type": "Feature",
  "properties": {
    "gn:admin1_code":"LI",
    "gn:admin2_code":"802.0",
    "gn:admin3_code":"80201.0",
    "gn:asciiname":"Leopa",
    "gn:country_code":"TL",
    "gn:dem":8,
    "gn:feature_class":"P",
    "gn:feature_code":"PPL",
    "gn:name":"Leopa",
    "gn:population":0,
    "gn:timezone":"Asia/Dili",
    "iso:country":"TL",
    "wof:name":"Leopa",
    "wof:placetype":"locality"
},
  "geometry": {"coordinates":[125.32528000000001,-8.59167],"type":"Point"}
}