{
  "type": "Feature",
  "properties": {
    "gn:admin1_code":"LA",
    "gn:admin2_code":"901.0",
    "gn:admin3_code":"90105.0",
    "gn:asciiname":"Cacaven Lama",
    "gn:country_code":"TL",
    "gn:dem":356,
    "gn:feature_class":"P",
    "gn:feature_code":"PPL",
    "gn:name":"Cacaven Lama",
    "gn:population":0,
    "gn:timezone":"Asia/Dili",
    "iso:country":"TL",
    "wof:name":"Cacaven Lama",
    "wof:placetype":"locality"
},
  "geometry": {"coordinates":[126.90139000000001,-8.54778],"type":"Point"}
}