{
  "type": "Feature",
  "properties": {
    "gn:admin1_code":"BA",
    "gn:admin2_code":"304.0",
    "gn:admin3_code":"30404.0",
    "gn:asciiname":"Afalari",
    "gn:country_code":"TL",
    "gn:dem":845,
    "gn:feature_class":"P",
    "gn:feature_code":"PPL",
    "gn:name":"Afalari",
    "gn:population":0,
    "gn:timezone":"Asia/Dili",
    "iso:country":"TL",
    "wof:name":"Afalari",
    "wof:placetype":"locality"
},
  "geometry": {"coordinates":[126.64221999999999,-8.63056],"type":"Point"}
}