{
  "type": "Feature",
  "properties": {
    "gn:admin1_code":"AN",
    "gn:admin2_code":"104.0",
    "gn:admin3_code":"10401.0",
    "gn:asciiname":"Hutseo 1",
    "gn:country_code":"TL",
    "gn:dem":422,
    "gn:feature_class":"P",
    "gn:feature_code":"PPL",
    "gn:name":"Hutseo 1",
    "gn:population":0,
    "gn:timezone":"Asia/Dili",
    "iso:country":"TL",
    "wof:name":"Hutseo 1",
    "wof:placetype":"locality"
},
  "geometry": {"coordinates":[125.58667,-9.13694],"type":"Point"}
}