{
  "type": "Feature",
  "properties": {
    "gn:admin1_code":"VI",
    "gn:admin2_code":"1301.0",
    "gn:admin3_code":"130106.0",
    "gn:asciiname":"Lauaba",
    "gn:country_code":"TL",
    "gn:dem":207,
    "gn:feature_class":"P",
    "gn:feature_code":"PPL",
    "gn:name":"Lauaba",
    "gn:population":0,
    "gn:timezone":"Asia/Dili",
    "iso:country":"TL",
    "wof:name":"Lauaba",
    "wof:placetype":"locality"
},
  "geometry": {"coordinates":[126.69194,-8.65417],"type":"Point"}
}