{
  "type": "Feature",
  "properties": {
    "gn:admin1_code":"ER",
    "gn:admin2_code":"701.0",
    "gn:admin3_code":"70105.0",
    "gn:asciiname":"Railakopu",
    "gn:country_code":"TL",
    "gn:dem":969,
    "gn:feature_class":"P",
    "gn:feature_code":"PPL",
    "gn:name":"Railakopu",
    "gn:population":0,
    "gn:timezone":"Asia/Dili",
    "iso:country":"TL",
    "wof:name":"Railakopu",
    "wof:placetype":"locality"
},
  "geometry": {"coordinates":[125.47333,-8.67833],"type":"Point"}
}