{
  "type": "Feature",
  "properties": {
    "gn:admin1_code":"BO",
    "gn:admin2_code":"402.0",
    "gn:admin3_code":"40204.0",
    "gn:asciiname":"Maumela",
    "gn:country_code":"TL",
    "gn:dem":83,
    "gn:feature_class":"P",
    "gn:feature_code":"PPL",
    "gn:name":"Maumela",
    "gn:population":0,
    "gn:timezone":"Asia/Dili",
    "iso:country":"TL",
    "wof:name":"Maumela",
    "wof:placetype":"locality"
},
  "geometry": {"coordinates":[125.21333,-8.86889],"type":"Point"}
}