{
  "type": "Feature",
  "properties": {
    "gn:admin1_code":"ER",
    "gn:admin2_code":"705.0",
    "gn:admin3_code":"70501.0",
    "gn:asciiname":"Leodato",
    "gn:country_code":"TL",
    "gn:dem":1027,
    "gn:feature_class":"P",
    "gn:feature_code":"PPL",
    "gn:name":"Leodato",
    "gn:population":0,
    "gn:timezone":"Asia/Dili",
    "iso:country":"TL",
    "wof:name":"Leodato",
    "wof:placetype":"locality"
},
  "geometry": {"coordinates":[125.38443999999998,-8.85694],"type":"Point"}
}