{
  "type": "Feature",
  "properties": {
    "gn:admin1_code":"LA",
    "gn:admin2_code":"901.0",
    "gn:admin3_code":"90105.0",
    "gn:asciiname":"Luturula",
    "gn:country_code":"TL",
    "gn:dem":432,
    "gn:feature_class":"P",
    "gn:feature_code":"PPL",
    "gn:name":"Luturula",
    "gn:population":0,
    "gn:timezone":"Asia/Dili",
    "iso:country":"TL",
    "wof:name":"Luturula",
    "wof:placetype":"locality"
},
  "geometry": {"coordinates":[126.9175,-8.53278],"type":"Point"}
}