{
  "type": "Feature",
  "properties": {
    "gn:admin1_code":"MT",
    "gn:admin2_code":"1105.0",
    "gn:admin3_code":"110505.0",
    "gn:asciiname":"Dambohum",
    "gn:country_code":"TL",
    "gn:dem":728,
    "gn:feature_class":"P",
    "gn:feature_code":"PPL",
    "gn:name":"Dambohum",
    "gn:population":0,
    "gn:timezone":"Asia/Dili",
    "iso:country":"TL",
    "wof:name":"Dambohum",
    "wof:placetype":"locality"
},
  "geometry": {"coordinates":[125.96805999999999,-8.91389],"type":"Point"}
}