{
  "type": "Feature",
  "properties": {
    "gn:admin1_code":"BA",
    "gn:admin2_code":"306.0",
    "gn:admin3_code":"30606.0",
    "gn:asciiname":"Betonau",
    "gn:country_code":"TL",
    "gn:dem":644,
    "gn:feature_class":"P",
    "gn:feature_code":"PPL",
    "gn:name":"Betonau",
    "gn:population":0,
    "gn:timezone":"Asia/Dili",
    "iso:country":"TL",
    "wof:name":"Betonau",
    "wof:placetype":"locality"
},
  "geometry": {"coordinates":[126.38472,-8.59611],"type":"Point"}
}