{
  "type": "Feature",
  "properties": {
    "gn:admin1_code":"VI",
    "gn:admin2_code":"1303.0",
    "gn:admin3_code":"130306.0",
    "gn:asciiname":"Ateuaissi",
    "gn:country_code":"TL",
    "gn:dem":473,
    "gn:feature_class":"P",
    "gn:feature_code":"PPL",
    "gn:name":"Ateuaissi",
    "gn:population":0,
    "gn:timezone":"Asia/Dili",
    "iso:country":"TL",
    "wof:name":"Ateuaissi",
    "wof:placetype":"locality"
},
  "geometry": {"coordinates":[126.51528,-8.68111],"type":"Point"}
}