{
  "type": "Feature",
  "properties": {
    "gn:admin1_code":"ER",
    "gn:admin2_code":"705.0",
    "gn:admin3_code":"70508.0",
    "gn:asciiname":"Simohei",
    "gn:country_code":"TL",
    "gn:dem":685,
    "gn:feature_class":"P",
    "gn:feature_code":"PPL",
    "gn:name":"Simohei",
    "gn:population":0,
    "gn:timezone":"Asia/Dili",
    "iso:country":"TL",
    "wof:name":"Simohei",
    "wof:placetype":"locality"
},
  "geometry": {"coordinates":[125.32832999999999,-8.81694],"type":"Point"}
}