{
  "type": "Feature",
  "properties": {
    "gn:admin1_code":"LI",
    "gn:admin2_code":"802.0",
    "gn:admin3_code":"80206.0",
    "gn:asciiname":"Cirilelo",
    "gn:country_code":"TL",
    "gn:dem":541,
    "gn:feature_class":"P",
    "gn:feature_code":"PPL",
    "gn:name":"Cirilelo",
    "gn:population":0,
    "gn:timezone":"Asia/Dili",
    "iso:country":"TL",
    "wof:name":"Cirilelo",
    "wof:placetype":"locality"
},
  "geometry": {"coordinates":[125.33028,-8.68917],"type":"Point"}
}