{
  "type": "Feature",
  "properties": {
    "gn:admin1_code":"DI",
    "gn:admin2_code":"603.0",
    "gn:admin3_code":"60302.0",
    "gn:asciiname":"Priramatan",
    "gn:country_code":"TL",
    "gn:dem":7,
    "gn:feature_class":"P",
    "gn:feature_code":"PPL",
    "gn:name":"Priramatan",
    "gn:population":0,
    "gn:timezone":"Asia/Dili",
    "iso:country":"TL",
    "wof:name":"Priramatan",
    "wof:placetype":"locality"
},
  "geometry": {"coordinates":[125.75111,-8.53056],"type":"Point"}
}