{
  "type": "Feature",
  "properties": {
    "gn:admin1_code":"BO",
    "gn:admin2_code":"404.0",
    "gn:admin3_code":"40404.0",
    "gn:asciiname":"Hataz",
    "gn:country_code":"TL",
    "gn:dem":74,
    "gn:feature_class":"P",
    "gn:feature_code":"PPL",
    "gn:name":"Hataz",
    "gn:population":0,
    "gn:timezone":"Asia/Dili",
    "iso:country":"TL",
    "name:fra_x_preferred":[
        "Hataz"
    ],
    "wof:name":"Hataz",
    "wof:placetype":"locality"
},
  "geometry": {"coordinates":[125.18000000000001,-8.87278],"type":"Point"}
}