{
  "type": "Feature",
  "properties": {
    "gn:admin1_code":"CO",
    "gn:admin2_code":"506.0",
    "gn:admin3_code":"50601.0",
    "gn:asciiname":"Baer",
    "gn:country_code":"TL",
    "gn:dem":210,
    "gn:feature_class":"P",
    "gn:feature_code":"PPL",
    "gn:name":"Baer",
    "gn:population":0,
    "gn:timezone":"Asia/Dili",
    "iso:country":"TL",
    "name:deu_x_preferred":[
        "Baer"
    ],
    "name:fin_x_preferred":[
        "Baer"
    ],
    "wof:name":"Baer",
    "wof:placetype":"locality"
},
  "geometry": {"coordinates":[125.092,-9.30767],"type":"Point"}
}