{
  "type": "Feature",
  "properties": {
    "gn:admin1_code":"VI",
    "gn:admin2_code":"1302.0",
    "gn:admin3_code":"130208.0",
    "gn:asciiname":"Dalirisi",
    "gn:country_code":"TL",
    "gn:dem":571,
    "gn:feature_class":"P",
    "gn:feature_code":"PPL",
    "gn:name":"Dalirisi",
    "gn:population":0,
    "gn:timezone":"Asia/Dili",
    "iso:country":"TL",
    "wof:name":"Dalirisi",
    "wof:placetype":"locality"
},
  "geometry": {"coordinates":[126.43611,-8.73444],"type":"Point"}
}