{
  "type": "Feature",
  "properties": {
    "gn:admin1_code":"LA",
    "gn:admin2_code":"901.0",
    "gn:admin3_code":"90102.0",
    "gn:asciiname":"Lore II",
    "gn:country_code":"TL",
    "gn:dem":396,
    "gn:feature_class":"P",
    "gn:feature_code":"PPL",
    "gn:name":"Lore II",
    "gn:population":0,
    "gn:timezone":"Asia/Dili",
    "iso:country":"TL",
    "wof:name":"Lore II",
    "wof:placetype":"locality"
},
  "geometry": {"coordinates":[126.98694,-8.57028],"type":"Point"}
}