{
  "type": "Feature",
  "properties": {
    "gn:admin1_code":"AL",
    "gn:admin2_code":"201.0",
    "gn:admin3_code":"20103.0",
    "gn:asciiname":"Sidole",
    "gn:country_code":"TL",
    "gn:dem":949,
    "gn:feature_class":"P",
    "gn:feature_code":"PPL",
    "gn:name":"Sidole",
    "gn:population":0,
    "gn:timezone":"Asia/Dili",
    "iso:country":"TL",
    "wof:name":"Sidole",
    "wof:placetype":"locality"
},
  "geometry": {"coordinates":[125.58772999999999,-8.72071],"type":"Point"}
}