{
  "type": "Feature",
  "properties": {
    "gn:admin1_code":"LI",
    "gn:admin2_code":"801.0",
    "gn:admin3_code":"80103.0",
    "gn:asciiname":"Tibar",
    "gn:country_code":"TL",
    "gn:dem":5,
    "gn:feature_class":"P",
    "gn:feature_code":"PPL",
    "gn:name":"Tibar",
    "gn:population":0,
    "gn:timezone":"Asia/Dili",
    "iso:country":"TL",
    "name:und_x_variant":[
        "Nova Alg\u00e9s",
        "Tibar"
    ],
    "wof:name":"Tibar",
    "wof:placetype":"locality"
},
  "geometry": {"coordinates":[125.48972000000001,-8.56944],"type":"Point"}
}