{
  "type": "Feature",
  "properties": {
    "gn:admin1_code":"LI",
    "gn:admin2_code":"802.0",
    "gn:admin3_code":"80201.0",
    "gn:asciiname":"Nunturi",
    "gn:country_code":"TL",
    "gn:dem":1012,
    "gn:feature_class":"P",
    "gn:feature_code":"PPL",
    "gn:name":"Nunturi",
    "gn:population":0,
    "gn:timezone":"Asia/Dili",
    "iso:country":"TL",
    "wof:name":"Nunturi",
    "wof:placetype":"locality"
},
  "geometry": {"coordinates":[125.34222,-8.64722],"type":"Point"}
}