{
  "type": "Feature",
  "properties": {
    "gn:admin1_code":"DI",
    "gn:admin2_code":"602.0",
    "gn:admin3_code":"60206.0",
    "gn:asciiname":"Gricenfor",
    "gn:country_code":"TL",
    "gn:dem":4,
    "gn:feature_class":"P",
    "gn:feature_code":"PPL",
    "gn:name":"Gricenfor",
    "gn:population":0,
    "gn:timezone":"Asia/Dili",
    "iso:country":"TL",
    "wof:name":"Gricenfor",
    "wof:placetype":"locality"
},
  "geometry": {"coordinates":[125.58395,-8.55344],"type":"Point"}
}