{
  "type": "Feature",
  "properties": {
    "gn:admin1_code":"BA",
    "gn:admin2_code":"302.0",
    "gn:admin3_code":"30204.0",
    "gn:asciiname":"Loilaku",
    "gn:country_code":"TL",
    "gn:dem":512,
    "gn:feature_class":"P",
    "gn:feature_code":"PPL",
    "gn:name":"Loilaku",
    "gn:population":0,
    "gn:timezone":"Asia/Dili",
    "iso:country":"TL",
    "wof:name":"Loilaku",
    "wof:placetype":"locality"
},
  "geometry": {"coordinates":[126.66186999999999,-8.48503],"type":"Point"}
}