{
  "type": "Feature",
  "properties": {
    "iso:country":"TL",
    "name:ara_x_preferred":[
        "\u0623\u064a\u0646\u0627\u0631\u0648"
    ],
    "name:bel_x_preferred":[
        "\u0413\u043e\u0440\u0430\u0434 \u0410\u0439\u043d\u0430\u0440\u0443"
    ],
    "name:ben_x_preferred":[
        "\u0986\u0987\u09a8\u09be\u09b0\u09c1"
    ],
    "name:ceb_x_preferred":[
        "Ainaro"
    ],
    "name:dan_x_preferred":[
        "Ainaro"
    ],
    "name:deu_x_preferred":[
        "Ainaro"
    ],
    "name:ell_x_preferred":[
        "\u0391\u03ca\u03bd\u03ac\u03c1\u03bf"
    ],
    "name:eng_x_preferred":[
        "Ainaro"
    ],
    "name:est_x_preferred":[
        "Ainaro"
    ],
    "name:fas_x_preferred":[
        "\u0627\u06cc\u0646\u0627\u0631\u0648"
    ],
    "name:fin_x_preferred":[
        "Ainaro"
    ],
    "name:fra_x_preferred":[
        "Ainaro"
    ],
    "name:guj_x_preferred":[
        "\u0a8f\u0aa8\u0abe\u0ab0\u0acb"
    ],
    "name:heb_x_preferred":[
        "\u05d0\u05d9\u05d9\u05e0\u05e8\u05d5"
    ],
    "name:hin_x_preferred":[
        "\u0906\u0907\u0928\u093e\u0930\u094b"
    ],
    "name:ind_x_preferred":[
        "Ainaro"
    ],
    "name:ita_x_preferred":[
        "Ainaro"
    ],
    "name:jpn_x_preferred":[
        "\u30a2\u30a4\u30ca\u30ed"
    ],
    "name:kan_x_preferred":[
        "\u0c90\u0ca8\u0cbe\u0cb0\u0cca"
    ],
    "name:kor_x_preferred":[
        "\uc544\uc774\ub098\ub8e8"
    ],
    "name:lav_x_preferred":[
        "Ainaro"
    ],
    "name:lit_x_preferred":[
        "Ainaras"
    ],
    "name:mar_x_preferred":[
        "\u0910\u0928\u093e\u0930\u094b"
    ],
    "name:msa_x_preferred":[
        "Ainaro"
    ],
    "name:nld_x_preferred":[
        "Ainaro"
    ],
    "name:nob_x_preferred":[
        "Ainora"
    ],
    "name:pol_x_preferred":[
        "Ainaro"
    ],
    "name:por_x_preferred":[
        "Ainaro"
    ],
    "name:rus_x_preferred":[
        "\u0410\u0439\u043d\u0430\u0440\u0443"
    ],
    "name:sin_x_preferred":[
        "\u0d85\u0dba\u0dd2\u0db1\u0dcf\u0dbb\u0ddd"
    ],
    "name:swe_x_preferred":[
        "Ainaro"
    ],
    "name:tam_x_preferred":[
        "\u0b90\u0ba8\u0bbe\u0bb0\u0bcb"
    ],
    "name:tel_x_preferred":[
        "\u0c05\u0c2f\u0c3f\u0c28\u0c3e\u0c30\u0c4b"
    ],
    "name:tet_x_preferred":[
        "Ainaru"
    ],
    "name:tha_x_preferred":[
        "\u0e44\u0e2d\u0e19\u0e32\u0e42\u0e23"
    ],
    "name:tur_x_preferred":[
        "Ainaro"
    ],
    "name:ukr_x_preferred":[
        "\u0410\u0439\u043d\u0430\u0440\u0443"
    ],
    "name:urd_x_preferred":[
        "\u0622\u0626\u0646\u0627\u0631\u0648"
    ],
    "name:vie_x_preferred":[
        "Ainaro"
    ],
    "name:war_x_preferred":[
        "Ainaro"
    ],
    "name:zho_x_preferred":[
        "\u963f\u4f0a\u7d0d\u7f85"
    ],
    "qs:gn_pop":0,
    "qs:name":"Ainaro",
    "qs:name_adm0":"East Timor",
    "qs:name_adm1":"Ainaro",
    "qs:photos":33,
    "qs:photos_1k":7,
    "qs:photos_9k":1,
    "qs:photos_9r":2,
    "qs:photos_all":33,
    "qs:photos_sr":2,
    "qs:placetype":"Town",
    "qs:pop_sr":"0",
    "qs:woe_adm0":23424968,
    "wd:wordcount":173,
    "wof:name":"Ainaro",
    "wof:placetype":"locality"
},
  "geometry": {"coordinates":[125.519485,-8.986366],"type":"Point"}
}