{
  "type": "Feature",
  "properties": {
    "gn:admin1_code":"BA",
    "gn:admin2_code":"301.0",
    "gn:admin3_code":"30110.0",
    "gn:asciiname":"Umarama",
    "gn:country_code":"TL",
    "gn:dem":7,
    "gn:feature_class":"P",
    "gn:feature_code":"PPL",
    "gn:name":"Umarama",
    "gn:population":0,
    "gn:timezone":"Asia/Dili",
    "iso:country":"TL",
    "wof:name":"Umarama",
    "wof:placetype":"locality"
},
  "geometry": {"coordinates":[126.55049,-8.48274],"type":"Point"}
}