{
  "type": "Feature",
  "properties": {
    "gn:admin1_code":"VI",
    "gn:admin2_code":"1305.0",
    "gn:admin3_code":"130501.0",
    "gn:asciiname":"Aidaklaran",
    "gn:country_code":"TL",
    "gn:dem":106,
    "gn:feature_class":"P",
    "gn:feature_code":"PPL",
    "gn:name":"Aidaklaran",
    "gn:population":0,
    "gn:timezone":"Asia/Dili",
    "iso:country":"TL",
    "wof:name":"Aidaklaran",
    "wof:placetype":"locality"
},
  "geometry": {"coordinates":[126.2075,-8.83444],"type":"Point"}
}