{
  "type": "Feature",
  "properties": {
    "gn:admin1_code":"AN",
    "gn:admin2_code":"103.0",
    "gn:admin3_code":"10307.0",
    "gn:asciiname":"Kartolo",
    "gn:country_code":"TL",
    "gn:dem":1704,
    "gn:feature_class":"P",
    "gn:feature_code":"PPL",
    "gn:name":"Kartolo",
    "gn:population":0,
    "gn:timezone":"Asia/Dili",
    "iso:country":"TL",
    "wof:name":"Kartolo",
    "wof:placetype":"locality"
},
  "geometry": {"coordinates":[125.56944,-8.8675],"type":"Point"}
}