{
  "type": "Feature",
  "properties": {
    "gn:admin1_code":"OE",
    "gn:admin2_code":"1201.0",
    "gn:admin3_code":"120105.0",
    "gn:asciiname":"Ulas",
    "gn:country_code":"TL",
    "gn:dem":200,
    "gn:feature_class":"P",
    "gn:feature_code":"PPL",
    "gn:name":"Ulas",
    "gn:population":0,
    "gn:timezone":"Asia/Dili",
    "iso:country":"TL",
    "wof:name":"Ulas",
    "wof:placetype":"locality"
},
  "geometry": {"coordinates":[124.30500000000001,-9.26389],"type":"Point"}
}