{
  "type": "Feature",
  "properties": {
    "gn:admin1_code":"MT",
    "gn:admin2_code":"1106.0",
    "gn:admin3_code":"110602.0",
    "gn:asciiname":"Lauado",
    "gn:country_code":"TL",
    "gn:dem":1287,
    "gn:feature_class":"P",
    "gn:feature_code":"PPL",
    "gn:name":"Lauado",
    "gn:population":0,
    "gn:timezone":"Asia/Dili",
    "iso:country":"TL",
    "wof:name":"Lauado",
    "wof:placetype":"locality"
},
  "geometry": {"coordinates":[125.90000000000001,-8.75],"type":"Point"}
}