{
  "type": "Feature",
  "properties": {
    "gn:admin1_code":"BO",
    "gn:admin2_code":"403.0",
    "gn:admin3_code":"40302.0",
    "gn:asciiname":"Remian",
    "gn:country_code":"TL",
    "gn:dem":426,
    "gn:feature_class":"P",
    "gn:feature_code":"PPL",
    "gn:name":"Remian",
    "gn:population":0,
    "gn:timezone":"Asia/Dili",
    "iso:country":"TL",
    "wof:name":"Remian",
    "wof:placetype":"locality"
},
  "geometry": {"coordinates":[125.05722,-9.01972],"type":"Point"}
}