{
  "type": "Feature",
  "properties": {
    "gn:admin1_code":"AL",
    "gn:admin2_code":"203.0",
    "gn:admin3_code":"20302.0",
    "gn:asciiname":"Samalete",
    "gn:country_code":"TL",
    "gn:dem":832,
    "gn:feature_class":"P",
    "gn:feature_code":"PPL",
    "gn:name":"Samalete",
    "gn:population":0,
    "gn:timezone":"Asia/Dili",
    "iso:country":"TL",
    "wof:name":"Samalete",
    "wof:placetype":"locality"
},
  "geometry": {"coordinates":[125.71738000000001,-8.62052],"type":"Point"}
}