{
  "type": "Feature",
  "properties": {
    "gn:admin1_code":"AL",
    "gn:admin2_code":"203.0",
    "gn:admin3_code":"20308.0",
    "gn:asciiname":"Mautoba",
    "gn:country_code":"TL",
    "gn:dem":1308,
    "gn:feature_class":"P",
    "gn:feature_code":"PPL",
    "gn:name":"Mautoba",
    "gn:population":0,
    "gn:timezone":"Asia/Dili",
    "iso:country":"TL",
    "wof:name":"Mautoba",
    "wof:placetype":"locality"
},
  "geometry": {"coordinates":[125.64306000000001,-8.66567],"type":"Point"}
}