{
  "type": "Feature",
  "properties": {
    "gn:admin1_code":"ER",
    "gn:admin2_code":"705.0",
    "gn:admin3_code":"70513.0",
    "gn:asciiname":"Matanova",
    "gn:country_code":"TL",
    "gn:dem":951,
    "gn:feature_class":"P",
    "gn:feature_code":"PPL",
    "gn:name":"Matanova",
    "gn:population":0,
    "gn:timezone":"Asia/Dili",
    "iso:country":"TL",
    "wof:name":"Matanova",
    "wof:placetype":"locality"
},
  "geometry": {"coordinates":[125.32111,-8.73806],"type":"Point"}
}